Workbook
Name AFNORX44101: Classification!$L$1:$L$6
Name Arrant: [1]Sheet2Form2!$B$2:$B$12
Name Arrant: [2]Sheet2Form2!$B$2:$B$12
Name Arrant: Classification!$B$2:$B$12
Name Arrant: [3]Sheet2Form2!$B$2:$B$12
Name BS_5295: Classification!$J$1:$J$7
Name Class_Air_Changes: 'Class Air Changes'!$D$5:$F$75
Name EUGMP: Classification!$G$1:$G$5
Name FDA: Classification!$D$1:$D$7
Name GERMANY_VD: Classification!$K$1:$K$9
Name GMP: Classification!$E$1:$E$5
Name ISO_14644: Classification!$C1:$C10
Name JIS_B_9920: Classification!$F$1:$F$10
Name NC__Non_Classified: Classification!$M$1:$M$9
Name NC_Non_Classified: Classification!$M$1:$M$9
Name Standards: Table1[#All]
Name TGA: Classification!$I$1:$I$7
Name WHO: Classification!$H$1:$H$8

Sheet Class Air Changes
C5: STANDARDS | D5: CLASSIFICATION | E5: NO.AIR CH/HR | G5: Term. Filter Coverage | K5: Standard/Class | L5: ACH Range | M5: Notes
C6: ISO 14644-4 | D6: ISO 9 | E6: 5 | F6: 15 | G6: 0.05 | H6: 0.15 | K6: ISO 14644-1 Class 1 | L6: 500–750 | M6: Ultra-clean (semiconductors)
C7: ISO 14644-4 | D7: ISO 8 | E7: 20 | F7: 60 | G7: 0.05 | H7: 0.15 | K7: ISO 14644-1 Class 2–3 | L7: 500–750
C8: ISO 14644-4 | D8: ISO 7 | E8: 60 | F8: 150 | G8: 0.15 | H8: 0.25 | K8: ISO 14644-1 Class 4 | L8: 400–750
C9: ISO 14644-4 | D9: ISO 6 | E9: 150 | F9: 240 | G9: 0.25 | H9: 0.4 | K9: ISO 14644-1 Class 5 | L9: 240–600 | M9: Sterile manufacturing
C10: ISO 14644-4 | D10: ISO 5 | E10: 240 | F10: 500 | G10: 0.35 | H10: 0.7 | K10: ISO 14644-1 Class 6 | L10: 150–240
C11: ISO 14644-4 | D11: ISO 4 | E11: 300 | F11: 600 | G11: 0.5 | H11: 0.9 | K11: ISO 14644-1 Class 7 | L11: 60–150
C12: ISO 14644-4 | D12: ISO 3 | E12: 400 | F12: 750 | G12: 0.6 | H12: 1 | K12: ISO 14644-1 Class 8 | L12: 10–25
C13: ISO 14644-4 | D13: ISO 2 | E13: 500 | F13: 750 | G13: 0.8 | H13: 1 | K13: ISO 14698 | L13: 20–40 | M13: Biocontamination control
C14: ISO 14644-4 | D14: ISO 1 | E14: 500 | F14: 750 | G14: 0.8 | H14: 1 | K14: BS 5295 Class 1–4 | L14: 240–600
C15: FDA 209E | D15: Class100K | E15: 12 | F15: 25 | K15: AFNOR NF S 90-351 | L15: 20–240 | M15: French standard
C16: FDA 209E | D16: Class10K | E16: 30 | F16: 60 | K16: TGA (Australia) | L16: 240–600 | M16: Based on ISO/GMP
C17: FDA 209E | D17: Class1K | E17: 80 | F17: 130 | K17: WHO GMP Grades A–D | L17: 20–240 | M17: A–D grades
C18: FDA 209E | D18: Class 100 | E18: 150 | F18: 300 | K18: JIS B 9920 (Japan) | L18: 10–600 | M18: Similar to ISO
C19: FDA 209E | D19: Class 10 | E19: 180 | F19: 400 | K19: FDA (US) | L19: 240–600 | M19: Follows ISO/GMP
C20: FDA 209E | D20: Class 1 | E20: 240 | F20: 500 | K20: EU GMP Grades A–D | L20: 20–240 | M20: Grades A–D
C21: GMP | D21: Grade D (ISO 8 at Rest & Not Defined) | E21: 20 | F21: 40 | K21: Germany VDI 2083 | L21: 20–600 | M21: Engineering guideline
C22: GMP | D22: Grade C (ISO 7 at Rest & ISO 8 in Oper.) | E22: 60 | F22: 120
C23: GMP | D23: Grade B (ISO 5 at Rest & ISO 7 in Oper.) | E23: 120 | F23: 180
C24: GMP | D24: Grade A (ISO 5 at Rest & ISO 5 in Oper.) | E24: 180 | F24: 240
C25: JIS B 9920 | D25: JIS Class 9 | E25: 10 | F25: 20
C26: JIS B 9920 | D26: JIS Class 8 | E26: 20 | F26: 60
C27: JIS B 9920 | D27: JIS Class 7 | E27: 60 | F27: 120
C28: JIS B 9920 | D28: JIS Class 6 | E28: 120 | F28: 180
C29: JIS B 9920 | D29: JIS Class 5 | E29: 180 | F29: 240
C30: JIS B 9920 | D30: JIS Class 4 | E30: 240 | F30: 350
C31: JIS B 9920 | D31: JIS Class 3 | E31: 350 | F31: 500
C32: JIS B 9920 | D32: JIS Class 2 | E32: 400 | F32: 600
C33: JIS B 9920 | D33: JIS Class 1 | E33: 400 | F33: 600
... C37: EU GMP | D37: Grade A (ISO 5 at Rest & ISO 5 in Oper.) | E37: 180 | F37: 240
C38: TGA | D38: 3500 | E38: 15 | F38: 40
C39: TGA | D39: 350 | E39: 40 | F39: 80
C40: TGA | D40: 35 | E40: 80 | F40: 130
C41: TGA | D41: 3.5 | E41: 130 | F41: 300
C42: TGA | D42: 0.35 | E42: 180 | F42: 400
C43: TGA | D43: 0.035 | E43: 240 | F43: 500
C44: BS 5295 | D44: K | E44: 12 | F44: 25
C45: BS 5295 | D45: J | E45: 30 | F45: 80
C46: BS 5295 | D46: G or H | E46: 120 | F46: 180
C47: BS 5295 | D47: E or F | E47: 240 | F47: 350
C48: BS 5295 | D48: D | E48: 350 | F48: 600
C49: BS 5295 | D49: C | E49: 400 | F49: 600
C50: GERMANY VD | D50: 6 | E50: 20 | F50: 60
C51: GERMANY VD | D51: 5 | E51: 60 | F51: 120
C52: GERMANY VD | D52: 4 | E52: 120 | F52: 180
C53: GERMANY VD | D53: 3 | E53: 180 | F53: 240
C54: GERMANY VD | D54: 2 | E54: 240 | F54: 360
C55: GERMANY VD | D55: 1 | E55: 360 | F55: 550
C56: GERMANY VD | D56: 0 | E56: 400 | F56: 600
C57: AFNOR X44101 | D57: 4000000 | E57: 20 | F57: 50
C58: AFNOR X44101 | D58: 400000 | E58: 60 | F58: 120
C59: AFNOR X44101 | D59: 4000 | E59: 120 | F59: 240
C60: NC-Non Classified | D60: 20µ | E60: 5 | F60: 15
C61: NC-Non Classified | D61: 15µ | E61: 5 | F61: 20
C62: NC-Non Classified | D62: 10µ | E62: 10 | F62: 25
C63: NC-Non Classified | D63: 5µ | E63: 15 | F63: 25
C64: NC-Non Classified | D64: 1µ | E64: 15 | F64: 25
C65: NC-Non Classified | D65: No-Filtration | E65: 5 | F65: 10
C66: NC-Non Classified | D66: Positive Pressure | E66: 5 | F66: 10
C67: NC-Non Classified | D67: Exhaust
C68: ISO 14698 | D68: BSL - 1 | E68: 6 | F68: 12
C69: ISO 14698 | D69: BSL - 2 | E69: 10 | F69: 15
C70: ISO 14698 | D70: BSL - 3 | E70: 15 | F70: 20
C71: ISO 14698 | D71: BSL - 4 | E71: 20 | F71: 30
C72: SCHEDULE M | D72: GRADE CLASS A | E72: 80 | F72: 100
C73: SCHEDULE M | D73: GRADE CLASS B | E73: 60 | F73: 80
C74: SCHEDULE M | D74: GRADE CLASS C | E74: 40 | F74: 60
C75: SCHEDULE M | D75: GRADE CLASS D | E75: 20 | F75: 40

Sheet Sheet1
A1: STANDARDS | B1: CLASSIFICATION | C1: NO.AIR CH/HR
A2: ISO 14644-4 | B2: ISO 9 | C2: 5 | D2: 15 | E2: ="INSERT INTO tCR_metadata (standard_name, classification_name, acph_min, acph_max) VALUES ('"&A2&"', '"&B2&"', "&C2&", "&D2&");" -> INSERT INTO tCR_metadata (standard_name, classification_name, acph_min, acph_max) VALUES ('ISO 14644-4', 'ISO 9', 5, 15);
A3: ISO 14644-4 | B3: ISO 8 | C3: 20 | D3: 60 | E3: ="INSERT INTO tCR_metadata (standard_name, classification_name, acph_min, acph_max) VALUES ('"&A3&"', '"&B3&"', "&C3&", "&D3&");" -> INSERT INTO tCR_metadata (standard_name, classification_name, acph_min, acph_max) VALUES ('ISO 14644-4', 'ISO 8', 20, 60);
A4: ISO 14644-4 | B4: ISO 7 | C4: 60 | D4: 150 | E4: ="INSERT INTO tCR_metadata (standard_name, classification_name, acph_min, acph_max) VALUES ('"&A4&"', '"&B4&"', "&C4&", "&D4&");" -> INSERT INTO tCR_metadata (standard_name, classification_name, acph_min, acph_max) VALUES ('ISO 14644-4', 'ISO 7', 60, 150);
A5: ISO 14644-4 | B5: ISO 6 | C5: 150 | D5: 240 | E5: ="INSERT INTO tCR_metadata (standard_name, classification_name, acph_min, acph_max) VALUES ('"&A5&"', '"&B5&"', "&C5&", "&D5&");" -> INSERT INTO tCR_metadata (standard_name, classification_name, acph_min, acph_max) VALUES ('ISO 14644-4', 'ISO 6', 150, 240);
A6: ISO 14644-4 | B6: ISO 5 | C6: 240 | D6: 500 | E6: ="INSERT INTO tCR_metadata (standard_name, classification_name, acph_min, acph_max) VALUES ('"&A6&"', '"&B6&"', "&C6&", "&D6&");" -> INSERT INTO tCR_metadata (standard_name, classification_name, acph_min, acph_max) VALUES ('ISO 14644-4', 'ISO 5', 240, 500);
A7: ISO 14644-4 | B7: ISO 4 | C7: 300 | D7: 600 | E7: ="INSERT INTO tCR_metadata (standard_name, classification_name, acph_min, acph_max) VALUES ('"&A7&"', '"&B7&"', "&C7&", "&D7&");" -> INSERT INTO tCR_metadata (standard_name, classification_name, acph_min, acph_max) VALUES ('ISO 14644-4', 'ISO 4', 300, 600);
A8: ISO 14644-4 | B8: ISO 3 | C8: 400 | D8: 750 | E8: ="INSERT INTO tCR_metadata (standard_name, classification_name, acph_min, acph_max) VALUES ('"&A8&"', '"&B8&"', "&C8&", "&D8&");" -> INSERT INTO tCR_metadata (standard_name, classification_name, acph_min, acph_max) VALUES ('ISO 14644-4', 'ISO 3', 400, 750);
A9: ISO 14644-4 | B9: ISO 2 | C9: 500 | D9: 750 | E9: ="INSERT INTO tCR_metadata (standard_name, classification_name, acph_min, acph_max) VALUES ('"&A9&"', '"&B9&"', "&C9&", "&D9&");" -> INSERT INTO tCR_metadata (standard_name, classification_name, acph_min, acph_max) VALUES ('ISO 14644-4', 'ISO 2', 500, 750);
A10: ISO 14644-4 | B10: ISO 1 | C10: 500 | D10: 750 | E10: ="INSERT INTO tCR_metadata (standard_name, classification_name, acph_min, acph_max) VALUES ('"&A10&"', '"&B10&"', "&C10&", "&D10&");" -> INSERT INTO tCR_metadata (standard_name, classification_name, acph_min, acph_max) VALUES ('ISO 14644-4', 'ISO 1', 500, 750);
A11: FDA 209E | B11: Class100K | C11: 12 | D11: 25 | E11: ="INSERT INTO tCR_metadata (standard_name, classification_name, acph_min, acph_max) VALUES ('"&A11&"', '"&B11&"', "&C11&", "&D11&");" -> INSERT INTO tCR_metadata (standard_name, classification_name, acph_min, acph_max) VALUES ('FDA 209E', 'Class100K', 12, 25);
A12: FDA 209E | B12: Class10K | C12: 30 | D12: 60 | E12: ="INSERT INTO tCR_metadata (standard_name, classification_name, acph_min, acph_max) VALUES ('"&A12&"', '"&B12&"', "&C12&", "&D12&");" -> INSERT INTO tCR_metadata (standard_name, classification_name, acph_min, acph_max) VALUES ('FDA 209E', 'Class10K', 30, 60);
A13: FDA 209E | B13: Class1K | C13: 80 | D13: 130 | E13: ="INSERT INTO tCR_metadata (standard_name, classification_name, acph_min, acph_max) VALUES ('"&A13&"', '"&B13&"', "&C13&", "&D13&");" -> INSERT INTO tCR_metadata (standard_name, classification_name, acph_min, acph_max) VALUES ('FDA 209E', 'Class1K', 80, 130);
... A33: EU GMP | B33: Grade A (ISO 5 at Rest & ISO 5 in Oper.) | C33: 180 | D33: 240 | E33: ="INSERT INTO tCR_metadata (standard_name, classification_name, acph_min, acph_max) VALUES ('"&A33&"', '"&B33&"', "&C33&", "&D33&");" -> INSERT INTO tCR_metadata (standard_name, classification_name, acph_min, acph_max) VALUES ('EU GMP', 'Grade A (ISO 5 at Rest & ISO 5 in Oper.)', 180, 240);
A34: TGA | B34: 3500 | C34: 15 | D34: 40 | E34: ="INSERT INTO tCR_metadata (standard_name, classification_name, acph_min, acph_max) VALUES ('"&A34&"', '"&B34&"', "&C34&", "&D34&");" -> INSERT INTO tCR_metadata (standard_name, classification_name, acph_min, acph_max) VALUES ('TGA', '3500', 15, 40);
A35: TGA | B35: 350 | C35: 40 | D35: 80 | E35: ="INSERT INTO tCR_metadata (standard_name, classification_name, acph_min, acph_max) VALUES ('"&A35&"', '"&B35&"', "&C35&", "&D35&");" -> INSERT INTO tCR_metadata (standard_name, classification_name, acph_min, acph_max) VALUES ('TGA', '350', 40, 80);
A36: TGA | B36: 35 | C36: 80 | D36: 130 | E36: ="INSERT INTO tCR_metadata (standard_name, classification_name, acph_min, acph_max) VALUES ('"&A36&"', '"&B36&"', "&C36&", "&D36&");" -> INSERT INTO tCR_metadata (standard_name, classification_name, acph_min, acph_max) VALUES ('TGA', '35', 80, 130);
A37: TGA | B37: 3.5 | C37: 130 | D37: 300 | E37: ="INSERT INTO tCR_metadata (standard_name, classification_name, acph_min, acph_max) VALUES ('"&A37&"', '"&B37&"', "&C37&", "&D37&");" -> INSERT INTO tCR_metadata (standard_name, classification_name, acph_min, acph_max) VALUES ('TGA', '3.5', 130, 300);
A38: TGA | B38: 0.35 | C38: 180 | D38: 400 | E38: ="INSERT INTO tCR_metadata (standard_name, classification_name, acph_min, acph_max) VALUES ('"&A38&"', '"&B38&"', "&C38&", "&D38&");" -> INSERT INTO tCR_metadata (standard_name, classification_name, acph_min, acph_max) VALUES ('TGA', '0.35', 180, 400);
A39: TGA | B39: 0.035 | C39: 240 | D39: 500 | E39: ="INSERT INTO tCR_metadata (standard_name, classification_name, acph_min, acph_max) VALUES ('"&A39&"', '"&B39&"', "&C39&", "&D39&");" -> INSERT INTO tCR_metadata (standard_name, classification_name, acph_min, acph_max) VALUES ('TGA', '0.035', 240, 500);
A40: BS 5295 | B40: K | C40: 12 | D40: 25 | E40: ="INSERT INTO tCR_metadata (standard_name, classification_name, acph_min, acph_max) VALUES ('"&A40&"', '"&B40&"', "&C40&", "&D40&");" -> INSERT INTO tCR_metadata (standard_name, classification_name, acph_min, acph_max) VALUES ('BS 5295', 'K', 12, 25);
A41: BS 5295 | B41: J | C41: 30 | D41: 80 | E41: ="INSERT INTO tCR_metadata (standard_name, classification_name, acph_min, acph_max) VALUES ('"&A41&"', '"&B41&"', "&C41&", "&D41&");" -> INSERT INTO tCR_metadata (standard_name, classification_name, acph_min, acph_max) VALUES ('BS 5295', 'J', 30, 80);
A42: BS 5295 | B42: G or H | C42: 120 | D42: 180 | E42: ="INSERT INTO tCR_metadata (standard_name, classification_name, acph_min, acph_max) VALUES ('"&A42&"', '"&B42&"', "&C42&", "&D42&");" -> INSERT INTO tCR_metadata (standard_name, classification_name, acph_min, acph_max) VALUES ('BS 5295', 'G or H', 120, 180);
A43: BS 5295 | B43: E or F | C43: 240 | D43: 350 | E43: ="INSERT INTO tCR_metadata (standard_name, classification_name, acph_min, acph_max) VALUES ('"&A43&"', '"&B43&"', "&C43&", "&D43&");" -> INSERT INTO tCR_metadata (standard_name, classification_name, acph_min, acph_max) VALUES ('BS 5295', 'E or F', 240, 350);
A44: BS 5295 | B44: D | C44: 350 | D44: 600 | E44: ="INSERT INTO tCR_metadata (standard_name, classification_name, acph_min, acph_max) VALUES ('"&A44&"', '"&B44&"', "&C44&", "&D44&");" -> INSERT INTO tCR_metadata (standard_name, classification_name, acph_min, acph_max) VALUES ('BS 5295', 'D', 350, 600);
A45: BS 5295 | B45: C | C45: 400 | D45: 600 | E45: ="INSERT INTO tCR_metadata (standard_name, classification_name, acph_min, acph_max) VALUES ('"&A45&"', '"&B45&"', "&C45&", "&D45&");" -> INSERT INTO tCR_metadata (standard_name, classification_name, acph_min, acph_max) VALUES ('BS 5295', 'C', 400, 600);
A46: GERMANY VD | B46: 6 | C46: 20 | D46: 60 | E46: ="INSERT INTO tCR_metadata (standard_name, classification_name, acph_min, acph_max) VALUES ('"&A46&"', '"&B46&"', "&C46&", "&D46&");" -> INSERT INTO tCR_metadata (standard_name, classification_name, acph_min, acph_max) VALUES ('GERMANY VD', '6', 20, 60);
A47: GERMANY VD | B47: 5 | C47: 60 | D47: 120 | E47: ="INSERT INTO tCR_metadata (standard_name, classification_name, acph_min, acph_max) VALUES ('"&A47&"', '"&B47&"', "&C47&", "&D47&");" -> INSERT INTO tCR_metadata (standard_name, classification_name, acph_min, acph_max) VALUES ('GERMANY VD', '5', 60, 120);
A48: GERMANY VD | B48: 4 | C48: 120 | D48: 180 | E48: ="INSERT INTO tCR_metadata (standard_name, classification_name, acph_min, acph_max) VALUES ('"&A48&"', '"&B48&"', "&C48&", "&D48&");" -> INSERT INTO tCR_metadata (standard_name, classification_name, acph_min, acph_max) VALUES ('GERMANY VD', '4', 120, 180);
A49: GERMANY VD | B49: 3 | C49: 180 | D49: 240 | E49: ="INSERT INTO tCR_metadata (standard_name, classification_name, acph_min, acph_max) VALUES ('"&A49&"', '"&B49&"', "&C49&", "&D49&");" -> INSERT INTO tCR_metadata (standard_name, classification_name, acph_min, acph_max) VALUES ('GERMANY VD', '3', 180, 240);
A50: GERMANY VD | B50: 2 | C50: 240 | D50: 360 | E50: ="INSERT INTO tCR_metadata (standard_name, classification_name, acph_min, acph_max) VALUES ('"&A50&"', '"&B50&"', "&C50&", "&D50&");" -> INSERT INTO tCR_metadata (standard_name, classification_name, acph_min, acph_max) VALUES ('GERMANY VD', '2', 240, 360);
A51: GERMANY VD | B51: 1 | C51: 360 | D51: 550 | E51: ="INSERT INTO tCR_metadata (standard_name, classification_name, acph_min, acph_max) VALUES ('"&A51&"', '"&B51&"', "&C51&", "&D51&");" -> INSERT INTO tCR_metadata (standard_name, classification_name, acph_min, acph_max) VALUES ('GERMANY VD', '1', 360, 550);
A52: GERMANY VD | B52: 0 | C52: 400 | D52: 600 | E52: ="INSERT INTO tCR_metadata (standard_name, classification_name, acph_min, acph_max) VALUES ('"&A52&"', '"&B52&"', "&C52&", "&D52&");" -> INSERT INTO tCR_metadata (standard_name, classification_name, acph_min, acph_max) VALUES ('GERMANY VD', '0', 400, 600);
A53: AFNOR X44101 | B53: 4000000 | C53: 20 | D53: 50 | E53: ="INSERT INTO tCR_metadata (standard_name, classification_name, acph_min, acph_max) VALUES ('"&A53&"', '"&B53&"', "&C53&", "&D53&");" -> INSERT INTO tCR_metadata (standard_name, classification_name, acph_min, acph_max) VALUES ('AFNOR X44101', '4000000', 20, 50);
A54: AFNOR X44101 | B54: 400000 | C54: 60 | D54: 120 | E54: ="INSERT INTO tCR_metadata (standard_name, classification_name, acph_min, acph_max) VALUES ('"&A54&"', '"&B54&"', "&C54&", "&D54&");" -> INSERT INTO tCR_metadata (standard_name, classification_name, acph_min, acph_max) VALUES ('AFNOR X44101', '400000', 60, 120);
A55: AFNOR X44101 | B55: 4000 | C55: 120 | D55: 240 | E55: ="INSERT INTO tCR_metadata (standard_name, classification_name, acph_min, acph_max) VALUES ('"&A55&"', '"&B55&"', "&C55&", "&D55&");" -> INSERT INTO tCR_metadata (standard_name, classification_name, acph_min, acph_max) VALUES ('AFNOR X44101', '4000', 120, 240);
A56: NC-Non Classified | B56: 20µ | C56: 5 | D56: 15 | E56: ="INSERT INTO tCR_metadata (standard_name, classification_name, acph_min, acph_max) VALUES ('"&A56&"', '"&B56&"', "&C56&", "&D56&");" -> INSERT INTO tCR_metadata (standard_name, classification_name, acph_min, acph_max) VALUES ('NC-Non Classified', '20µ', 5, 15);
A57: NC-Non Classified | B57: 15µ | C57: 5 | D57: 20 | E57: ="INSERT INTO tCR_metadata (standard_name, classification_name, acph_min, acph_max) VALUES ('"&A57&"', '"&B57&"', "&C57&", "&D57&");" -> INSERT INTO tCR_metadata (standard_name, classification_name, acph_min, acph_max) VALUES ('NC-Non Classified', '15µ', 5, 20);
A58: NC-Non Classified | B58: 10µ | C58: 10 | D58: 25 | E58: ="INSERT INTO tCR_metadata (standard_name, classification_name, acph_min, acph_max) VALUES ('"&A58&"', '"&B58&"', "&C58&", "&D58&");" -> INSERT INTO tCR_metadata (standard_name, classification_name, acph_min, acph_max) VALUES ('NC-Non Classified', '10µ', 10, 25);
A59: NC-Non Classified | B59: 5µ | C59: 15 | D59: 25 | E59: ="INSERT INTO tCR_metadata (standard_name, classification_name, acph_min, acph_max) VALUES ('"&A59&"', '"&B59&"', "&C59&", "&D59&");" -> INSERT INTO tCR_metadata (standard_name, classification_name, acph_min, acph_max) VALUES ('NC-Non Classified', '5µ', 15, 25);
A60: NC-Non Classified | B60: 1µ | C60: 15 | D60: 25 | E60: ="INSERT INTO tCR_metadata (standard_name, classification_name, acph_min, acph_max) VALUES ('"&A60&"', '"&B60&"', "&C60&", "&D60&");" -> INSERT INTO tCR_metadata (standard_name, classification_name, acph_min, acph_max) VALUES ('NC-Non Classified', '1µ', 15, 25);
A61: NC-Non Classified | B61: No-Filtration | C61: 5 | D61: 10 | E61: ="INSERT INTO tCR_metadata (standard_name, classification_name, acph_min, acph_max) VALUES ('"&A61&"', '"&B61&"', "&C61&", "&D61&");" -> INSERT INTO tCR_metadata (standard_name, classification_name, acph_min, acph_max) VALUES ('NC-Non Classified', 'No-Filtration', 5, 10);
A62: NC-Non Classified | B62: Positive Pressure | C62: 5 | D62: 10 | E62: ="INSERT INTO tCR_metadata (standard_name, classification_name, acph_min, acph_max) VALUES ('"&A62&"', '"&B62&"', "&C62&", "&D62&");" -> INSERT INTO tCR_metadata (standard_name, classification_name, acph_min, acph_max) VALUES ('NC-Non Classified', 'Positive Pressure', 5, 10);
A63: NC-Non Classified | B63: Exhaust | C63: 0 | D63: 0 | E63: ="INSERT INTO tCR_metadata (standard_name, classification_name, acph_min, acph_max) VALUES ('"&A63&"', '"&B63&"', "&C63&", "&D63&");" -> INSERT INTO tCR_metadata (standard_name, classification_name, acph_min, acph_max) VALUES ('NC-Non Classified', 'Exhaust', 0, 0);
A64: ISO 14698 | B64: BSL - 1 | C64: 6 | D64: 12 | E64: ="INSERT INTO tCR_metadata (standard_name, classification_name, acph_min, acph_max) VALUES ('"&A64&"', '"&B64&"', "&C64&", "&D64&");" -> INSERT INTO tCR_metadata (standard_name, classification_name, acph_min, acph_max) VALUES ('ISO 14698', 'BSL - 1', 6, 12);
A65: ISO 14698 | B65: BSL - 2 | C65: 10 | D65: 15 | E65: ="INSERT INTO tCR_metadata (standard_name, classification_name, acph_min, acph_max) VALUES ('"&A65&"', '"&B65&"', "&C65&", "&D65&");" -> INSERT INTO tCR_metadata (standard_name, classification_name, acph_min, acph_max) VALUES ('ISO 14698', 'BSL - 2', 10, 15);
A66: ISO 14698 | B66: BSL - 3 | C66: 15 | D66: 20 | E66: ="INSERT INTO tCR_metadata (standard_name, classification_name, acph_min, acph_max) VALUES ('"&A66&"', '"&B66&"', "&C66&", "&D66&");" -> INSERT INTO tCR_metadata (standard_name, classification_name, acph_min, acph_max) VALUES ('ISO 14698', 'BSL - 3', 15, 20);
A67: ISO 14698 | B67: BSL - 4 | C67: 20 | D67: 30 | E67: ="INSERT INTO tCR_metadata (standard_name, classification_name, acph_min, acph_max) VALUES ('"&A67&"', '"&B67&"', "&C67&", "&D67&");" -> INSERT INTO tCR_metadata (standard_name, classification_name, acph_min, acph_max) VALUES ('ISO 14698', 'BSL - 4', 20, 30);
... A71: SCHEDULE M | B71: GRADE CLASS D | C71: 20 | D71: 40 | E71: ="INSERT INTO tCR_metadata (standard_name, classification_name, acph_min, acph_max) VALUES ('"&A71&"', '"&B71&"', "&C71&", "&D71&");" -> INSERT INTO tCR_metadata (standard_name, classification_name, acph_min, acph_max) VALUES ('SCHEDULE M', 'GRADE CLASS D', 20, 40);

Sheet Classification
A1: ids | B1: Standards | C1: ISO_14644 | D1: FDA | E1: GMP | F1: JIS_B_9920 | G1: EUGMP | H1: WHO | I1: TGA | J1: BS_5295 | K1: GERMANY_VD | L1: AFNORX44101 | M1: NC -Non Classified
A2: =IF(B2&C3&D2="","",TRIM(TEXT(B2 & C3 & D2,0))&TEXT(ROW()-1,"00000")) -> ISO_14644ISO 8Class100K00001 | B2: ISO_14644 | C2: ISO 9 | D2: Class100K | E2: Grade D (ISO 8 at Rest & Not Defined) | F2: JIS Class 9 | G2: Grade D (ISO 7 at Rest & ISO 8 in Oper.) | H2: Asia | I2: 3500 | J2: K | M2: 20µ
A3: =IF(B3&C4&D3="","",TRIM(TEXT(B3&C4&D3,0))&TEXT(ROW()-1,"00000")) -> FDAISO 7Class10K00002 | B3: FDA | C3: ISO 8 | D3: Class10K | E3: Grade C (ISO 7 at Rest & ISO 8 in Oper.) | F3: JIS Class 8 | G3: Grade C (ISO 7 at Rest & ISO 7 in Oper.) | H3: Africa | I3: 350 | J3: J | K3: 6 | L3: 4000000 | M3: 15µ
A4: =IF(B4&C5&D4="","",TRIM(TEXT(B4&C5&D4,0))&TEXT(ROW()-1,"00000")) -> GMPISO 6Class1K00003 | B4: GMP | C4: ISO 7 | D4: Class1K | E4: Grade B (ISO 5 at Rest & ISO 7 in Oper.) | F4: JIS Class 7 | G4: Grade B (ISO 5 at Rest & ISO 7 in Oper.) | H4: North America | I4: 35 | J4: G or H | K4: 5 | L4: 400000 | M4: 10µ
A5: =IF(B5&C6&D5="","",TRIM(TEXT(B5&C6&D5,0))&TEXT(ROW()-1,"00000")) -> TGAISO 5Class 10000004 | B5: TGA | C5: ISO 6 | D5: Class 100 | E5: Grade A (ISO 5 at Rest & ISO 5 in Oper.) | F5: JIS Class 6 | G5: Grade A (ISO 5 at Rest & ISO 5 in Oper.) | H5: South America | I5: 3.5 | J5: E or F | K5: 4 | L5: - | M5: 5µ
A6: =IF(B6&C7&D6="","",TRIM(TEXT(B6&C7&D6,0))&TEXT(ROW()-1,"00000")) -> JIS_B_9920ISO 4Class 1000005 | B6: JIS_B_9920 | C6: ISO 5 | D6: Class 10 | F6: JIS Class 5 | H6: Antartica | I6: 0.35 | J6: D | K6: 3 | L6: 4000 | M6: 1µ
A7: =IF(B7&C8&D7="","",TRIM(TEXT(B7&C8&D7,0))&TEXT(ROW()-1,"00000")) -> EUGMPISO 3Class 100006 | B7: EUGMP | C7: ISO 4 | D7: Class 1 | F7: JIS Class 4 | H7: Europe | I7: 0.035 | J7: C | K7: 2 | L7: - | M7: No-Filtration
A8: =IF(B8&#REF!&D8="","",TRIM(TEXT(B8&#REF!&D8,0))&TEXT(ROW()-1,"00000")) -> #REF! | B8: WHO | C8: ISO 3 | F8: JIS Class 3 | H8: Australia | K8: 1 | L8: - | M8: Positive Pressure
A9: =IF(B9&C9&D9="","",TRIM(TEXT(B9&C9&D9,0))&TEXT(ROW()-1,"00000")) -> BS_5295ISO 200008 | B9: BS_5295 | C9: ISO 2 | F9: JIS Class 2 | K9: 0 | L9: - | M9: Exhaust
A10: =IF(B10&C10&D10="","",TRIM(TEXT(B10&C10&D10,0))&TEXT(ROW()-1,"00000")) -> GERMANY_VDISO 100009 | B10: GERMANY_VD | C10: ISO 1 | F10: JIS Class 1
A11: =IF(B11&C11&D11="","",TRIM(TEXT(B11&C11&D11,0))&TEXT(ROW()-1,"00000")) -> AFNORX4410100010 | B11: AFNORX44101
A12: =IF(B12&C12&D12="","",TRIM(TEXT(B12&C12&D12,0))&TEXT(ROW()-1,"00000")) -> NC_Non_Classified00011 | B12: NC_Non_Classified
A13: =IF(B13&C13&D13="","",TRIM(TEXT(B13&C13&D13,0))&TEXT(ROW()-1,"00000"))
A14: =IF(B14&C14&D14="","",TRIM(TEXT(B14&C14&D14,0))&TEXT(ROW()-1,"00000"))
A15: =IF(B15&C15&D15="","",TRIM(TEXT(B15&C15&D15,0))&TEXT(ROW()-1,"00000"))
A16: =IF(B16&C16&D16="","",TRIM(TEXT(B16,6))&TEXT(ROW()-1,"00000"))
A17: =IF(B17&C17&D17="","",TRIM(TEXT(B17,6))&TEXT(ROW()-1,"00000"))
A18: =IF(B18&C18&D18="","",TRIM(TEXT(B18,6))&TEXT(ROW()-1,"00000")) | E18: Filtration Stages
B19: Air-conditioning System | E19: 1S | F19: 20 micron filters made out of HDPE media with one side HDPE & other side Al. expanded mesh of efficiency 90%(150 mm thick) for fresh air supply
B20: Ventilation System | E20: 1E | F20: 20 micron filters made out of HDPE media with one side HDPE & other side Al. expanded mesh of efficiency 90%(100 mm thick) for Exhaust air.
E21: 2S | F21: 10 micron filters made out of HLP media with one side HDPE & other side Al. expanded mesh of efficiency 95%(150 mm thick) for fresh air supply
A22: TGA | B22: Adelaide | E22: 2E | F22: 10 micron filters made out of HLP media with one side HDPE & other side Al. expanded mesh of efficiency 95%(150 mm thick) for Exhaust Air
E23: 3S | F23: 5 micron filters made out of SNPF media 150GSM with one side HDPE & other side Al. expanded mesh of efficiency 99%(300 mm thick) for fresh air supply
E24: 3E | F24: 5 micron filters made out of SNPF media 150GSM with one side HDPE & other side Al. expanded mesh of efficiency 99%(300 mm thick) for Exhaust Air
E25: 4S | F25: 1 micron filters made out of SNPF media 200GSM with one side HDPE & other side Al. expanded mesh of efficiency 99.9%(300 mm thick) for fresh air supply
E26: 4E | F26: 1 micron filters made out of SNPF media 200GSM with one side HDPE & other side Al. expanded mesh of efficiency 99.9%(300 mm thick) for Exhaust Air
E27: 5S | F27: 0.3 micron 95% Eff. HEPA filters made out of imported Lydall media with efficiency 95%(300 mm thick) for fresh air supply
E28: 5E | F28: 0.3 micron 95% Eff. HEPA filters made out of imported Lydall media with efficiency 95%(300 mm thick) for Exhaust Air
E29: 6S | F29: 0.3 micron 99.97% Eff. HEPA filters made out of imported Lydall media with efficiency 95%(150 mm thick) for Supply Air
E30: 6E | F30: 0.3 micron 99.97% Eff. HEPA filters made out of imported Lydall media with efficiency 95%(150 mm thick) for Exhaust Air
E31: 7S | F31: 0.1 micron 99.9995% Eff. ULPA filters made out of imported Lydall media with efficiency 95%(150 mm thick) for Supply Air
E32: 7E | F32: 0.1 micron 99.9995% Eff. ULPA filters made out of imported Lydall media with efficiency 95%(150 mm thick) for Exhaust Air
A37: ids | B37: Standards | C37: ISO_14644 | D37: FDA | E37: GMP | F37: JIS_B_9920 | G37: EUGMP | H37: WHO | I37: TGA | J37: BS_5295 | K37: GERMANY_VD | L37: AFNORX44101 | M37: NC -Non Classified
A38: =IF(B38&C39&D38="","",TRIM(TEXT(B38 & C39 & D38,0))&TEXT(ROW()-1,"00000")) -> ISO_14644ISO 8Class100K00037 | B38: ISO_14644 | C38: ISO 9 | D38: Class100K | E38: Grade D (ISO 8 at Rest & Not Defined) | F38: JIS Class 9 | G38: Grade D (ISO 7 at Rest & ISO 8 in Oper.) | H38: Asia | I38: 3500 | J38: K | M38: 20µ
A39: =IF(B39&C40&D39="","",TRIM(TEXT(B39&C40&D39,0))&TEXT(ROW()-1,"00000")) -> FDAISO 7Class10K00038 | B39: FDA | C39: ISO 8 | D39: Class10K | E39: Grade C (ISO 7 at Rest & ISO 8 in Oper.) | F39: JIS Class 8 | G39: Grade C (ISO 7 at Rest & ISO 7 in Oper.) | H39: Africa | I39: 350 | J39: J | K39: 6 | L39: 4000000 | M39: 15µ
A40: =IF(B40&C41&D40="","",TRIM(TEXT(B40&C41&D40,0))&TEXT(ROW()-1,"00000")) -> GMPISO 6Class1K00039 | B40: GMP | C40: ISO 7 | D40: Class1K | E40: Grade B (ISO 5 at Rest & ISO 7 in Oper.) | F40: JIS Class 7 | G40: Grade B (ISO 5 at Rest & ISO 7 in Oper.) | H40: North America | I40: 35 | J40: G or H | K40: 5 | L40: 400000 | M40: 10µ
A41: =IF(B41&C42&D41="","",TRIM(TEXT(B41&C42&D41,0))&TEXT(ROW()-1,"00000")) -> TGAISO 5Class 10000040 | B41: TGA | C41: ISO 6 | D41: Class 100 | E41: Grade A (ISO 5 at Rest & ISO 5 in Oper.) | F41: JIS Class 6 | G41: Grade A (ISO 5 at Rest & ISO 5 in Oper.) | H41: South America | I41: 3.5 | J41: E or F | K41: 4 | L41: - | M41: 5µ
A42: =IF(B42&C43&D42="","",TRIM(TEXT(B42&C43&D42,0))&TEXT(ROW()-1,"00000")) -> JIS_B_9920ISO 4Class 1000041 | B42: JIS_B_9920 | C42: ISO 5 | D42: Class 10 | F42: JIS Class 5 | H42: Antartica | I42: 0.35 | J42: D | K42: 3 | L42: 4000 | M42: 1µ
A43: =IF(B43&C44&D43="","",TRIM(TEXT(B43&C44&D43,0))&TEXT(ROW()-1,"00000")) -> EUGMPISO 3Class 100042 | B43: EUGMP | C43: ISO 4 | D43: Class 1 | F43: JIS Class 4 | H43: Europe | I43: 0.035 | J43: C | K43: 2 | L43: - | M43: No-Filtration
A44: =IF(B44&#REF!&D44="","",TRIM(TEXT(B44&#REF!&D44,0))&TEXT(ROW()-1,"00000")) -> #REF! | B44: WHO | C44: ISO 3 | F44: JIS Class 3 | H44: Australia | K44: 1 | L44: - | M44: Positive Pressure
A45: =IF(B45&C45&D45="","",TRIM(TEXT(B45&C45&D45,0))&TEXT(ROW()-1,"00000")) -> BS_5295ISO 200044 | B45: BS_5295 | C45: ISO 2 | F45: JIS Class 2 | K45: 0 | L45: - | M45: Exhaust
A46: =IF(B46&C46&D46="","",TRIM(TEXT(B46&C46&D46,0))&TEXT(ROW()-1,"00000")) -> GERMANY_VDISO 100045 | B46: GERMANY_VD | C46: ISO 1 | F46: JIS Class 1
A47: =IF(B47&C47&D47="","",TRIM(TEXT(B47&C47&D47,0))&TEXT(ROW()-1,"00000")) -> AFNORX4410100046 | B47: AFNORX44101
A48: =IF(B48&C48&D48="","",TRIM(TEXT(B48&C48&D48,0))&TEXT(ROW()-1,"00000")) -> NC_Non_Classified00047 | B48: NC_Non_Classified

Sheet Input BOD
C8: ="Zoning Area AHU - " & INT((ROW()-8)/20)+1 & " " & IF(ISNUMBER(N10),"Air-Conditioning System " & IF(AH10="D","(DX)",IF(AH10="C","(Chilled Water)","")),IF(AND(N10="Amb",ISTEXT(N10)),"Ventilation System","Refer")) -> Zoning Area AHU - 1 Air-Conditioning System
C9: S.No. | D9: Room Name | E9: Length in mtrs | F9: Width in mtrs | G9: Height in mtrs | H9: People in Nos | I9: Eqpt. Load in KW | J9: Lighting in W/Sft | K9: No.of Inf./Hr | L9: Fresh Air | M9: Exhaust | N9: T ˚C (Required inside) | O9: RH(in) +/- 5% | P9: Peak Max Temp.(Out) in ˚C | Q9: RH(Out) in +/- 5% | R9: Select Class | S9: ACPH | T9: Chilled water enter C Direct Expansion enter D | U9: Select Standards | V9: Manual Entry for ACPH
C10: 1 | D10: Chandrashekar | E10: 1 | F10: 1 | G10: 2 | H10: 1 | I10: 2 | J10: 1.75 | K10: 2 | L10: 0.1 | M10: 0 | N10: 24 | O10: 50 | P10: 41 | Q10: 85 | R10: Class100K | S10: =Y10 -> 12 | T10: D | U10: FDA | V10: 0 | Y10: =IF(AND(ISNUMBER(V10), V10>0), V10, IFERROR(INDEX('Class Air Changes'!$E$6:$E$75, MATCH(R10, 'Class Air Changes'!$D$6:$D$75, 0)), "Not Found")) -> 12
C11: 2 | D11: vijay bhasker | E11: 1 | F11: 1 | G11: 2 | H11: 1 | I11: 2 | J11: 1.75 | K11: 2 | L11: 0.1 | M11: 0 | N11: =N10 -> 24 | O11: 50 | P11: =P10 -> 41 | Q11: 85 | R11: =R10 -> Class100K | S11: =S10 -> 12 | T11: D | U11: =U10 -> FDA | V11: =V10 -> 0 | Y11: =IF(AND(ISNUMBER(X11), X11>0), X11, IFERROR(INDEX('Class Air Changes'!$E$6:$E$75, MATCH(R11, 'Class Air Changes'!$D$6:$D$75, 0)), "Not Found")) -> 12
C12: 3 | D12: nimma | E12: 1 | F12: 1 | G12: 2 | H12: 1 | I12: 2 | J12: 1.75 | K12: 2 | L12: 0.1 | M12: 0 | N12: =N11 -> 24 | O12: 50 | P12: =P11 -> 41 | Q12: 85 | R12: =R11 -> Class100K | S12: =S11 -> 12 | T12: D | U12: =U11 -> FDA | V12: =V11 -> 0 | Y12: =IF(AND(ISNUMBER(X12), X12>0), X12, IFERROR(INDEX('Class Air Changes'!$E$6:$E$75, MATCH(R12, 'Class Air Changes'!$D$6:$D$75, 0)), "Not Found")) -> 12
C13: 4 | D13: sahajanand | E13: 1 | F13: 1 | G13: 2 | H13: 1 | I13: 2 | J13: 1.75 | K13: 2 | L13: 0.1 | M13: 0 | N13: =N12 -> 24 | O13: 50 | P13: =P12 -> 41 | Q13: 85 | R13: =R12 -> Class100K | S13: =S12 -> 12 | T13: D | U13: =U12 -> FDA | V13: =V12 -> 0 | Y13: =IF(AND(ISNUMBER(X13), X13>0), X13, IFERROR(INDEX('Class Air Changes'!$E$6:$E$75, MATCH(R13, 'Class Air Changes'!$D$6:$D$75, 0)), "Not Found")) -> 12
C14: 5 | D14: xyz | E14: 1 | F14: 1 | G14: 2 | H14: 1 | I14: 2 | J14: 1.75 | K14: 2 | L14: 0.1 | M14: 0 | N14: =N13 -> 24 | O14: 50 | P14: =P13 -> 41 | Q14: 85 | R14: =R13 -> Class100K | S14: =S13 -> 12 | T14: D | U14: =U13 -> FDA | V14: =V13 -> 0 | Y14: =IF(AND(ISNUMBER(X14), X14>0), X14, IFERROR(INDEX('Class Air Changes'!$E$6:$E$75, MATCH(R14, 'Class Air Changes'!$D$6:$D$75, 0)), "Not Found")) -> 12
C15: 6 | D15: abc | E15: 1 | F15: 1 | G15: 2 | H15: 1 | I15: 2 | J15: 1.75 | K15: 2 | L15: 0.1 | M15: 0 | N15: =N14 -> 24 | O15: 50 | P15: =P14 -> 41 | Q15: 85 | R15: =R14 -> Class100K | S15: =S14 -> 12 | T15: D | U15: =U14 -> FDA | V15: =V14 -> 0 | Y15: =IF(AND(ISNUMBER(X15), X15>0), X15, IFERROR(INDEX('Class Air Changes'!$E$6:$E$75, MATCH(R15, 'Class Air Changes'!$D$6:$D$75, 0)), "Not Found")) -> 12
C16: 7 | D16: excel | E16: 1 | F16: 1 | G16: 2 | H16: 1 | I16: 2 | J16: 1.75 | K16: 2 | L16: 0.1 | M16: 0 | N16: =N15 -> 24 | O16: 50 | P16: =P15 -> 41 | Q16: 85 | R16: =R15 -> Class100K | S16: =S15 -> 12 | T16: D | U16: =U15 -> FDA | V16: =V15 -> 0 | Y16: =IF(AND(ISNUMBER(X16), X16>0), X16, IFERROR(INDEX('Class Air Changes'!$E$6:$E$75, MATCH(R16, 'Class Air Changes'!$D$6:$D$75, 0)), "Not Found")) -> 12
C17: 8 | D17: word | E17: 1 | F17: 1 | G17: 2 | H17: 1 | I17: 2 | J17: 1.75 | K17: 2 | L17: 0.1 | M17: 0 | N17: =N16 -> 24 | O17: 50 | P17: =P16 -> 41 | Q17: 85 | R17: =R16 -> Class100K | S17: =S16 -> 12 | T17: D | U17: =U16 -> FDA | V17: =V16 -> 0 | Y17: =IF(AND(ISNUMBER(X17), X17>0), X17, IFERROR(INDEX('Class Air Changes'!$E$6:$E$75, MATCH(R17, 'Class Air Changes'!$D$6:$D$75, 0)), "Not Found")) -> 12
C18: 9 | D18: java | E18: 1 | F18: 1 | G18: 2 | H18: 1 | I18: 2 | J18: 1.75 | K18: 2 | L18: 0.1 | M18: 0 | N18: =N17 -> 24 | O18: 50 | P18: =P17 -> 41 | Q18: 85 | R18: =R17 -> Class100K | S18: =S17 -> 12 | T18: D | U18: =U17 -> FDA | V18: =V17 -> 0 | Y18: =IF(AND(ISNUMBER(X18), X18>0), X18, IFERROR(INDEX('Class Air Changes'!$E$6:$E$75, MATCH(R18, 'Class Air Changes'!$D$6:$D$75, 0)), "Not Found")) -> 12
C19: 10 | D19: 12345 | E19: 1 | F19: 1 | G19: 2 | H19: 1 | I19: 2 | J19: 1.75 | K19: 2 | L19: 0.1 | M19: 0 | N19: =N18 -> 24 | O19: 50 | P19: =P18 -> 41 | Q19: 85 | R19: =R18 -> Class100K | S19: =S18 -> 12 | T19: D | U19: =U18 -> FDA | V19: =V18 -> 0 | Y19: =IF(AND(ISNUMBER(X19), X19>0), X19, IFERROR(INDEX('Class Air Changes'!$E$6:$E$75, MATCH(R19, 'Class Air Changes'!$D$6:$D$75, 0)), "Not Found")) -> 12
C20: 11 | D20: cvdwvjvq | E20: 1 | F20: 1 | G20: 2 | H20: 1 | I20: 2 | J20: 1.75 | K20: 2 | L20: 0.1 | M20: 0 | N20: =N19 -> 24 | O20: 50 | P20: =P19 -> 41 | Q20: 85 | R20: =R19 -> Class100K | S20: =S19 -> 12 | T20: D | U20: =U19 -> FDA | V20: =V19 -> 0 | Y20: =IF(AND(ISNUMBER(X20), X20>0), X20, IFERROR(INDEX('Class Air Changes'!$E$6:$E$75, MATCH(R20, 'Class Air Changes'!$D$6:$D$75, 0)), "Not Found")) -> 12
C21: 12 | D21: jcvbbvk | E21: 1 | F21: 1 | G21: 2 | H21: 1 | I21: 2 | J21: 1.75 | K21: 2 | L21: 0.1 | M21: 0 | N21: =N20 -> 24 | O21: 50 | P21: =P20 -> 41 | Q21: 85 | R21: =R20 -> Class100K | S21: =S20 -> 12 | T21: D | U21: =U20 -> FDA | V21: =V20 -> 0 | Y21: =IF(AND(ISNUMBER(X21), X21>0), X21, IFERROR(INDEX('Class Air Changes'!$E$6:$E$75, MATCH(R21, 'Class Air Changes'!$D$6:$D$75, 0)), "Not Found")) -> 12
C22: 13 | D22: vbwbvb | E22: 1 | F22: 1 | G22: 2 | H22: 1 | I22: 2 | J22: 1.75 | K22: 2 | L22: 0.1 | M22: 0 | N22: =N21 -> 24 | O22: 50 | P22: =P21 -> 41 | Q22: 85 | R22: =R21 -> Class100K | S22: =S21 -> 12 | T22: D | U22: =U21 -> FDA | V22: =V21 -> 0 | Y22: =IF(AND(ISNUMBER(X22), X22>0), X22, IFERROR(INDEX('Class Air Changes'!$E$6:$E$75, MATCH(R22, 'Class Air Changes'!$D$6:$D$75, 0)), "Not Found")) -> 12
C23: 14 | D23: b cjvjvve | E23: 1 | F23: 1 | G23: 2 | H23: 1 | I23: 2 | J23: 1.75 | K23: 2 | L23: 0.1 | M23: 0 | N23: =N22 -> 24 | O23: 50 | P23: =P22 -> 41 | Q23: 85 | R23: =R22 -> Class100K | S23: =S22 -> 12 | T23: D | U23: =U22 -> FDA | V23: =V22 -> 0 | Y23: =IF(AND(ISNUMBER(X23), X23>0), X23, IFERROR(INDEX('Class Air Changes'!$E$6:$E$75, MATCH(R23, 'Class Air Changes'!$D$6:$D$75, 0)), "Not Found")) -> 12
C24: 15 | D24: ifhiuhfigi | E24: 1 | F24: 1 | G24: 2 | H24: 1 | I24: 2 | J24: 1.75 | K24: 2 | L24: 0.1 | M24: 0 | N24: =N23 -> 24 | O24: 50 | P24: =P23 -> 41 | Q24: 85 | R24: =R23 -> Class100K | S24: =S23 -> 12 | T24: D | U24: =U23 -> FDA | V24: =V23 -> 0 | Y24: =IF(AND(ISNUMBER(X24), X24>0), X24, IFERROR(INDEX('Class Air Changes'!$E$6:$E$75, MATCH(R24, 'Class Air Changes'!$D$6:$D$75, 0)), "Not Found")) -> 12
C25: 16 | D25: hbhwbfb | E25: 1 | F25: 1 | G25: 2 | H25: 1 | I25: 2 | J25: 1.75 | K25: 2 | L25: 0.1 | M25: 0 | N25: =N24 -> 24 | O25: 50 | P25: =P24 -> 41 | Q25: 85 | R25: =R24 -> Class100K | S25: =S24 -> 12 | T25: D | U25: =U24 -> FDA | V25: =V24 -> 0 | Y25: =IF(AND(ISNUMBER(X25), X25>0), X25, IFERROR(INDEX('Class Air Changes'!$E$6:$E$75, MATCH(R25, 'Class Air Changes'!$D$6:$D$75, 0)), "Not Found")) -> 12
C26: =IF(D26<>"",COUNTA($D$10:D26),"")
C27: =IF(D27<>"",COUNTA($D$10:D27),"")
C28: ="Zoning Area AHU - " & INT((ROW()-8)/20)+1 & " " & IF(ISNUMBER(N30),"Air-Conditioning System " & IF(AH30="D","(DX)",IF(AH30="C","(Chilled Water)","")),IF(AND(N30="Amb",ISTEXT(N30)),"Ventilation System","Refer")) -> Zoning Area AHU - 2 Air-Conditioning System
D29: Room Name | E29: Length in mtrs | F29: Width in mtrs | G29: Height in mtrs | H29: People in Nos | I29: Eqpt. Load in KW | J29: Lighting in W/Sft | K29: No.of Inf./Hr | L29: Fresh Air | M29: Exhaust | N29: T ˚C (Required inside) | O29: RH(in) +/- 5% | P29: Peak Max Temp.(Out) in ˚C | Q29: RH(Out) in +/- 5% | R29: Class | S29: ACPH | T29: ACPH
C30: =IF(D30<>"",COUNTA($D$10:D30),"") -> 18 | D30: Clean Room 10 | E30: 3 | F30: 3 | G30: 2.4 | H30: 1 | I30: 2 | J30: 1.75 | K30: 3 | L30: 0.1 | M30: 0 | N30: 24 | O30: 50 | P30: 45 | Q30: 85 | R30: ISO 6 | S30: 160 | T30: C
C31: =IF(D31<>"",COUNTA($D$10:D31),"") -> 19 | D31: Clean Room 11 | E31: 1.8 | F31: 2.2 | G31: 2.4 | H31: 2 | I31: 1 | J31: 1.75 | K31: 3 | L31: 0.1 | M31: 0 | N31: 24 | O31: 50 | P31: 45 | Q31: 85 | R31: ISO 6 | S31: 160 | T31: C
C32: =IF(D32<>"",COUNTA($D$10:D32),"") -> 20 | D32: Clean Room 12 | E32: 1.5 | F32: 2.8 | G32: 2.4 | H32: 2 | I32: 3 | J32: 1.75 | K32: 3 | L32: 0.1 | M32: 0 | N32: 24 | O32: 50 | P32: 45 | Q32: 85 | R32: ISO 6 | S32: 160 | T32: C
C33: =IF(D33<>"",COUNTA($D$10:D33),"") -> 21 | D33: Clean Room 13 | E33: 2.1 | F33: 3.5 | G33: 2.4 | H33: 0 | I33: 1 | J33: 1.75 | K33: 3 | L33: 0.1 | M33: 0 | N33: 24 | O33: 50 | P33: 45 | Q33: 85 | R33: ISO 6 | S33: 160 | T33: C
C34: =IF(D34<>"",COUNTA($D$10:D34),"") -> 22 | D34: Clean Room 14 | E34: 2.7 | F34: 4 | G34: 2.4 | H34: 2 | I34: 1 | J34: 1.75 | K34: 3 | L34: 0.1 | M34: 0 | N34: 24 | O34: 50 | P34: 45 | Q34: 85 | R34: ISO 6 | S34: 160 | T34: C
C35: =IF(D35<>"",COUNTA($D$10:D35),"") -> 23 | D35: Clean Room 15 | E35: 3.8 | F35: 4.2 | G35: 2.4 | H35: 3 | I35: 3 | J35: 1.75 | K35: 3 | L35: 0.1 | M35: 0 | N35: 24 | O35: 50 | P35: 45 | Q35: 85 | R35: ISO 6 | S35: 160 | T35: C
C36: =IF(D36<>"",COUNTA($D$10:D36),"") -> 24 | D36: Clean Room 16 | E36: 3.1 | F36: 2.6 | G36: 2.4 | H36: 2 | I36: 1 | J36: 1.75 | K36: 3 | L36: 0.1 | M36: 0 | N36: 24 | O36: 50 | P36: 45 | Q36: 85 | R36: ISO 6 | S36: 160 | T36: C
C37: =IF(D37<>"",COUNTA($D$10:D37),"") -> 25 | D37: Clean Room 17 | E37: 1.9 | F37: 2.4 | G37: 2.4 | H37: 3 | I37: 2 | J37: 1.75 | K37: 3 | L37: 0.1 | M37: 0 | N37: 24 | O37: 50 | P37: 45 | Q37: 85 | R37: ISO 6 | S37: 160 | T37: C
C38: =IF(D38<>"",COUNTA($D$10:D38),"") -> 26 | D38: Clean Room 18 | E38: 3 | F38: 2.9 | G38: 2.4 | H38: 2 | I38: 1 | J38: 1.75 | K38: 3 | L38: 0.1 | M38: 0 | N38: 24 | O38: 50 | P38: 45 | Q38: 85 | R38: ISO 6 | S38: 160 | T38: C
C39: =IF(D39<>"",COUNTA($D$10:D39),"") -> 27 | D39: Clean Room 19 | E39: 2.4 | F39: 2 | G39: 2.4 | H39: 2 | I39: 1 | J39: 1.75 | K39: 3 | L39: 0.1 | M39: 0 | N39: 24 | O39: 50 | P39: 45 | Q39: 85 | R39: ISO 6 | S39: 160 | T39: C
C40: =IF(D40<>"",COUNTA($D$10:D40),"") -> 28 | D40: Clean Room 20 | E40: 2.1 | F40: 1.8 | G40: 2.4 | H40: 2 | I40: 1 | J40: 1.75 | K40: 3 | L40: 0.1 | M40: 0 | N40: 24 | O40: 50 | P40: 45 | Q40: 85 | R40: ISO 6 | S40: 160 | T40: C
C41: =IF(D41<>"",COUNTA($D$10:D41),"") -> 29 | D41: Clean Room 21 | E41: 1.8 | F41: 1.9 | G41: 2.4 | H41: 2 | I41: 1 | J41: 1.75 | K41: 3 | L41: 0.1 | M41: 0 | N41: 24 | O41: 50 | P41: 45 | Q41: 85 | R41: ISO 6 | S41: 160 | T41: C
... C45: =IF(D45<>"",COUNTA($D$10:D45),"") -> 33 | D45: Clean Room 25 | E45: 2.8 | F45: 2.4 | G45: 2.4 | H45: 2 | I45: 1 | J45: 1.75 | K45: 3 | L45: 0.1 | M45: 0 | N45: 24 | O45: 50 | P45: 45 | Q45: 85 | R45: ISO 6 | S45: 160 | T45: C
C46: =IF(D46<>"",COUNTA($D$10:D46),"")
C47: =IF(D47<>"",COUNTA($D$10:D47),"")
C48: ="Zoning Area AHU - " & INT((ROW()-8)/20)+1 & " " & IF(ISNUMBER(N50),"Air-Conditioning System " & IF(AH50="D","(DX)",IF(AH50="C","(Chilled Water)","")),IF(AND(N50="Amb",ISTEXT(N50)),"Ventilation System","Refer")) -> Zoning Area AHU - 3 Air-Conditioning System
C49: =IF(D49<>"",COUNTA($D$10:D49),"") -> 34 | D49: Room Name | E49: Length in mtrs | F49: Width in mtrs | G49: Height in mtrs | H49: People in Nos | I49: Eqpt. Load in KW | J49: Lighting in W/Sft | K49: No.of Inf./Hr | L49: Fresh Air | M49: Exhaust | N49: T ˚C (Required inside) | O49: RH(in) +/- 5% | P49: Peak Max Temp.(Out) in ˚C | Q49: RH(Out) in +/- 5% | R49: Class | S49: ACPH | T49: ACPH
C50: =IF(D50<>"",COUNTA($D$10:D50),"") -> 35 | D50: Clean Room 10 | E50: 3 | F50: 3 | G50: 2.4 | H50: 1 | I50: 2 | J50: 1.75 | K50: 3 | L50: 0.1 | M50: 0 | N50: 24 | O50: 50 | P50: 45 | Q50: 85 | R50: GRADE A | S50: 150 | T50: C
C51: =IF(D51<>"",COUNTA($D$10:D51),"") -> 36 | D51: Clean Room 11 | E51: 1.8 | F51: 2.2 | G51: 2.4 | H51: 2 | I51: 1 | J51: 1.75 | K51: 3 | L51: 0.1 | M51: 0 | N51: 24 | O51: 50 | P51: 45 | Q51: 85 | R51: GRADE A | S51: 150 | T51: C
C52: =IF(D52<>"",COUNTA($D$10:D52),"") -> 37 | D52: Clean Room 12 | E52: 1.5 | F52: 2.8 | G52: 2.4 | H52: 2 | I52: 3 | J52: 1.75 | K52: 3 | L52: 0.1 | M52: 0 | N52: 24 | O52: 50 | P52: 45 | Q52: 85 | R52: GRADE A | S52: 150 | T52: C
C53: =IF(D53<>"",COUNTA($D$10:D53),"") -> 38 | D53: Clean Room 13 | E53: 2.1 | F53: 3.5 | G53: 2.4 | H53: 0 | I53: 1 | J53: 1.75 | K53: 3 | L53: 0.1 | M53: 0 | N53: 24 | O53: 50 | P53: 45 | Q53: 85 | R53: GRADE A | S53: 150 | T53: C
C54: =IF(D54<>"",COUNTA($D$10:D54),"") -> 39 | D54: Clean Room 14 | E54: 2.7 | F54: 4 | G54: 2.4 | H54: 2 | I54: 1 | J54: 1.75 | K54: 3 | L54: 0.1 | M54: 0 | N54: 24 | O54: 50 | P54: 45 | Q54: 85 | R54: GRADE A | S54: 150 | T54: C
C55: =IF(D55<>"",COUNTA($D$10:D55),"") -> 40 | D55: Clean Room 15 | E55: 3.8 | F55: 4.2 | G55: 2.4 | H55: 3 | I55: 3 | J55: 1.75 | K55: 3 | L55: 0.1 | M55: 0 | N55: 24 | O55: 50 | P55: 45 | Q55: 85 | R55: GRADE A | S55: 150 | T55: C
C56: =IF(D56<>"",COUNTA($D$10:D56),"") -> 41 | D56: Clean Room 16 | E56: 3.1 | F56: 2.6 | G56: 2.4 | H56: 2 | I56: 1 | J56: 1.75 | K56: 3 | L56: 0.1 | M56: 0 | N56: 24 | O56: 50 | P56: 45 | Q56: 85 | R56: GRADE A | S56: 150 | T56: C
C57: =IF(D57<>"",COUNTA($D$10:D57),"") -> 42 | D57: Clean Room 17 | E57: 1.9 | F57: 2.4 | G57: 2.4 | H57: 3 | I57: 2 | J57: 1.75 | K57: 3 | L57: 0.1 | M57: 0 | N57: 24 | O57: 50 | P57: 45 | Q57: 85 | R57: GRADE A | S57: 150 | T57: C
C58: =IF(D58<>"",COUNTA($D$10:D58),"") -> 43 | D58: Clean Room 18 | E58: 3 | F58: 2.9 | G58: 2.4 | H58: 2 | I58: 1 | J58: 1.75 | K58: 3 | L58: 0.1 | M58: 0 | N58: 24 | O58: 50 | P58: 45 | Q58: 85 | R58: GRADE A | S58: 150 | T58: C
C59: =IF(D59<>"",COUNTA($D$10:D59),"") -> 44 | D59: Clean Room 19 | E59: 2.4 | F59: 2 | G59: 2.4 | H59: 2 | I59: 1 | J59: 1.75 | K59: 3 | L59: 0.1 | M59: 0 | N59: 24 | O59: 50 | P59: 45 | Q59: 85 | R59: GRADE A | S59: 150 | T59: C
C60: =IF(D60<>"",COUNTA($D$10:D60),"") -> 45 | D60: Clean Room 20 | E60: 2.1 | F60: 1.8 | G60: 2.4 | H60: 2 | I60: 1 | J60: 1.75 | K60: 3 | L60: 0.1 | M60: 0 | N60: 24 | O60: 50 | P60: 45 | Q60: 85 | R60: GRADE A | S60: 150 | T60: C
C61: =IF(D61<>"",COUNTA($D$10:D61),"") -> 46 | D61: Clean Room 21 | E61: 1.8 | F61: 1.9 | G61: 2.4 | H61: 2 | I61: 1 | J61: 1.75 | K61: 3 | L61: 0.1 | M61: 0 | N61: 24 | O61: 50 | P61: 45 | Q61: 85 | R61: GRADE A | S61: 150 | T61: C
... C65: =IF(D65<>"",COUNTA($D$10:D65),"") -> 50 | D65: Clean Room 25 | E65: 2.8 | F65: 2.4 | G65: 2.4 | H65: 2 | I65: 1 | J65: 1.75 | K65: 3 | L65: 0.1 | M65: 0 | N65: 24 | O65: 50 | P65: 45 | Q65: 85 | R65: GRADE A | S65: 150 | T65: C
C66: =IF(D66<>"",COUNTA($D$10:D66),"")
C67: =IF(D67<>"",COUNTA($D$10:D67),"")
C68: ="Zoning Area AHU - " & INT((ROW()-8)/20)+1 & " " & IF(ISNUMBER(N70),"Air-Conditioning System " & IF(AH70="D","(DX)",IF(AH70="C","(Chilled Water)","")),IF(AND(N70="Amb",ISTEXT(N70)),"Ventilation System","Refer")) -> Zoning Area AHU - 4 Air-Conditioning System
C69: =IF(D69<>"",COUNTA($D$10:D69),"") -> 51 | D69: Room Name | E69: Length in mtrs | F69: Width in mtrs | G69: Height in mtrs | H69: People in Nos | I69: Eqpt. Load in KW | J69: Lighting in W/Sft | K69: No.of Inf./Hr | L69: Fresh Air | M69: Exhaust | N69: T ˚C (Required inside) | O69: RH(in) +/- 5% | P69: Peak Max Temp.(Out) in ˚C | Q69: RH(Out) in +/- 5% | R69: Class | S69: ACPH | T69: ACPH
C70: =IF(D70<>"",COUNTA($D$10:D70),"") -> 52 | D70: Clean Room 10 | E70: 3 | F70: 3 | G70: 2.4 | H70: 1 | I70: 2 | J70: 1.75 | K70: 3 | L70: 0.1 | M70: 0 | N70: 24 | O70: 50 | P70: 45 | Q70: 85 | R70: 10K | S70: 80 | T70: C
C71: =IF(D71<>"",COUNTA($D$10:D71),"") -> 53 | D71: Clean Room 11 | E71: 1.8 | F71: 2.2 | G71: 2.4 | H71: 2 | I71: 1 | J71: 1.75 | K71: 3 | L71: 0.1 | M71: 0 | N71: 24 | O71: 50 | P71: 45 | Q71: 85 | R71: 10K | S71: 80 | T71: C
C72: =IF(D72<>"",COUNTA($D$10:D72),"") -> 54 | D72: Clean Room 12 | E72: 1.5 | F72: 2.8 | G72: 2.4 | H72: 2 | I72: 3 | J72: 1.75 | K72: 3 | L72: 0.1 | M72: 0 | N72: 24 | O72: 50 | P72: 45 | Q72: 85 | R72: 10K | S72: 80 | T72: C
C73: =IF(D73<>"",COUNTA($D$10:D73),"") -> 55 | D73: Clean Room 13 | E73: 2.1 | F73: 3.5 | G73: 2.4 | H73: 0 | I73: 1 | J73: 1.75 | K73: 3 | L73: 0.1 | M73: 0 | N73: 24 | O73: 50 | P73: 45 | Q73: 85 | R73: 10K | S73: 80 | T73: C
C74: =IF(D74<>"",COUNTA($D$10:D74),"") -> 56 | D74: Clean Room 14 | E74: 2.7 | F74: 4 | G74: 2.4 | H74: 2 | I74: 1 | J74: 1.75 | K74: 3 | L74: 0.1 | M74: 0 | N74: 24 | O74: 50 | P74: 45 | Q74: 85 | R74: 10K | S74: 80 | T74: C
C75: =IF(D75<>"",COUNTA($D$10:D75),"") -> 57 | D75: Clean Room 15 | E75: 3.8 | F75: 4.2 | G75: 2.4 | H75: 3 | I75: 3 | J75: 1.75 | K75: 3 | L75: 0.1 | M75: 0 | N75: 24 | O75: 50 | P75: 45 | Q75: 85 | R75: 10K | S75: 80 | T75: C
C76: =IF(D76<>"",COUNTA($D$10:D76),"") -> 58 | D76: Clean Room 16 | E76: 3.1 | F76: 2.6 | G76: 2.4 | H76: 2 | I76: 1 | J76: 1.75 | K76: 3 | L76: 0.1 | M76: 0 | N76: 24 | O76: 50 | P76: 45 | Q76: 85 | R76: 10K | S76: 80 | T76: C
C77: =IF(D77<>"",COUNTA($D$10:D77),"") -> 59 | D77: Clean Room 17 | E77: 1.9 | F77: 2.4 | G77: 2.4 | H77: 3 | I77: 2 | J77: 1.75 | K77: 3 | L77: 0.1 | M77: 0 | N77: 24 | O77: 50 | P77: 45 | Q77: 85 | R77: 10K | S77: 80 | T77: C
C78: =IF(D78<>"",COUNTA($D$10:D78),"") -> 60 | D78: Clean Room 18 | E78: 3 | F78: 2.9 | G78: 2.4 | H78: 2 | I78: 1 | J78: 1.75 | K78: 3 | L78: 0.1 | M78: 0 | N78: 24 | O78: 50 | P78: 45 | Q78: 85 | R78: 10K | S78: 80 | T78: C
C79: =IF(D79<>"",COUNTA($D$10:D79),"") -> 61 | D79: Clean Room 19 | E79: 2.4 | F79: 2 | G79: 2.4 | H79: 2 | I79: 1 | J79: 1.75 | K79: 3 | L79: 0.1 | M79: 0 | N79: 24 | O79: 50 | P79: 45 | Q79: 85 | R79: 10K | S79: 80 | T79: C
C80: =IF(D80<>"",COUNTA($D$10:D80),"") -> 62 | D80: Clean Room 20 | E80: 2.1 | F80: 1.8 | G80: 2.4 | H80: 2 | I80: 1 | J80: 1.75 | K80: 3 | L80: 0.1 | M80: 0 | N80: 24 | O80: 50 | P80: 45 | Q80: 85 | R80: 10K | S80: 80 | T80: C
C81: =IF(D81<>"",COUNTA($D$10:D81),"") -> 63 | D81: Clean Room 21 | E81: 1.8 | F81: 1.9 | G81: 2.4 | H81: 2 | I81: 1 | J81: 1.75 | K81: 3 | L81: 0.1 | M81: 0 | N81: 24 | O81: 50 | P81: 45 | Q81: 85 | R81: 10K | S81: 80 | T81: C
... C85: =IF(D85<>"",COUNTA($D$10:D85),"") -> 67 | D85: Clean Room 25 | E85: 2.8 | F85: 2.4 | G85: 2.4 | H85: 2 | I85: 1 | J85: 1.75 | K85: 3 | L85: 0.1 | M85: 0 | N85: 24 | O85: 50 | P85: 45 | Q85: 85 | R85: 10K | S85: 80 | T85: C
C86: =IF(D86<>"",COUNTA($D$10:D86),"")
C87: =IF(D87<>"",COUNTA($D$10:D87),"")
C88: ="Zoning Area AHU - " & INT((ROW()-8)/20)+1 & " " & IF(ISNUMBER(N90),"Air-Conditioning System " & IF(AH90="D","(DX)",IF(AH90="C","(Chilled Water)","")),IF(AND(N90="Amb",ISTEXT(N90)),"Ventilation System","Refer")) -> Zoning Area AHU - 5 Air-Conditioning System
C89: =IF(D89<>"",COUNTA($D$10:D89),"") -> 68 | D89: Room Name | E89: Length in mtrs | F89: Width in mtrs | G89: Height in mtrs | H89: People in Nos | I89: Eqpt. Load in KW | J89: Lighting in W/Sft | K89: No.of Inf./Hr | L89: Fresh Air | M89: Exhaust | N89: T ˚C (Required inside) | O89: RH(in) +/- 5% | P89: Peak Max Temp.(Out) in ˚C | Q89: RH(Out) in +/- 5% | R89: Class | S89: ACPH | T89: ACPH
C90: =IF(D90<>"",COUNTA($D$10:D90),"") -> 69 | D90: Clean Room 10 | E90: 3 | F90: 3 | G90: 2.4 | H90: 1 | I90: 2 | J90: 1.75 | K90: 3 | L90: 0.1 | M90: 0 | N90: 24 | O90: 50 | P90: 45 | Q90: 85 | R90: NC | S90: 20 | T90: C
C91: =IF(D91<>"",COUNTA($D$10:D91),"") -> 70 | D91: Clean Room 11 | E91: 1.8 | F91: 2.2 | G91: 2.4 | H91: 2 | I91: 1 | J91: 1.75 | K91: 3 | L91: 0.1 | M91: 0 | N91: 24 | O91: 50 | P91: 45 | Q91: 85 | R91: NC | S91: 20 | T91: C
C92: =IF(D92<>"",COUNTA($D$10:D92),"") -> 71 | D92: Clean Room 12 | E92: 1.5 | F92: 2.8 | G92: 2.4 | H92: 2 | I92: 3 | J92: 1.75 | K92: 3 | L92: 0.1 | M92: 0 | N92: 24 | O92: 50 | P92: 45 | Q92: 85 | R92: NC | S92: 20 | T92: C
C93: =IF(D93<>"",COUNTA($D$10:D93),"") -> 72 | D93: Clean Room 13 | E93: 2.1 | F93: 3.5 | G93: 2.4 | H93: 0 | I93: 1 | J93: 1.75 | K93: 3 | L93: 0.1 | M93: 0 | N93: 24 | O93: 50 | P93: 45 | Q93: 85 | R93: NC | S93: 20 | T93: C
C94: =IF(D94<>"",COUNTA($D$10:D94),"") -> 73 | D94: Clean Room 14 | E94: 2.7 | F94: 4 | G94: 2.4 | H94: 2 | I94: 1 | J94: 1.75 | K94: 3 | L94: 0.1 | M94: 0 | N94: 24 | O94: 50 | P94: 45 | Q94: 85 | R94: NC | S94: 20 | T94: C
C95: =IF(D95<>"",COUNTA($D$10:D95),"") -> 74 | D95: Clean Room 15 | E95: 3.8 | F95: 4.2 | G95: 2.4 | H95: 3 | I95: 3 | J95: 1.75 | K95: 3 | L95: 0.1 | M95: 0 | N95: 24 | O95: 50 | P95: 45 | Q95: 85 | R95: NC | S95: 20 | T95: C
C96: =IF(D96<>"",COUNTA($D$10:D96),"") -> 75 | D96: Clean Room 16 | E96: 3.1 | F96: 2.6 | G96: 2.4 | H96: 2 | I96: 1 | J96: 1.75 | K96: 3 | L96: 0.1 | M96: 0 | N96: 24 | O96: 50 | P96: 45 | Q96: 85 | R96: NC | S96: 20 | T96: C
C97: =IF(D97<>"",COUNTA($D$10:D97),"") -> 76 | D97: Clean Room 17 | E97: 1.9 | F97: 2.4 | G97: 2.4 | H97: 3 | I97: 2 | J97: 1.75 | K97: 3 | L97: 0.1 | M97: 0 | N97: 24 | O97: 50 | P97: 45 | Q97: 85 | R97: NC | S97: 20 | T97: C
C98: =IF(D98<>"",COUNTA($D$10:D98),"") -> 77 | D98: Clean Room 18 | E98: 3 | F98: 2.9 | G98: 2.4 | H98: 2 | I98: 1 | J98: 1.75 | K98: 3 | L98: 0.1 | M98: 0 | N98: 24 | O98: 50 | P98: 45 | Q98: 85 | R98: NC | S98: 20 | T98: C
C99: =IF(D99<>"",COUNTA($D$10:D99),"") -> 78 | D99: Clean Room 19 | E99: 2.4 | F99: 2 | G99: 2.4 | H99: 2 | I99: 1 | J99: 1.75 | K99: 3 | L99: 0.1 | M99: 0 | N99: 24 | O99: 50 | P99: 45 | Q99: 85 | R99: NC | S99: 20 | T99: C
C100: =IF(D100<>"",COUNTA($D$10:D100),"") -> 79 | D100: Clean Room 20 | E100: 2.1 | F100: 1.8 | G100: 2.4 | H100: 2 | I100: 1 | J100: 1.75 | K100: 3 | L100: 0.1 | M100: 0 | N100: 24 | O100: 50 | P100: 45 | Q100: 85 | R100: NC | S100: 20 | T100: C
C101: =IF(D101<>"",COUNTA($D$10:D101),"") -> 80 | D101: Clean Room 21 | E101: 1.8 | F101: 1.9 | G101: 2.4 | H101: 2 | I101: 1 | J101: 1.75 | K101: 3 | L101: 0.1 | M101: 0 | N101: 24 | O101: 50 | P101: 45 | Q101: 85 | R101: NC | S101: 20 | T101: C
... C105: =IF(D105<>"",COUNTA($D$10:D105),"") -> 84 | D105: Clean Room 25 | E105: 2.8 | F105: 2.4 | G105: 2.4 | H105: 2 | I105: 1 | J105: 1.75 | K105: 3 | L105: 0.1 | M105: 0 | N105: 24 | O105: 50 | P105: 45 | Q105: 85 | R105: NC | S105: 20 | T105: C
C106: =IF(D106<>"",COUNTA($D$10:D106),"")
C107: =IF(D107<>"",COUNTA($D$10:D107),"")
C108: ="Zoning Area AHU - " & INT((ROW()-8)/20)+1 & " " & IF(ISNUMBER(N110),"Air-Conditioning System " & IF(AH110="D","(DX)",IF(AH110="C","(Chilled Water)","")),IF(AND(N110="Amb",ISTEXT(N110)),"Ventilation System","Refer")) -> Zoning Area AHU - 6 Air-Conditioning System
C109: =IF(D109<>"",COUNTA($D$10:D109),"") -> 85 | D109: Room Name | E109: Length in mtrs | F109: Width in mtrs | G109: Height in mtrs | H109: People in Nos | I109: Eqpt. Load in KW | J109: Lighting in W/Sft | K109: No.of Inf./Hr | L109: Fresh Air | M109: Exhaust | N109: T ˚C (Required inside) | O109: RH(in) +/- 5% | P109: Peak Max Temp.(Out) in ˚C | Q109: RH(Out) in +/- 5% | R109: Class | S109: ACPH | T109: ACPH
C110: =IF(D110<>"",COUNTA($D$10:D110),"") -> 86 | D110: Clean Room 10 | E110: 3 | F110: 3 | G110: 2.4 | H110: 1 | I110: 2 | J110: 1.75 | K110: 3 | L110: 0.1 | M110: 0 | N110: 24 | O110: 50 | P110: 45 | Q110: 85 | R110: 5 Micron | S110: 25 | T110: C
C111: =IF(D111<>"",COUNTA($D$10:D111),"") -> 87 | D111: Clean Room 11 | E111: 1.8 | F111: 2.2 | G111: 2.4 | H111: 2 | I111: 1 | J111: 1.75 | K111: 3 | L111: 0.1 | M111: 0 | N111: 24 | O111: 50 | P111: 45 | Q111: 85 | R111: 5 Micron | S111: 25 | T111: C
C112: =IF(D112<>"",COUNTA($D$10:D112),"") -> 88 | D112: Clean Room 12 | E112: 1.5 | F112: 2.8 | G112: 2.4 | H112: 2 | I112: 3 | J112: 1.75 | K112: 3 | L112: 0.1 | M112: 0 | N112: 24 | O112: 50 | P112: 45 | Q112: 85 | R112: 5 Micron | S112: 25 | T112: C
C113: =IF(D113<>"",COUNTA($D$10:D113),"") -> 89 | D113: Clean Room 13 | E113: 2.1 | F113: 3.5 | G113: 2.4 | H113: 0 | I113: 1 | J113: 1.75 | K113: 3 | L113: 0.1 | M113: 0 | N113: 24 | O113: 50 | P113: 45 | Q113: 85 | R113: 5 Micron | S113: 25 | T113: C
C114: =IF(D114<>"",COUNTA($D$10:D114),"") -> 90 | D114: Clean Room 14 | E114: 2.7 | F114: 4 | G114: 2.4 | H114: 2 | I114: 1 | J114: 1.75 | K114: 3 | L114: 0.1 | M114: 0 | N114: 24 | O114: 50 | P114: 45 | Q114: 85 | R114: 5 Micron | S114: 25 | T114: C
C115: =IF(D115<>"",COUNTA($D$10:D115),"") -> 91 | D115: Clean Room 15 | E115: 3.8 | F115: 4.2 | G115: 2.4 | H115: 3 | I115: 3 | J115: 1.75 | K115: 3 | L115: 0.1 | M115: 0 | N115: 24 | O115: 50 | P115: 45 | Q115: 85 | R115: 5 Micron | S115: 25 | T115: C
C116: =IF(D116<>"",COUNTA($D$10:D116),"") -> 92 | D116: Clean Room 16 | E116: 3.1 | F116: 2.6 | G116: 2.4 | H116: 2 | I116: 1 | J116: 1.75 | K116: 3 | L116: 0.1 | M116: 0 | N116: 24 | O116: 50 | P116: 45 | Q116: 85 | R116: 5 Micron | S116: 25 | T116: C
C117: =IF(D117<>"",COUNTA($D$10:D117),"") -> 93 | D117: Clean Room 17 | E117: 1.9 | F117: 2.4 | G117: 2.4 | H117: 3 | I117: 2 | J117: 1.75 | K117: 3 | L117: 0.1 | M117: 0 | N117: 24 | O117: 50 | P117: 45 | Q117: 85 | R117: 5 Micron | S117: 25 | T117: C
C118: =IF(D118<>"",COUNTA($D$10:D118),"") -> 94 | D118: Clean Room 18 | E118: 3 | F118: 2.9 | G118: 2.4 | H118: 2 | I118: 1 | J118: 1.75 | K118: 3 | L118: 0.1 | M118: 0 | N118: 24 | O118: 50 | P118: 45 | Q118: 85 | R118: 5 Micron | S118: 25 | T118: C
C119: =IF(D119<>"",COUNTA($D$10:D119),"") -> 95 | D119: Clean Room 19 | E119: 2.4 | F119: 2 | G119: 2.4 | H119: 2 | I119: 1 | J119: 1.75 | K119: 3 | L119: 0.1 | M119: 0 | N119: 24 | O119: 50 | P119: 45 | Q119: 85 | R119: 5 Micron | S119: 25 | T119: C
...

Sheet Output BOD
C8: ="Zoning Area AHU - " & INT((ROW()-8)/20)+1 & " " &IF(AQ10>0,"Air-Conditioning System " & IF(AH10="D","(DX)",IF(AH10="C","(Chilled Water)","")),IF(AND(N10="Amb",AQ10=0),"Ventilation System","Refer")) -> Zoning Area AHU - 1 Air-Conditioning System (DX) | AS8: Chilled Water Details | AW8: Hot Water/Steam Details
C9: S.No. | D9: Room Name | E9: Length in mtrs | F9: Width in mtrs | G9: Height in mtrs | H9: People in Nos | I9: Eqpt. Load in KW | J9: Lighting in W/Sft | K9: No.of Inf./Hr | L9: Fresh Air | M9: Exhaust | N9: T ˚C (Required inside) | O9: RH(in) +/- 5% | P9: Peak Max Temp.(Out) in ˚C | Q9: RH(Out) in +/- 5% | R9: Class | S9: ACPH | T9: Peak Min Temp.(Out) in ˚C | U9: RH(Out) +/- 5% | V9: Class | W9: ACPH | X9: Area | Y9: Volume | Z9: Room Cfm | AA9: FA | AB9: EA | AC9: Rem. Water vapour Kg/hr | AD9: Deh. Cfm | AE9: Res. Cfm | AF9: Room Terminal Supply Module in Sft | AG9: Res. Cooling Load in TR | AH9: Chilled Water (C) OR DX (D) | AI9: Room AC load in TR | AJ9: Cfm AC load in TR | AK9: AHU Cfm | AL9: AHU Size | AM9: Static Pressure | AN9: Blower Model BDB | AO9: Motor Selected in Hp | AP9: No. of Rows of Cooling Coil | AQ9: AHU Cooling Load in TR | AR9: No. Of Stages of Filtr. | AS9: Chilled water in GPM | AT9: Chilled water in L/s | AU9: Flow Velocity in m/s | AV9: Pipe Size in mm | AW9: Hot Water/Steam in GPM | AX9: Hot water/Steam in L/s | AY9: Flow Velocity | AZ9: Pipe Size
C10: ='Input BOD'!C10 -> 1 | D10: ='BOD-Cold & Amb.'!D10 -> Chandrashekar | E10: ='BOD-Cold & Amb.'!E10 -> 1 | F10: ='BOD-Cold & Amb.'!F10 -> 1 | G10: ='BOD-Cold & Amb.'!G10 -> 2 | H10: ='BOD-Cold & Amb.'!H10 -> 1 | I10: ='BOD-Cold & Amb.'!I10 -> 2 | J10: ='BOD-Cold & Amb.'!J10 -> 1.75 | K10: ='BOD-Cold & Amb.'!K10 -> 2 | ... AJ10: ='BOD-Cold & Amb.'!AJ10 -> 3.5 | AK10: ='BOD-Cold & Amb.'!AK10:AK25 -> 15750 | AL10: W | AM10: ='BOD-Cold & Amb.'!AM10:AM25 -> 125 | AN10: ='BOD-Cold & Amb.'!AN10:AN25 -> 710 | AO10: ='BOD-Cold & Amb.'!AO10:AO25 -> 20 | AP10: ='BOD-Cold & Amb.'!AP10:AP25 -> 8 | AQ10: ='BOD-Cold & Amb.'!AQ10:AQ25 -> 56 | AR10: ='BOD-Cold & Amb.'!AR10:AR25 -> 3 | AS10: ='BOD-Cold & Amb.'!AS10:AS25 -> 224 | AT10: ='BOD-Cold & Amb.'!AT10:AT25 -> 14.13216 | ... AV10: ='BOD-Cold & Amb.'!AV10:AV25 -> 94.875581
C11: ='Input BOD'!C11 -> 2 | D11: ='BOD-Cold & Amb.'!D11 -> vijay bhasker | E11: ='BOD-Cold & Amb.'!E11 -> 1 | F11: ='BOD-Cold & Amb.'!F11 -> 1 | G11: ='BOD-Cold & Amb.'!G11 -> 2 | H11: ='BOD-Cold & Amb.'!H11 -> 1 | I11: ='BOD-Cold & Amb.'!I11 -> 2 | J11: ='BOD-Cold & Amb.'!J11 -> 1.75 | K11: ='BOD-Cold & Amb.'!K11 -> 2 | ... AJ11: ='BOD-Cold & Amb.'!AJ11 -> 3.5 | AL11: ='BOD-Cold & Amb.'!AL11 -> 2050
C12: ='Input BOD'!C12 -> 3 | D12: ='BOD-Cold & Amb.'!D12 -> nimma | E12: ='BOD-Cold & Amb.'!E12 -> 1 | F12: ='BOD-Cold & Amb.'!F12 -> 1 | G12: ='BOD-Cold & Amb.'!G12 -> 2 | H12: ='BOD-Cold & Amb.'!H12 -> 1 | I12: ='BOD-Cold & Amb.'!I12 -> 2 | J12: ='BOD-Cold & Amb.'!J12 -> 1.75 | K12: ='BOD-Cold & Amb.'!K12 -> 2 | ... AJ12: ='BOD-Cold & Amb.'!AJ12 -> 3.5 | AL12: H
C13: ='Input BOD'!C13 -> 4 | D13: ='BOD-Cold & Amb.'!D13 -> sahajanand | E13: ='BOD-Cold & Amb.'!E13 -> 1 | F13: ='BOD-Cold & Amb.'!F13 -> 1 | G13: ='BOD-Cold & Amb.'!G13 -> 2 | H13: ='BOD-Cold & Amb.'!H13 -> 1 | I13: ='BOD-Cold & Amb.'!I13 -> 2 | J13: ='BOD-Cold & Amb.'!J13 -> 1.75 | K13: ='BOD-Cold & Amb.'!K13 -> 2 | ... AJ13: ='BOD-Cold & Amb.'!AJ13 -> 3.5 | AL13: ='BOD-Cold & Amb.'!AL13 -> 2050
C14: ='Input BOD'!C14 -> 5 | D14: ='BOD-Cold & Amb.'!D14 -> xyz | E14: ='BOD-Cold & Amb.'!E14 -> 1 | F14: ='BOD-Cold & Amb.'!F14 -> 1 | G14: ='BOD-Cold & Amb.'!G14 -> 2 | H14: ='BOD-Cold & Amb.'!H14 -> 1 | I14: ='BOD-Cold & Amb.'!I14 -> 2 | J14: ='BOD-Cold & Amb.'!J14 -> 1.75 | K14: ='BOD-Cold & Amb.'!K14 -> 2 | ... AJ14: ='BOD-Cold & Amb.'!AJ14 -> 3.5 | AL14: L
C15: ='Input BOD'!C15 -> 6 | D15: ='BOD-Cold & Amb.'!D15 -> abc | E15: ='BOD-Cold & Amb.'!E15 -> 1 | F15: ='BOD-Cold & Amb.'!F15 -> 1 | G15: ='BOD-Cold & Amb.'!G15 -> 2 | H15: ='BOD-Cold & Amb.'!H15 -> 1 | I15: ='BOD-Cold & Amb.'!I15 -> 2 | J15: ='BOD-Cold & Amb.'!J15 -> 1.75 | K15: ='BOD-Cold & Amb.'!K15 -> 2 | ... AJ15: ='BOD-Cold & Amb.'!AJ15 -> 3.5 | AL15: ='BOD-Cold & Amb.'!AL15 -> 5900
C16: ='Input BOD'!C16 -> 7 | D16: ='BOD-Cold & Amb.'!D16 -> excel | E16: ='BOD-Cold & Amb.'!E16 -> 1 | F16: ='BOD-Cold & Amb.'!F16 -> 1 | G16: ='BOD-Cold & Amb.'!G16 -> 2 | H16: ='BOD-Cold & Amb.'!H16 -> 1 | I16: ='BOD-Cold & Amb.'!I16 -> 2 | J16: ='BOD-Cold & Amb.'!J16 -> 1.75 | K16: ='BOD-Cold & Amb.'!K16 -> 2 | ... AJ16: ='BOD-Cold & Amb.'!AJ16 -> 3.5
C17: ='Input BOD'!C17 -> 8 | D17: ='BOD-Cold & Amb.'!D17 -> word | E17: ='BOD-Cold & Amb.'!E17 -> 1 | F17: ='BOD-Cold & Amb.'!F17 -> 1 | G17: ='BOD-Cold & Amb.'!G17 -> 2 | H17: ='BOD-Cold & Amb.'!H17 -> 1 | I17: ='BOD-Cold & Amb.'!I17 -> 2 | J17: ='BOD-Cold & Amb.'!J17 -> 1.75 | K17: ='BOD-Cold & Amb.'!K17 -> 2 | ... AJ17: ='BOD-Cold & Amb.'!AJ17 -> 3.5
C18: ='Input BOD'!C18 -> 9 | D18: ='BOD-Cold & Amb.'!D18 -> java | E18: ='BOD-Cold & Amb.'!E18 -> 1 | F18: ='BOD-Cold & Amb.'!F18 -> 1 | G18: ='BOD-Cold & Amb.'!G18 -> 2 | H18: ='BOD-Cold & Amb.'!H18 -> 1 | I18: ='BOD-Cold & Amb.'!I18 -> 2 | J18: ='BOD-Cold & Amb.'!J18 -> 1.75 | K18: ='BOD-Cold & Amb.'!K18 -> 2 | ... AJ18: ='BOD-Cold & Amb.'!AJ18 -> 3.5
C19: ='Input BOD'!C19 -> 10 | D19: ='BOD-Cold & Amb.'!D19 -> 12345 | E19: ='BOD-Cold & Amb.'!E19 -> 1 | F19: ='BOD-Cold & Amb.'!F19 -> 1 | G19: ='BOD-Cold & Amb.'!G19 -> 2 | H19: ='BOD-Cold & Amb.'!H19 -> 1 | I19: ='BOD-Cold & Amb.'!I19 -> 2 | J19: ='BOD-Cold & Amb.'!J19 -> 1.75 | K19: ='BOD-Cold & Amb.'!K19 -> 2 | ... AJ19: ='BOD-Cold & Amb.'!AJ19 -> 3.5 | AL19: ='BOD-Cold & Amb.'!AL19 -> 5500
C20: ='Input BOD'!C20 -> 11 | D20: ='BOD-Cold & Amb.'!D20 -> cvdwvjvq | E20: ='BOD-Cold & Amb.'!E20 -> 1 | F20: ='BOD-Cold & Amb.'!F20 -> 1 | G20: ='BOD-Cold & Amb.'!G20 -> 2 | H20: ='BOD-Cold & Amb.'!H20 -> 1 | I20: ='BOD-Cold & Amb.'!I20 -> 2 | J20: ='BOD-Cold & Amb.'!J20 -> 1.75 | K20: ='BOD-Cold & Amb.'!K20 -> 2 | ... AJ20: ='BOD-Cold & Amb.'!AJ20 -> 3.5
C21: ='Input BOD'!C21 -> 12 | D21: ='BOD-Cold & Amb.'!D21 -> jcvbbvk | E21: ='BOD-Cold & Amb.'!E21 -> 1 | F21: ='BOD-Cold & Amb.'!F21 -> 1 | G21: ='BOD-Cold & Amb.'!G21 -> 2 | H21: ='BOD-Cold & Amb.'!H21 -> 1 | I21: ='BOD-Cold & Amb.'!I21 -> 2 | J21: ='BOD-Cold & Amb.'!J21 -> 1.75 | K21: ='BOD-Cold & Amb.'!K21 -> 2 | ... AJ21: ='BOD-Cold & Amb.'!AJ21 -> 3.5
C22: ='Input BOD'!C22 -> 13 | D22: ='BOD-Cold & Amb.'!D22 -> vbwbvb | E22: ='BOD-Cold & Amb.'!E22 -> 1 | F22: ='BOD-Cold & Amb.'!F22 -> 1 | G22: ='BOD-Cold & Amb.'!G22 -> 2 | H22: ='BOD-Cold & Amb.'!H22 -> 1 | I22: ='BOD-Cold & Amb.'!I22 -> 2 | J22: ='BOD-Cold & Amb.'!J22 -> 1.75 | K22: ='BOD-Cold & Amb.'!K22 -> 2 | ... AJ22: ='BOD-Cold & Amb.'!AJ22 -> 3.5
C23: ='Input BOD'!C23 -> 14 | D23: ='BOD-Cold & Amb.'!D23 -> b cjvjvve | E23: ='BOD-Cold & Amb.'!E23 -> 1 | F23: ='BOD-Cold & Amb.'!F23 -> 1 | G23: ='BOD-Cold & Amb.'!G23 -> 2 | H23: ='BOD-Cold & Amb.'!H23 -> 1 | I23: ='BOD-Cold & Amb.'!I23 -> 2 | J23: ='BOD-Cold & Amb.'!J23 -> 1.75 | K23: ='BOD-Cold & Amb.'!K23 -> 2 | ... AJ23: ='BOD-Cold & Amb.'!AJ23 -> 3.5
C24: ='Input BOD'!C24 -> 15 | D24: ='BOD-Cold & Amb.'!D24 -> ifhiuhfigi | E24: ='BOD-Cold & Amb.'!E24 -> 1 | F24: ='BOD-Cold & Amb.'!F24 -> 1 | G24: ='BOD-Cold & Amb.'!G24 -> 2 | H24: ='BOD-Cold & Amb.'!H24 -> 1 | I24: ='BOD-Cold & Amb.'!I24 -> 2 | J24: ='BOD-Cold & Amb.'!J24 -> 1.75 | K24: ='BOD-Cold & Amb.'!K24 -> 2 | ... AJ24: ='BOD-Cold & Amb.'!AJ24 -> 3.5
C25: ='Input BOD'!C25 -> 16 | D25: ='BOD-Cold & Amb.'!D25 -> hbhwbfb | E25: ='BOD-Cold & Amb.'!E25 -> 1 | F25: ='BOD-Cold & Amb.'!F25 -> 1 | G25: ='BOD-Cold & Amb.'!G25 -> 2 | H25: ='BOD-Cold & Amb.'!H25 -> 1 | I25: ='BOD-Cold & Amb.'!I25 -> 2 | J25: ='BOD-Cold & Amb.'!J25 -> 1.75 | K25: ='BOD-Cold & Amb.'!K25 -> 2 | ... AJ25: ='BOD-Cold & Amb.'!AJ25 -> 3.5
C26: =IF(D26<>"",COUNTA($D$10:D26),"") | X26: =SUM(X10:X25) -> 172.16 | Y26: =SUM(Y10:Y25) -> 1129.3696 | Z26: =SUM(Z10:Z25) -> 225.87392 | AA26: =SUM(AA10:AA25) -> 22.587392 | AB26: =SUM(AB10:AB25) -> 0 | AC26: =SUM(AC10:AC25) -> 1.5729225 | AD26: =SUM(AD10:AD25) -> 15600 | AE26: =SUM(AE10:AE25) -> 15600 | ... AG26: =SUM(AG10:AG25) -> 56 | AI26: =SUM(AI10:AI25) -> 40 | AJ26: =SUM(AJ10:AJ25) -> 56
C27: =IF(D27<>"",COUNTA($D$10:D27),"")
C28: ="Zoning Area AHU - " & INT((ROW()-8)/20)+1 & " " &IF(AQ30>0,"Air-Conditioning System " & IF(AH30="D","(DX)",IF(AH30="C","(Chilled Water)","")),IF(AND(N30="Amb",AQ30=0),"Ventilation System","Refer")) -> #DIV/0! | AS28: Chilled Water Details | AW28: Hot Water/Steam Details
D29: Room Name | E29: Length in mtrs | F29: Width in mtrs | G29: Height in mtrs | H29: People in Nos | I29: Eqpt. Load in KW | J29: Lighting in W/Sft | K29: No.of Inf./Hr | L29: Fresh Air | M29: Exhaust | N29: T ˚C (Required inside) | O29: RH(in) +/- 5% | P29: Peak Max Temp.(Out) in ˚C | Q29: RH(Out) in +/- 5% | R29: Class | S29: ACPH | T29: Peak Min Temp.(Out) in ˚C | U29: RH(Out) +/- 5% | V29: Class | W29: ACPH | X29: Area | Y29: Volume | Z29: Room Cfm | AA29: FA | AB29: EA | AC29: Rem. Water vapour Kg/hr | AD29: Deh. Cfm | AE29: Res. Cfm | AF29: Room Terminal Supply Module in Sft | AG29: Res. Cooling Load in TR | AH29: Chilled Water (C) OR DX (D) | AI29: Room AC load in TR | AJ29: Cfm AC load in TR | AK29: AHU Cfm | AL29: AHU Size | AM29: Static Pressure | AN29: Blower Model BDB | AO29: Motor Selected in Hp | AP29: No. of Rows of Cooling Coil | AQ29: AHU Cooling Load in TR | AR29: No. Of Stages of Filtr. | AS29: Chilled water in GPM | AT29: Chilled water in L/s | AU29: Flow Velocity in m/s | AV29: Pipe Size in mm | AW29: Hot Water/Steam in GPM | AX29: Hot water/Steam in L/s | AY29: Flow Velocity | AZ29: Pipe Size
C30: =IF(D30<>"",COUNTA($D$10:D30),"") -> 18 | D30: Clean Room 10 | E30: 3 | F30: 3 | G30: 2.4 | H30: 1 | I30: 2 | J30: 1.75 | K30: 3 | L30: 0.1 | M30: 0 | N30: 24 | O30: 50 | P30: 45 | Q30: 85 | R30: ISO 6 | S30: 160 | T30: 0 | U30: 100 | V30: =R30 -> ISO 6 | W30: =S30 -> 160 | X30: =E30*F30*10.76 -> 96.84 | Y30: =X30*G30*3.28 -> 762.32448 | Z30: =Y30*S30/60 -> 2032.8653 | AA30: =Z30*L30 -> 203.28653 | AB30: =IF(N30="Amb",Z30,Z30*M30) -> 0 | AC30: =IF(ISNUMBER(N30), (AA30*0.075*60/2.20462)*BP30/7000, "Ambient") -> 0 | AD30: =IF(ISNUMBER(N30), CEILING(CF30/(0.68*BP30),25), "Ambient") -> #DIV/0! | AE30: =CEILING(MAX((Z30+AA30),AD30),25) -> #DIV/0! | AF30: =CEILING(IF(OR($R30="ISO 6",$R30="GRADE B",$R30="1K",$R30=1000),AE30*1/175,IF(OR($R30="ISO 5",$R30="GRADE A",$R30=100),AE30*1/100,IF(OR($R30="ISO 7",$R30="GRADE C",$R30="10K",$R30=10000),$AE30*1/250,IF(OR($R30="ISO 8",$R30="GRADE D",$R30="100K",$R30=100000),$AE30*1/250,IF(OR($R30="NC",$R30="20 Micron",$R30="5 Micron",$R30="N C"),$AE30*1/350,0))))),2) -> #DIV/0! | AG30: =IF(ISNUMBER(N30), CEILING(MAX(AI30,AJ30),0.5), "Ambient") -> #DIV/0! | AH30: C | AI30: =IF(ISNUMBER(N30), CEILING(CE30/12000,0.5), "Ambient") -> 0 | AJ30: =IF(ISNUMBER(N30),CEILING(AE30/(IF(AH30="C",400,300)),0.5), "Ambient") -> #DIV/0! | AK30: =CEILING(SUM(AE30:AE45),250) -> #DIV/0! | AL30: W | AM30: 150 | AN30: =IF(AK30<=1300,200,IF(AK30<=1600,225,IF(AK30<=2100,250,IF(AK30<=2700,280,IF(AK30<=3450,315,IF(AK30<=4250,355,IF(AK30<=5250,400,IF(AK30<=6750,450,IF(AK30<=8500,500,IF(AK30<=10750,560,IF(AK30<=13500,630,IF(AK30<=17000,710,IF(AK30<=21500,800,IF(AK30<=27000,900,IF(AK30<=34000,1000,IF(AK30<=43000,1120,IF(AK30<=49000,1200,IF(AK30<=68000,1450,"Refer")))))))))))))))))) -> #DIV/0! | AO30: =IF(AK30*AM30/(6356*0.7*0.9*1.1*25.4)<=1,1,IF(AK30*AM30/(6356*0.7*0.9*1.1*25.4)<=1.5,1.5,IF(AK30*AM30/(6356*0.7*0.9*1.1*25.4)<=2,2,IF(AK30*AM30/(6356*0.7*0.9*1.1*25.4)<=3,3,IF(AK30*AM30/(6356*0.7*0.9*1.1*25.4)<=5,5,IF(AK30*AM30/(6356*0.7*0.9*1.1*25.4)<=7.5,7.5,IF(AK30*AM30/(6356*0.7*0.9*1.1*25.4)<=10,10,IF(AK30*AM30/(6356*0.7*0.9*1.1*25.4)<=12.5,12.5,IF(AK30*AM30/(6356*0.7*0.9*1.1*25.4)<=15,15,IF(AK30*AM30/(6356*0.7*0.9*1.1*25.4)<=20,20,IF(AK30*AM30/(6356*0.7*0.9*1.1*25.4)<=25,25,IF(AK30*AM30/(6356*0.7*0.9*1.1*25.4)<=30,30,IF(AK30*AM30/(6356*0.7*0.9*1.1*25.4)<=40,40,IF(AK30*AM30/(6356*0.7*0.9*1.1*25.4)<=50,50,IF(AK30*AM30/(6356*0.7*0.9*1.1*25.4)<=60,60,IF(AK30*AM30/(6356*0.7*0.9*1.1*25.4)<=75,75,"Refer")))))))))))))))) -> #DIV/0! | AP30: =IF(AND(AQ30=0, N30="Amb"), "Amb",IF((AL31-250)*(AL33-150)*10.76/(1000*1000) >= MAX(AI46,AJ46), 4,IF((AL31-250)*(AL33-150)*10.76*1.5/(1000*1000) >= MAX(AI46,AJ46), 6,IF((AL31-250)*(AL33-150)*10.76*2/(1000*1000) >= MAX(AI46,AJ46), 8, 0)) ) ) -> #DIV/0! | AQ30: =AG46 -> #DIV/0! | AR30: =_xlfn.SWITCH(TRIM(UPPER(R30)),"ISO 9", 3,"ISO 8", 4,"Grade D", 4,"Class 100,000", 4,"Class 100K", 4,"ISO 7", 3,"Grade C", 3,"Class 10,000", 3,"Class 10K", 3,"ISO 6", 3,"Class 1,000", 3,"Class 1K", 3,"ISO 5", 4,"Grade A", 4,"Grade B", 4,"Class 100", 4,"ISO 4", 3,"ISO 3", 4,"ISO 2", 4,"ISO 1", 4,"NCV20",1,"NCV-10",2,"NCV-5",3,"NCAC-10",1,"NCAC-5",2,"NCAC-1",3,3) -> 3 | AS30: =MAX(AI46,AJ46)*24/6 -> #DIV/0! | AT30: =AS30*0.06309 -> #DIV/0! | AU30: 2 | AV30: =SQRT((4*AS30*0.00006309)/(3.14*AU30))*1000 -> #DIV/0!
C31: =IF(D31<>"",COUNTA($D$10:D31),"") -> 19 | D31: Clean Room 11 | E31: 1.8 | F31: 2.2 | G31: 2.4 | H31: 2 | I31: 1 | J31: 1.75 | K31: 3 | L31: 0.1 | M31: 0 | N31: 24 | O31: 50 | P31: 45 | Q31: 85 | R31: ISO 6 | S31: 160 | T31: 0 | U31: 100 | V31: =R31 -> ISO 6 | W31: =S31 -> 160 | X31: =E31*F31*10.76 -> 42.6096 | Y31: =X31*G31*3.28 -> 335.42277 | Z31: =Y31*S31/60 -> 894.46072 | AA31: =Z31*L31 -> 89.446072 | AB31: =IF(N31="Amb",Z31,Z31*M31) -> 0 | AC31: =IF(ISNUMBER(N31), (AA31*0.075*60/2.20462)*BP31/7000, "Ambient") -> 0 | AD31: =IF(ISNUMBER(N31), CEILING(CF31/(0.68*BP31),25), "Ambient") -> #DIV/0! | AE31: =CEILING(MAX((Z31+AA31),AD31),25) -> #DIV/0! | AF31: =CEILING(IF(OR($R31="ISO 6",$R31="GRADE B",$R31="1K",$R31=1000),AE31*1/175,IF(OR($R31="ISO 5",$R31="GRADE A",$R31=100),AE31*1/100,IF(OR($R31="ISO 7",$R31="GRADE C",$R31="10K",$R31=10000),$AE31*1/250,IF(OR($R31="ISO 8",$R31="GRADE D",$R31="100K",$R31=100000),$AE31*1/250,IF(OR($R31="NC",$R31="20 Micron",$R31="5 Micron",$R31="N C"),$AE31*1/350,0))))),2) -> #DIV/0! | AG31: =IF(ISNUMBER(N31), CEILING(MAX(AI31,AJ31),0.5), "Ambient") -> #DIV/0! | AH31: C | AI31: =IF(ISNUMBER(N31), CEILING(CE31/12000,0.5), "Ambient") -> 0 | AJ31: =IF(ISNUMBER(N31),CEILING(AE31/(IF(AH31="C",400,300)),0.5), "Ambient") -> #DIV/0! | AL31: =IF(AK30<=2000,950,(IF(AK30<=3000,1150,(IF(AK30<=8000,1550,(IF(AK30<=10000,1750,(IF(AK30<=18000,2050,(IF(AK30<=32000,2900,(IF(AK30<=40000,3600,4000))))))))))))) -> #DIV/0!
C32: =IF(D32<>"",COUNTA($D$10:D32),"") -> 20 | D32: Clean Room 12 | E32: 1.5 | F32: 2.8 | G32: 2.4 | H32: 2 | I32: 3 | J32: 1.75 | K32: 3 | L32: 0.1 | M32: 0 | N32: 24 | O32: 50 | P32: 45 | Q32: 85 | R32: ISO 6 | S32: 160 | T32: 0 | U32: 100 | V32: =R32 -> ISO 6 | W32: =S32 -> 160 | X32: =E32*F32*10.76 -> 45.192 | Y32: =X32*G32*3.28 -> 355.75142 | Z32: =Y32*S32/60 -> 948.67046 | AA32: =Z32*L32 -> 94.867046 | AB32: =IF(N32="Amb",Z32,Z32*M32) -> 0 | AC32: =IF(ISNUMBER(N32), (AA32*0.075*60/2.20462)*BP32/7000, "Ambient") -> 0 | AD32: =IF(ISNUMBER(N32), CEILING(CF32/(0.68*BP32),25), "Ambient") -> #DIV/0! | AE32: =CEILING(MAX((Z32+AA32),AD32),25) -> #DIV/0! | AF32: =CEILING(IF(OR($R32="ISO 6",$R32="GRADE B",$R32="1K",$R32=1000),AE32*1/175,IF(OR($R32="ISO 5",$R32="GRADE A",$R32=100),AE32*1/100,IF(OR($R32="ISO 7",$R32="GRADE C",$R32="10K",$R32=10000),$AE32*1/250,IF(OR($R32="ISO 8",$R32="GRADE D",$R32="100K",$R32=100000),$AE32*1/250,IF(OR($R32="NC",$R32="20 Micron",$R32="5 Micron",$R32="N C"),$AE32*1/350,0))))),2) -> #DIV/0! | AG32: =IF(ISNUMBER(N32), CEILING(MAX(AI32,AJ32),0.5), "Ambient") -> #DIV/0! | AH32: C | AI32: =IF(ISNUMBER(N32), CEILING(CE32/12000,0.5), "Ambient") -> 0 | AJ32: =IF(ISNUMBER(N32),CEILING(AE32/(IF(AH32="C",400,300)),0.5), "Ambient") -> #DIV/0! | AL32: H
C33: =IF(D33<>"",COUNTA($D$10:D33),"") -> 21 | D33: Clean Room 13 | E33: 2.1 | F33: 3.5 | G33: 2.4 | H33: 0 | I33: 1 | J33: 1.75 | K33: 3 | L33: 0.1 | M33: 0 | N33: 24 | O33: 50 | P33: 45 | Q33: 85 | R33: ISO 6 | S33: 160 | T33: 0 | U33: 100 | V33: =R33 -> ISO 6 | W33: =S33 -> 160 | X33: =E33*F33*10.76 -> 79.086 | Y33: =X33*G33*3.28 -> 622.56499 | Z33: =Y33*S33/60 -> 1660.1733 | AA33: =Z33*L33 -> 166.01733 | AB33: =IF(N33="Amb",Z33,Z33*M33) -> 0 | AC33: =IF(ISNUMBER(N33), (AA33*0.075*60/2.20462)*BP33/7000, "Ambient") -> 0 | AD33: =IF(ISNUMBER(N33), CEILING(CF33/(0.68*BP33),25), "Ambient") -> #DIV/0! | AE33: =CEILING(MAX((Z33+AA33),AD33),25) -> #DIV/0! | AF33: =CEILING(IF(OR($R33="ISO 6",$R33="GRADE B",$R33="1K",$R33=1000),AE33*1/175,IF(OR($R33="ISO 5",$R33="GRADE A",$R33=100),AE33*1/100,IF(OR($R33="ISO 7",$R33="GRADE C",$R33="10K",$R33=10000),$AE33*1/250,IF(OR($R33="ISO 8",$R33="GRADE D",$R33="100K",$R33=100000),$AE33*1/250,IF(OR($R33="NC",$R33="20 Micron",$R33="5 Micron",$R33="N C"),$AE33*1/350,0))))),2) -> #DIV/0! | AG33: =IF(ISNUMBER(N33), CEILING(MAX(AI33,AJ33),0.5), "Ambient") -> #DIV/0! | AH33: C | AI33: =IF(ISNUMBER(N33), CEILING(CE33/12000,0.5), "Ambient") -> 0 | AJ33: =IF(ISNUMBER(N33),CEILING(AE33/(IF(AH33="C",400,300)),0.5), "Ambient") -> #DIV/0! | AL33: =IF(AK30<=2000,950,(IF(AK30<=4000,1100,(IF(AK30<=6000,1250,(IF(AK30<=10000,1550,(IF(AK30<=15000,1750,(IF(AK30<=24000,2050,(IF(AK30<=40000,2900,3600))))))))))))) -> #DIV/0!
C34: =IF(D34<>"",COUNTA($D$10:D34),"") -> 22 | D34: Clean Room 14 | E34: 2.7 | F34: 4 | G34: 2.4 | H34: 2 | I34: 1 | J34: 1.75 | K34: 3 | L34: 0.1 | M34: 0 | N34: 24 | O34: 50 | P34: 45 | Q34: 85 | R34: ISO 6 | S34: 160 | T34: 0 | U34: 100 | V34: =R34 -> ISO 6 | W34: =S34 -> 160 | X34: =E34*F34*10.76 -> 116.208 | Y34: =X34*G34*3.28 -> 914.78938 | Z34: =Y34*S34/60 -> 2439.4383 | AA34: =Z34*L34 -> 243.94383 | AB34: =IF(N34="Amb",Z34,Z34*M34) -> 0 | AC34: =IF(ISNUMBER(N34), (AA34*0.075*60/2.20462)*BP34/7000, "Ambient") -> 0 | AD34: =IF(ISNUMBER(N34), CEILING(CF34/(0.68*BP34),25), "Ambient") -> #DIV/0! | AE34: =CEILING(MAX((Z34+AA34),AD34),25) -> #DIV/0! | AF34: =CEILING(IF(OR($R34="ISO 6",$R34="GRADE B",$R34="1K",$R34=1000),AE34*1/175,IF(OR($R34="ISO 5",$R34="GRADE A",$R34=100),AE34*1/100,IF(OR($R34="ISO 7",$R34="GRADE C",$R34="10K",$R34=10000),$AE34*1/250,IF(OR($R34="ISO 8",$R34="GRADE D",$R34="100K",$R34=100000),$AE34*1/250,IF(OR($R34="NC",$R34="20 Micron",$R34="5 Micron",$R34="N C"),$AE34*1/350,0))))),2) -> #DIV/0! | AG34: =IF(ISNUMBER(N34), CEILING(MAX(AI34,AJ34),0.5), "Ambient") -> #DIV/0! | AH34: C | AI34: =IF(ISNUMBER(N34), CEILING(CE34/12000,0.5), "Ambient") -> 0 | AJ34: =IF(ISNUMBER(N34),CEILING(AE34/(IF(AH34="C",400,300)),0.5), "Ambient") -> #DIV/0! | AL34: L
C35: =IF(D35<>"",COUNTA($D$10:D35),"") -> 23 | D35: Clean Room 15 | E35: 3.8 | F35: 4.2 | G35: 2.4 | H35: 3 | I35: 3 | J35: 1.75 | K35: 3 | L35: 0.1 | M35: 0 | N35: 24 | O35: 50 | P35: 45 | Q35: 85 | R35: ISO 6 | S35: 160 | T35: 0 | U35: 100 | V35: =R35 -> ISO 6 | W35: =S35 -> 160 | X35: =E35*F35*10.76 -> 171.7296 | Y35: =X35*G35*3.28 -> 1351.8554 | Z35: =Y35*S35/60 -> 3604.9478 | AA35: =Z35*L35 -> 360.49478 | AB35: =IF(N35="Amb",Z35,Z35*M35) -> 0 | AC35: =IF(ISNUMBER(N35), (AA35*0.075*60/2.20462)*BP35/7000, "Ambient") -> 0 | AD35: =IF(ISNUMBER(N35), CEILING(CF35/(0.68*BP35),25), "Ambient") -> #DIV/0! | AE35: =CEILING(MAX((Z35+AA35),AD35),25) -> #DIV/0! | AF35: =CEILING(IF(OR($R35="ISO 6",$R35="GRADE B",$R35="1K",$R35=1000),AE35*1/175,IF(OR($R35="ISO 5",$R35="GRADE A",$R35=100),AE35*1/100,IF(OR($R35="ISO 7",$R35="GRADE C",$R35="10K",$R35=10000),$AE35*1/250,IF(OR($R35="ISO 8",$R35="GRADE D",$R35="100K",$R35=100000),$AE35*1/250,IF(OR($R35="NC",$R35="20 Micron",$R35="5 Micron",$R35="N C"),$AE35*1/350,0))))),2) -> #DIV/0! | AG35: =IF(ISNUMBER(N35), CEILING(MAX(AI35,AJ35),0.5), "Ambient") -> #DIV/0! | AH35: C | AI35: =IF(ISNUMBER(N35), CEILING(CE35/12000,0.5), "Ambient") -> 0 | AJ35: =IF(ISNUMBER(N35),CEILING(AE35/(IF(AH35="C",400,300)),0.5), "Ambient") -> #DIV/0! | AL35: =IF(AL39<4000,AL39,AL39+400) -> #DIV/0!
C36: =IF(D36<>"",COUNTA($D$10:D36),"") -> 24 | D36: Clean Room 16 | E36: 3.1 | F36: 2.6 | G36: 2.4 | H36: 2 | I36: 1 | J36: 1.75 | K36: 3 | L36: 0.1 | M36: 0 | N36: 24 | O36: 50 | P36: 45 | Q36: 85 | R36: ISO 6 | S36: 160 | T36: 0 | U36: 100 | V36: =R36 -> ISO 6 | W36: =S36 -> 160 | X36: =E36*F36*10.76 -> 86.7256 | Y36: =X36*G36*3.28 -> 682.70392 | Z36: =Y36*S36/60 -> 1820.5438 | AA36: =Z36*L36 -> 182.05438 | AB36: =IF(N36="Amb",Z36,Z36*M36) -> 0 | AC36: =IF(ISNUMBER(N36), (AA36*0.075*60/2.20462)*BP36/7000, "Ambient") -> 0 | AD36: =IF(ISNUMBER(N36), CEILING(CF36/(0.68*BP36),25), "Ambient") -> #DIV/0! | AE36: =CEILING(MAX((Z36+AA36),AD36),25) -> #DIV/0! | AF36: =CEILING(IF(OR($R36="ISO 6",$R36="GRADE B",$R36="1K",$R36=1000),AE36*1/175,IF(OR($R36="ISO 5",$R36="GRADE A",$R36=100),AE36*1/100,IF(OR($R36="ISO 7",$R36="GRADE C",$R36="10K",$R36=10000),$AE36*1/250,IF(OR($R36="ISO 8",$R36="GRADE D",$R36="100K",$R36=100000),$AE36*1/250,IF(OR($R36="NC",$R36="20 Micron",$R36="5 Micron",$R36="N C"),$AE36*1/350,0))))),2) -> #DIV/0! | AG36: =IF(ISNUMBER(N36), CEILING(MAX(AI36,AJ36),0.5), "Ambient") -> #DIV/0! | AH36: C | AI36: =IF(ISNUMBER(N36), CEILING(CE36/12000,0.5), "Ambient") -> 0 | AJ36: =IF(ISNUMBER(N36),CEILING(AE36/(IF(AH36="C",400,300)),0.5), "Ambient") -> #DIV/0!
C37: =IF(D37<>"",COUNTA($D$10:D37),"") -> 25 | D37: Clean Room 17 | E37: 1.9 | F37: 2.4 | G37: 2.4 | H37: 3 | I37: 2 | J37: 1.75 | K37: 3 | L37: 0.1 | M37: 0 | N37: 24 | O37: 50 | P37: 45 | Q37: 85 | R37: ISO 6 | S37: 160 | T37: 0 | U37: 100 | V37: =R37 -> ISO 6 | W37: =S37 -> 160 | X37: =E37*F37*10.76 -> 49.0656 | Y37: =X37*G37*3.28 -> 386.2444 | Z37: =Y37*S37/60 -> 1029.9851 | AA37: =Z37*L37 -> 102.99851 | AB37: =IF(N37="Amb",Z37,Z37*M37) -> 0 | AC37: =IF(ISNUMBER(N37), (AA37*0.075*60/2.20462)*BP37/7000, "Ambient") -> 0 | AD37: =IF(ISNUMBER(N37), CEILING(CF37/(0.68*BP37),25), "Ambient") -> #DIV/0! | AE37: =CEILING(MAX((Z37+AA37),AD37),25) -> #DIV/0! | AF37: =CEILING(IF(OR($R37="ISO 6",$R37="GRADE B",$R37="1K",$R37=1000),AE37*1/175,IF(OR($R37="ISO 5",$R37="GRADE A",$R37=100),AE37*1/100,IF(OR($R37="ISO 7",$R37="GRADE C",$R37="10K",$R37=10000),$AE37*1/250,IF(OR($R37="ISO 8",$R37="GRADE D",$R37="100K",$R37=100000),$AE37*1/250,IF(OR($R37="NC",$R37="20 Micron",$R37="5 Micron",$R37="N C"),$AE37*1/350,0))))),2) -> #DIV/0! | AG37: =IF(ISNUMBER(N37), CEILING(MAX(AI37,AJ37),0.5), "Ambient") -> #DIV/0! | AH37: C | AI37: =IF(ISNUMBER(N37), CEILING(CE37/12000,0.5), "Ambient") -> 0 | AJ37: =IF(ISNUMBER(N37),CEILING(AE37/(IF(AH37="C",400,300)),0.5), "Ambient") -> #DIV/0!
C38: =IF(D38<>"",COUNTA($D$10:D38),"") -> 26 | D38: Clean Room 18 | E38: 3 | F38: 2.9 | G38: 2.4 | H38: 2 | I38: 1 | J38: 1.75 | K38: 3 | L38: 0.1 | M38: 0 | N38: 24 | O38: 50 | P38: 45 | Q38: 85 | R38: ISO 6 | S38: 160 | T38: 0 | U38: 100 | V38: =R38 -> ISO 6 | W38: =S38 -> 160 | X38: =E38*F38*10.76 -> 93.612 | Y38: =X38*G38*3.28 -> 736.91366 | Z38: =Y38*S38/60 -> 1965.1031 | AA38: =Z38*L38 -> 196.51031 | AB38: =IF(N38="Amb",Z38,Z38*M38) -> 0 | AC38: =IF(ISNUMBER(N38), (AA38*0.075*60/2.20462)*BP38/7000, "Ambient") -> 0 | AD38: =IF(ISNUMBER(N38), CEILING(CF38/(0.68*BP38),25), "Ambient") -> #DIV/0! | AE38: =CEILING(MAX((Z38+AA38),AD38),25) -> #DIV/0! | AF38: =CEILING(IF(OR($R38="ISO 6",$R38="GRADE B",$R38="1K",$R38=1000),AE38*1/175,IF(OR($R38="ISO 5",$R38="GRADE A",$R38=100),AE38*1/100,IF(OR($R38="ISO 7",$R38="GRADE C",$R38="10K",$R38=10000),$AE38*1/250,IF(OR($R38="ISO 8",$R38="GRADE D",$R38="100K",$R38=100000),$AE38*1/250,IF(OR($R38="NC",$R38="20 Micron",$R38="5 Micron",$R38="N C"),$AE38*1/350,0))))),2) -> #DIV/0! | AG38: =IF(ISNUMBER(N38), CEILING(MAX(AI38,AJ38),0.5), "Ambient") -> #DIV/0! | AH38: C | AI38: =IF(ISNUMBER(N38), CEILING(CE38/12000,0.5), "Ambient") -> 0 | AJ38: =IF(ISNUMBER(N38),CEILING(AE38/(IF(AH38="C",400,300)),0.5), "Ambient") -> #DIV/0!
C39: =IF(D39<>"",COUNTA($D$10:D39),"") -> 27 | D39: Clean Room 19 | E39: 2.4 | F39: 2 | G39: 2.4 | H39: 2 | I39: 1 | J39: 1.75 | K39: 3 | L39: 0.1 | M39: 0 | N39: 24 | O39: 50 | P39: 45 | Q39: 85 | R39: ISO 6 | S39: 160 | T39: 0 | U39: 100 | V39: =R39 -> ISO 6 | W39: =S39 -> 160 | X39: =E39*F39*10.76 -> 51.648 | Y39: =X39*G39*3.28 -> 406.57306 | Z39: =Y39*S39/60 -> 1084.1948 | AA39: =Z39*L39 -> 108.41948 | AB39: =IF(N39="Amb",Z39,Z39*M39) -> 0 | AC39: =IF(ISNUMBER(N39), (AA39*0.075*60/2.20462)*BP39/7000, "Ambient") -> 0 | AD39: =IF(ISNUMBER(N39), CEILING(CF39/(0.68*BP39),25), "Ambient") -> #DIV/0! | AE39: =CEILING(MAX((Z39+AA39),AD39),25) -> #DIV/0! | AF39: =CEILING(IF(OR($R39="ISO 6",$R39="GRADE B",$R39="1K",$R39=1000),AE39*1/175,IF(OR($R39="ISO 5",$R39="GRADE A",$R39=100),AE39*1/100,IF(OR($R39="ISO 7",$R39="GRADE C",$R39="10K",$R39=10000),$AE39*1/250,IF(OR($R39="ISO 8",$R39="GRADE D",$R39="100K",$R39=100000),$AE39*1/250,IF(OR($R39="NC",$R39="20 Micron",$R39="5 Micron",$R39="N C"),$AE39*1/350,0))))),2) -> #DIV/0! | AG39: =IF(ISNUMBER(N39), CEILING(MAX(AI39,AJ39),0.5), "Ambient") -> #DIV/0! | AH39: C | AI39: =IF(ISNUMBER(N39), CEILING(CE39/12000,0.5), "Ambient") -> 0 | AJ39: =IF(ISNUMBER(N39),CEILING(AE39/(IF(AH39="C",400,300)),0.5), "Ambient") -> #DIV/0! | AL39: =IF(AN30<=315,1600,(IF(AN30=355,1650,(IF(AN30=400,1650,(IF(AN30=450,1700,(IF(AN30=500,1700,(IF(AN30=560,1800,(IF(AN30=630,2000,(IF(AN30=710,2200,2500)))))))))))))))+IF(AR30=2,1800,(IF(AR30=3,2300,(IF(AR30=4,3300,0)))))+IF(AP30<=4,600,(IF(AP30<=6,800,(IF(AP30<=8,1000,1200))))) -> #DIV/0!
C40: =IF(D40<>"",COUNTA($D$10:D40),"") -> 28 | D40: Clean Room 20 | E40: 2.1 | F40: 1.8 | G40: 2.4 | H40: 2 | I40: 1 | J40: 1.75 | K40: 3 | L40: 0.1 | M40: 0 | N40: 24 | O40: 50 | P40: 45 | Q40: 85 | R40: ISO 6 | S40: 160 | T40: 0 | U40: 100 | V40: =R40 -> ISO 6 | W40: =S40 -> 160 | X40: =E40*F40*10.76 -> 40.6728 | Y40: =X40*G40*3.28 -> 320.17628 | Z40: =Y40*S40/60 -> 853.80342 | AA40: =Z40*L40 -> 85.380342 | AB40: =IF(N40="Amb",Z40,Z40*M40) -> 0 | AC40: =IF(ISNUMBER(N40), (AA40*0.075*60/2.20462)*BP40/7000, "Ambient") -> 0 | AD40: =IF(ISNUMBER(N40), CEILING(CF40/(0.68*BP40),25), "Ambient") -> #DIV/0! | AE40: =CEILING(MAX((Z40+AA40),AD40),25) -> #DIV/0! | AF40: =CEILING(IF(OR($R40="ISO 6",$R40="GRADE B",$R40="1K",$R40=1000),AE40*1/175,IF(OR($R40="ISO 5",$R40="GRADE A",$R40=100),AE40*1/100,IF(OR($R40="ISO 7",$R40="GRADE C",$R40="10K",$R40=10000),$AE40*1/250,IF(OR($R40="ISO 8",$R40="GRADE D",$R40="100K",$R40=100000),$AE40*1/250,IF(OR($R40="NC",$R40="20 Micron",$R40="5 Micron",$R40="N C"),$AE40*1/350,0))))),2) -> #DIV/0! | AG40: =IF(ISNUMBER(N40), CEILING(MAX(AI40,AJ40),0.5), "Ambient") -> #DIV/0! | AH40: C | AI40: =IF(ISNUMBER(N40), CEILING(CE40/12000,0.5), "Ambient") -> 0 | AJ40: =IF(ISNUMBER(N40),CEILING(AE40/(IF(AH40="C",400,300)),0.5), "Ambient") -> #DIV/0!
C41: =IF(D41<>"",COUNTA($D$10:D41),"") -> 29 | D41: Clean Room 21 | E41: 1.8 | F41: 1.9 | G41: 2.4 | H41: 2 | I41: 1 | J41: 1.75 | K41: 3 | L41: 0.1 | M41: 0 | N41: 24 | O41: 50 | P41: 45 | Q41: 85 | R41: ISO 6 | S41: 160 | T41: 0 | U41: 100 | V41: =R41 -> ISO 6 | W41: =S41 -> 160 | X41: =E41*F41*10.76 -> 36.7992 | Y41: =X41*G41*3.28 -> 289.6833 | Z41: =Y41*S41/60 -> 772.48881 | AA41: =Z41*L41 -> 77.248881 | AB41: =IF(N41="Amb",Z41,Z41*M41) -> 0 | AC41: =IF(ISNUMBER(N41), (AA41*0.075*60/2.20462)*BP41/7000, "Ambient") -> 0 | AD41: =IF(ISNUMBER(N41), CEILING(CF41/(0.68*BP41),25), "Ambient") -> #DIV/0! | AE41: =CEILING(MAX((Z41+AA41),AD41),25) -> #DIV/0! | AF41: =CEILING(IF(OR($R41="ISO 6",$R41="GRADE B",$R41="1K",$R41=1000),AE41*1/175,IF(OR($R41="ISO 5",$R41="GRADE A",$R41=100),AE41*1/100,IF(OR($R41="ISO 7",$R41="GRADE C",$R41="10K",$R41=10000),$AE41*1/250,IF(OR($R41="ISO 8",$R41="GRADE D",$R41="100K",$R41=100000),$AE41*1/250,IF(OR($R41="NC",$R41="20 Micron",$R41="5 Micron",$R41="N C"),$AE41*1/350,0))))),2) -> #DIV/0! | AG41: =IF(ISNUMBER(N41), CEILING(MAX(AI41,AJ41),0.5), "Ambient") -> #DIV/0! | AH41: C | AI41: =IF(ISNUMBER(N41), CEILING(CE41/12000,0.5), "Ambient") -> 0 | AJ41: =IF(ISNUMBER(N41),CEILING(AE41/(IF(AH41="C",400,300)),0.5), "Ambient") -> #DIV/0!
C42: =IF(D42<>"",COUNTA($D$10:D42),"") -> 30 | D42: Clean Room 22 | E42: 1.9 | F42: 2 | G42: 2.4 | H42: 2 | I42: 1 | J42: 1.75 | K42: 3 | L42: 0.1 | M42: 0 | N42: 24 | O42: 50 | P42: 45 | Q42: 85 | R42: ISO 6 | S42: 160 | T42: 0 | U42: 100 | V42: =R42 -> ISO 6 | W42: =S42 -> 160 | X42: =E42*F42*10.76 -> 40.888 | Y42: =X42*G42*3.28 -> 321.87034 | Z42: =Y42*S42/60 -> 858.3209 | AA42: =Z42*L42 -> 85.83209 | AB42: =IF(N42="Amb",Z42,Z42*M42) -> 0 | AC42: =IF(ISNUMBER(N42), (AA42*0.075*60/2.20462)*BP42/7000, "Ambient") -> 0 | AD42: =IF(ISNUMBER(N42), CEILING(CF42/(0.68*BP42),25), "Ambient") -> #DIV/0! | AE42: =CEILING(MAX((Z42+AA42),AD42),25) -> #DIV/0! | AF42: =CEILING(IF(OR($R42="ISO 6",$R42="GRADE B",$R42="1K",$R42=1000),AE42*1/175,IF(OR($R42="ISO 5",$R42="GRADE A",$R42=100),AE42*1/100,IF(OR($R42="ISO 7",$R42="GRADE C",$R42="10K",$R42=10000),$AE42*1/250,IF(OR($R42="ISO 8",$R42="GRADE D",$R42="100K",$R42=100000),$AE42*1/250,IF(OR($R42="NC",$R42="20 Micron",$R42="5 Micron",$R42="N C"),$AE42*1/350,0))))),2) -> #DIV/0! | AG42: =IF(ISNUMBER(N42), CEILING(MAX(AI42,AJ42),0.5), "Ambient") -> #DIV/0! | AH42: C | AI42: =IF(ISNUMBER(N42), CEILING(CE42/12000,0.5), "Ambient") -> 0 | AJ42: =IF(ISNUMBER(N42),CEILING(AE42/(IF(AH42="C",400,300)),0.5), "Ambient") -> #DIV/0!
C43: =IF(D43<>"",COUNTA($D$10:D43),"") -> 31 | D43: Clean Room 23 | E43: 2.3 | F43: 2.2 | G43: 2.4 | H43: 2 | I43: 1 | J43: 1.75 | K43: 3 | L43: 0.1 | M43: 0 | N43: 24 | O43: 50 | P43: 45 | Q43: 85 | R43: ISO 6 | S43: 160 | T43: 0 | U43: 100 | V43: =R43 -> ISO 6 | W43: =S43 -> 160 | X43: =E43*F43*10.76 -> 54.4456 | Y43: =X43*G43*3.28 -> 428.59576 | Z43: =Y43*S43/60 -> 1142.922 | AA43: =Z43*L43 -> 114.2922 | AB43: =IF(N43="Amb",Z43,Z43*M43) -> 0 | AC43: =IF(ISNUMBER(N43), (AA43*0.075*60/2.20462)*BP43/7000, "Ambient") -> 0 | AD43: =IF(ISNUMBER(N43), CEILING(CF43/(0.68*BP43),25), "Ambient") -> #DIV/0! | AE43: =CEILING(MAX((Z43+AA43),AD43),25) -> #DIV/0! | AF43: =CEILING(IF(OR($R43="ISO 6",$R43="GRADE B",$R43="1K",$R43=1000),AE43*1/175,IF(OR($R43="ISO 5",$R43="GRADE A",$R43=100),AE43*1/100,IF(OR($R43="ISO 7",$R43="GRADE C",$R43="10K",$R43=10000),$AE43*1/250,IF(OR($R43="ISO 8",$R43="GRADE D",$R43="100K",$R43=100000),$AE43*1/250,IF(OR($R43="NC",$R43="20 Micron",$R43="5 Micron",$R43="N C"),$AE43*1/350,0))))),2) -> #DIV/0! | AG43: =IF(ISNUMBER(N43), CEILING(MAX(AI43,AJ43),0.5), "Ambient") -> #DIV/0! | AH43: C | AI43: =IF(ISNUMBER(N43), CEILING(CE43/12000,0.5), "Ambient") -> 0 | AJ43: =IF(ISNUMBER(N43),CEILING(AE43/(IF(AH43="C",400,300)),0.5), "Ambient") -> #DIV/0!
C44: =IF(D44<>"",COUNTA($D$10:D44),"") -> 32 | D44: Clean Room 24 | E44: 2.2 | F44: 2.8 | G44: 2.4 | H44: 2 | I44: 1 | J44: 1.75 | K44: 3 | L44: 0.1 | M44: 0 | N44: 24 | O44: 50 | P44: 45 | Q44: 85 | R44: ISO 6 | S44: 160 | T44: 0 | U44: 100 | V44: =R44 -> ISO 6 | W44: =S44 -> 160 | X44: =E44*F44*10.76 -> 66.2816 | Y44: =X44*G44*3.28 -> 521.76876 | Z44: =Y44*S44/60 -> 1391.3833 | AA44: =Z44*L44 -> 139.13833 | AB44: =IF(N44="Amb",Z44,Z44*M44) -> 0 | AC44: =IF(ISNUMBER(N44), (AA44*0.075*60/2.20462)*BP44/7000, "Ambient") -> 0 | AD44: =IF(ISNUMBER(N44), CEILING(CF44/(0.68*BP44),25), "Ambient") -> #DIV/0! | AE44: =CEILING(MAX((Z44+AA44),AD44),25) -> #DIV/0! | AF44: =CEILING(IF(OR($R44="ISO 6",$R44="GRADE B",$R44="1K",$R44=1000),AE44*1/175,IF(OR($R44="ISO 5",$R44="GRADE A",$R44=100),AE44*1/100,IF(OR($R44="ISO 7",$R44="GRADE C",$R44="10K",$R44=10000),$AE44*1/250,IF(OR($R44="ISO 8",$R44="GRADE D",$R44="100K",$R44=100000),$AE44*1/250,IF(OR($R44="NC",$R44="20 Micron",$R44="5 Micron",$R44="N C"),$AE44*1/350,0))))),2) -> #DIV/0! | AG44: =IF(ISNUMBER(N44), CEILING(MAX(AI44,AJ44),0.5), "Ambient") -> #DIV/0! | AH44: C | AI44: =IF(ISNUMBER(N44), CEILING(CE44/12000,0.5), "Ambient") -> 0 | AJ44: =IF(ISNUMBER(N44),CEILING(AE44/(IF(AH44="C",400,300)),0.5), "Ambient") -> #DIV/0!
C45: =IF(D45<>"",COUNTA($D$10:D45),"") -> 33 | D45: Clean Room 25 | E45: 2.8 | F45: 2.4 | G45: 2.4 | H45: 2 | I45: 1 | J45: 1.75 | K45: 3 | L45: 0.1 | M45: 0 | N45: 24 | O45: 50 | P45: 45 | Q45: 85 | R45: ISO 6 | S45: 160 | T45: 0 | U45: 100 | V45: =R45 -> ISO 6 | W45: =S45 -> 160 | X45: =E45*F45*10.76 -> 72.3072 | Y45: =X45*G45*3.28 -> 569.20228 | Z45: =Y45*S45/60 -> 1517.8727 | AA45: =Z45*L45 -> 151.78727 | AB45: =IF(N45="Amb",Z45,Z45*M45) -> 0 | AC45: =IF(ISNUMBER(N45), (AA45*0.075*60/2.20462)*BP45/7000, "Ambient") -> 0 | AD45: =IF(ISNUMBER(N45), CEILING(CF45/(0.68*BP45),25), "Ambient") -> #DIV/0! | AE45: =CEILING(MAX((Z45+AA45),AD45),25) -> #DIV/0! | AF45: =CEILING(IF(OR($R45="ISO 6",$R45="GRADE B",$R45="1K",$R45=1000),AE45*1/175,IF(OR($R45="ISO 5",$R45="GRADE A",$R45=100),AE45*1/100,IF(OR($R45="ISO 7",$R45="GRADE C",$R45="10K",$R45=10000),$AE45*1/250,IF(OR($R45="ISO 8",$R45="GRADE D",$R45="100K",$R45=100000),$AE45*1/250,IF(OR($R45="NC",$R45="20 Micron",$R45="5 Micron",$R45="N C"),$AE45*1/350,0))))),2) -> #DIV/0! | AG45: =IF(ISNUMBER(N45), CEILING(MAX(AI45,AJ45),0.5), "Ambient") -> #DIV/0! | AH45: C | AI45: =IF(ISNUMBER(N45), CEILING(CE45/12000,0.5), "Ambient") -> 0 | AJ45: =IF(ISNUMBER(N45),CEILING(AE45/(IF(AH45="C",400,300)),0.5), "Ambient") -> #DIV/0!
C46: =IF(D46<>"",COUNTA($D$10:D46),"") | X46: =SUM(X30:X45) -> 1144.1108 | Y46: =SUM(Y30:Y45) -> 9006.4402 | Z46: =SUM(Z30:Z45) -> 24017.174 | AA46: =SUM(AA30:AA45) -> 2401.7174 | AB46: =SUM(AB30:AB45) -> 0 | AC46: =SUM(AC30:AC45) -> 0 | AD46: =SUM(AD30:AD45) -> #DIV/0! | AE46: =SUM(AE30:AE45) -> #DIV/0! | ... AG46: =SUM(AG30:AG45) -> #DIV/0! | AI46: =SUM(AI30:AI45) -> 0 | AJ46: =SUM(AJ30:AJ45) -> #DIV/0!
C47: =IF(D47<>"",COUNTA($D$10:D47),"")
C48: ="Zoning Area AHU - " & INT((ROW()-8)/20)+1 & " " &IF(AQ50>0,"Air-Conditioning System " & IF(AH50="D","(DX)",IF(AH50="C","(Chilled Water)","")),IF(AND(N50="Amb",AQ50=0),"Ventilation System","Refer")) -> #DIV/0! | AS48: Chilled Water Details | AW48: Hot Water/Steam Details
C49: =IF(D49<>"",COUNTA($D$10:D49),"") -> 34 | D49: Room Name | E49: Length in mtrs | F49: Width in mtrs | G49: Height in mtrs | H49: People in Nos | I49: Eqpt. Load in KW | J49: Lighting in W/Sft | K49: No.of Inf./Hr | L49: Fresh Air | M49: Exhaust | N49: T ˚C (Required inside) | O49: RH(in) +/- 5% | P49: Peak Max Temp.(Out) in ˚C | Q49: RH(Out) in +/- 5% | R49: Class | S49: ACPH | T49: Peak Min Temp.(Out) in ˚C | U49: RH(Out) +/- 5% | V49: Class | W49: ACPH | X49: Area | Y49: Volume | Z49: Room Cfm | AA49: FA | AB49: EA | AC49: Rem. Water vapour Kg/hr | AD49: Deh. Cfm | AE49: Res. Cfm | AF49: Room Terminal Supply Module in Sft | AG49: Res. Cooling Load in TR | AH49: Chilled Water (C) OR DX (D) | AI49: Room AC load in TR | AJ49: Cfm AC load in TR | AK49: AHU Cfm | AL49: AHU Size | AM49: Static Pressure | AN49: Blower Model BDB | AO49: Motor Selected in Hp | AP49: No. of Rows of Cooling Coil | AQ49: AHU Cooling Load in TR | AR49: No. Of Stages of Filtr. | AS49: Chilled water in GPM | AT49: Chilled water in L/s | AU49: Flow Velocity in m/s | AV49: Pipe Size in mm | AW49: Hot Water/Steam in GPM | AX49: Hot water/Steam in L/s | AY49: Flow Velocity | AZ49: Pipe Size
C50: =IF(D50<>"",COUNTA($D$10:D50),"") -> 35 | D50: Clean Room 10 | E50: 3 | F50: 3 | G50: 2.4 | H50: 1 | I50: 2 | J50: 1.75 | K50: 3 | L50: 0.1 | M50: 0 | N50: 24 | O50: 50 | P50: 45 | Q50: 85 | R50: GRADE A | S50: 150 | T50: 0 | U50: 100 | V50: =R50 -> GRADE A | W50: =S50 -> 150 | X50: =E50*F50*10.76 -> 96.84 | Y50: =X50*G50*3.28 -> 762.32448 | Z50: =Y50*S50/60 -> 1905.8112 | AA50: =Z50*L50 -> 190.58112 | AB50: =IF(N50="Amb",Z50,Z50*M50) -> 0 | AC50: =IF(ISNUMBER(N50), (AA50*0.075*60/2.20462)*BP50/7000, "Ambient") -> 0 | AD50: =IF(ISNUMBER(N50), CEILING(CF50/(0.68*BP50),25), "Ambient") -> #DIV/0! | AE50: =CEILING(MAX((Z50+AA50),AD50),25) -> #DIV/0! | AF50: =CEILING(IF(OR($R50="ISO 6",$R50="GRADE B",$R50="1K",$R50=1000),AE50*1/175,IF(OR($R50="ISO 5",$R50="GRADE A",$R50=100),AE50*1/100,IF(OR($R50="ISO 7",$R50="GRADE C",$R50="10K",$R50=10000),$AE50*1/250,IF(OR($R50="ISO 8",$R50="GRADE D",$R50="100K",$R50=100000),$AE50*1/250,IF(OR($R50="NC",$R50="20 Micron",$R50="5 Micron",$R50="N C"),$AE50*1/350,0))))),2) -> #DIV/0! | AG50: =IF(ISNUMBER(N50), CEILING(MAX(AI50,AJ50),0.5), "Ambient") -> #DIV/0! | AH50: D | AI50: =IF(ISNUMBER(N50), CEILING(CE50/12000,0.5), "Ambient") -> 0 | AJ50: =IF(ISNUMBER(N50),CEILING(AE50/(IF(AH50="C",400,300)),0.5), "Ambient") -> #DIV/0! | AK50: =CEILING(SUM(AE50:AE65),250) -> #DIV/0! | AL50: W | AM50: 150 | AN50: =IF(AK50<=1300,200,IF(AK50<=1600,225,IF(AK50<=2100,250,IF(AK50<=2700,280,IF(AK50<=3450,315,IF(AK50<=4250,355,IF(AK50<=5250,400,IF(AK50<=6750,450,IF(AK50<=8500,500,IF(AK50<=10750,560,IF(AK50<=13500,630,IF(AK50<=17000,710,IF(AK50<=21500,800,IF(AK50<=27000,900,IF(AK50<=34000,1000,IF(AK50<=43000,1120,IF(AK50<=49000,1200,IF(AK50<=68000,1450,"Refer")))))))))))))))))) -> #DIV/0! | AO50: =IF(AK50*AM50/(6356*0.7*0.9*1.1*25.4)<=1,1,IF(AK50*AM50/(6356*0.7*0.9*1.1*25.4)<=1.5,1.5,IF(AK50*AM50/(6356*0.7*0.9*1.1*25.4)<=2,2,IF(AK50*AM50/(6356*0.7*0.9*1.1*25.4)<=3,3,IF(AK50*AM50/(6356*0.7*0.9*1.1*25.4)<=5,5,IF(AK50*AM50/(6356*0.7*0.9*1.1*25.4)<=7.5,7.5,IF(AK50*AM50/(6356*0.7*0.9*1.1*25.4)<=10,10,IF(AK50*AM50/(6356*0.7*0.9*1.1*25.4)<=12.5,12.5,IF(AK50*AM50/(6356*0.7*0.9*1.1*25.4)<=15,15,IF(AK50*AM50/(6356*0.7*0.9*1.1*25.4)<=20,20,IF(AK50*AM50/(6356*0.7*0.9*1.1*25.4)<=25,25,IF(AK50*AM50/(6356*0.7*0.9*1.1*25.4)<=30,30,IF(AK50*AM50/(6356*0.7*0.9*1.1*25.4)<=40,40,IF(AK50*AM50/(6356*0.7*0.9*1.1*25.4)<=50,50,IF(AK50*AM50/(6356*0.7*0.9*1.1*25.4)<=60,60,IF(AK50*AM50/(6356*0.7*0.9*1.1*25.4)<=75,75,"Refer")))))))))))))))) -> #DIV/0! | AP50: =IF(AND(AQ50=0, N50="Amb"), "Amb",IF((AL51-250)*(AL53-150)*10.76/(1000*1000) >= MAX(AI66,AJ66), 4,IF((AL51-250)*(AL53-150)*10.76*1.5/(1000*1000) >= MAX(AI66,AJ66), 6,IF((AL51-250)*(AL53-150)*10.76*2/(1000*1000) >= MAX(AI66,AJ66), 8, 0)) ) ) -> #DIV/0! | AQ50: =AG66 -> #DIV/0! | AR50: =_xlfn.SWITCH(TRIM(UPPER(R50)),"ISO 9", 3,"ISO 8", 4,"Grade D", 4,"Class 100,000", 4,"Class 100K", 4,"ISO 7", 3,"Grade C", 3,"Class 10,000", 3,"Class 10K", 3,"ISO 6", 3,"Class 1,000", 3,"Class 1K", 3,"ISO 5", 4,"Grade A", 4,"Grade B", 4,"Class 100", 4,"ISO 4", 3,"ISO 3", 4,"ISO 2", 4,"ISO 1", 4,"NCV20",1,"NCV-10",2,"NCV-5",3,"NCAC-10",1,"NCAC-5",2,"NCAC-1",3,3) -> 4 | AS50: =MAX(AI66,AJ66)*24/6 -> #DIV/0! | AT50: =AS50*0.06309 -> #DIV/0! | AU50: 2 | AV50: =SQRT((4*AS50*0.00006309)/(3.14*AU50))*1000 -> #DIV/0!
C51: =IF(D51<>"",COUNTA($D$10:D51),"") -> 36 | D51: Clean Room 11 | E51: 1.8 | F51: 2.2 | G51: 2.4 | H51: 2 | I51: 1 | J51: 1.75 | K51: 3 | L51: 0.1 | M51: 0 | N51: 24 | O51: 50 | P51: 45 | Q51: 85 | R51: GRADE A | S51: 150 | T51: 0 | U51: 100 | V51: =R51 -> GRADE A | W51: =S51 -> 150 | X51: =E51*F51*10.76 -> 42.6096 | Y51: =X51*G51*3.28 -> 335.42277 | Z51: =Y51*S51/60 -> 838.55693 | AA51: =Z51*L51 -> 83.855693 | AB51: =IF(N51="Amb",Z51,Z51*M51) -> 0 | AC51: =IF(ISNUMBER(N51), (AA51*0.075*60/2.20462)*BP51/7000, "Ambient") -> 0 | AD51: =IF(ISNUMBER(N51), CEILING(CF51/(0.68*BP51),25), "Ambient") -> #DIV/0! | AE51: =CEILING(MAX((Z51+AA51),AD51),25) -> #DIV/0! | AF51: =CEILING(IF(OR($R51="ISO 6",$R51="GRADE B",$R51="1K",$R51=1000),AE51*1/175,IF(OR($R51="ISO 5",$R51="GRADE A",$R51=100),AE51*1/100,IF(OR($R51="ISO 7",$R51="GRADE C",$R51="10K",$R51=10000),$AE51*1/250,IF(OR($R51="ISO 8",$R51="GRADE D",$R51="100K",$R51=100000),$AE51*1/250,IF(OR($R51="NC",$R51="20 Micron",$R51="5 Micron",$R51="N C"),$AE51*1/350,0))))),2) -> #DIV/0! | AG51: =IF(ISNUMBER(N51), CEILING(MAX(AI51,AJ51),0.5), "Ambient") -> #DIV/0! | AH51: D | AI51: =IF(ISNUMBER(N51), CEILING(CE51/12000,0.5), "Ambient") -> 0 | AJ51: =IF(ISNUMBER(N51),CEILING(AE51/(IF(AH51="C",400,300)),0.5), "Ambient") -> #DIV/0! | AL51: =IF(AK50<=2000,950,(IF(AK50<=3000,1150,(IF(AK50<=8000,1550,(IF(AK50<=10000,1750,(IF(AK50<=18000,2050,(IF(AK50<=32000,2900,(IF(AK50<=40000,3600,4000))))))))))))) -> #DIV/0!
C52: =IF(D52<>"",COUNTA($D$10:D52),"") -> 37 | D52: Clean Room 12 | E52: 1.5 | F52: 2.8 | G52: 2.4 | H52: 2 | I52: 3 | J52: 1.75 | K52: 3 | L52: 0.1 | M52: 0 | N52: 24 | O52: 50 | P52: 45 | Q52: 85 | R52: GRADE A | S52: 150 | T52: 0 | U52: 100 | V52: =R52 -> GRADE A | W52: =S52 -> 150 | X52: =E52*F52*10.76 -> 45.192 | Y52: =X52*G52*3.28 -> 355.75142 | Z52: =Y52*S52/60 -> 889.37856 | AA52: =Z52*L52 -> 88.937856 | AB52: =IF(N52="Amb",Z52,Z52*M52) -> 0 | AC52: =IF(ISNUMBER(N52), (AA52*0.075*60/2.20462)*BP52/7000, "Ambient") -> 0 | AD52: =IF(ISNUMBER(N52), CEILING(CF52/(0.68*BP52),25), "Ambient") -> #DIV/0! | AE52: =CEILING(MAX((Z52+AA52),AD52),25) -> #DIV/0! | AF52: =CEILING(IF(OR($R52="ISO 6",$R52="GRADE B",$R52="1K",$R52=1000),AE52*1/175,IF(OR($R52="ISO 5",$R52="GRADE A",$R52=100),AE52*1/100,IF(OR($R52="ISO 7",$R52="GRADE C",$R52="10K",$R52=10000),$AE52*1/250,IF(OR($R52="ISO 8",$R52="GRADE D",$R52="100K",$R52=100000),$AE52*1/250,IF(OR($R52="NC",$R52="20 Micron",$R52="5 Micron",$R52="N C"),$AE52*1/350,0))))),2) -> #DIV/0! | AG52: =IF(ISNUMBER(N52), CEILING(MAX(AI52,AJ52),0.5), "Ambient") -> #DIV/0! | AH52: D | AI52: =IF(ISNUMBER(N52), CEILING(CE52/12000,0.5), "Ambient") -> 0 | AJ52: =IF(ISNUMBER(N52),CEILING(AE52/(IF(AH52="C",400,300)),0.5), "Ambient") -> #DIV/0! | AL52: H
C53: =IF(D53<>"",COUNTA($D$10:D53),"") -> 38 | D53: Clean Room 13 | E53: 2.1 | F53: 3.5 | G53: 2.4 | H53: 0 | I53: 1 | J53: 1.75 | K53: 3 | L53: 0.1 | M53: 0 | N53: 24 | O53: 50 | P53: 45 | Q53: 85 | R53: GRADE A | S53: 150 | T53: 0 | U53: 100 | V53: =R53 -> GRADE A | W53: =S53 -> 150 | X53: =E53*F53*10.76 -> 79.086 | Y53: =X53*G53*3.28 -> 622.56499 | Z53: =Y53*S53/60 -> 1556.4125 | AA53: =Z53*L53 -> 155.64125 | AB53: =IF(N53="Amb",Z53,Z53*M53) -> 0 | AC53: =IF(ISNUMBER(N53), (AA53*0.075*60/2.20462)*BP53/7000, "Ambient") -> 0 | AD53: =IF(ISNUMBER(N53), CEILING(CF53/(0.68*BP53),25), "Ambient") -> #DIV/0! | AE53: =CEILING(MAX((Z53+AA53),AD53),25) -> #DIV/0! | AF53: =CEILING(IF(OR($R53="ISO 6",$R53="GRADE B",$R53="1K",$R53=1000),AE53*1/175,IF(OR($R53="ISO 5",$R53="GRADE A",$R53=100),AE53*1/100,IF(OR($R53="ISO 7",$R53="GRADE C",$R53="10K",$R53=10000),$AE53*1/250,IF(OR($R53="ISO 8",$R53="GRADE D",$R53="100K",$R53=100000),$AE53*1/250,IF(OR($R53="NC",$R53="20 Micron",$R53="5 Micron",$R53="N C"),$AE53*1/350,0))))),2) -> #DIV/0! | AG53: =IF(ISNUMBER(N53), CEILING(MAX(AI53,AJ53),0.5), "Ambient") -> #DIV/0! | AH53: D | AI53: =IF(ISNUMBER(N53), CEILING(CE53/12000,0.5), "Ambient") -> 0 | AJ53: =IF(ISNUMBER(N53),CEILING(AE53/(IF(AH53="C",400,300)),0.5), "Ambient") -> #DIV/0! | AL53: =IF(AK50<=2000,950,(IF(AK50<=4000,1100,(IF(AK50<=6000,1250,(IF(AK50<=10000,1550,(IF(AK50<=15000,1750,(IF(AK50<=24000,2050,(IF(AK50<=40000,2900,3600))))))))))))) -> #DIV/0!
C54: =IF(D54<>"",COUNTA($D$10:D54),"") -> 39 | D54: Clean Room 14 | E54: 2.7 | F54: 4 | G54: 2.4 | H54: 2 | I54: 1 | J54: 1.75 | K54: 3 | L54: 0.1 | M54: 0 | N54: 24 | O54: 50 | P54: 45 | Q54: 85 | R54: GRADE A | S54: 150 | T54: 0 | U54: 100 | V54: =R54 -> GRADE A | W54: =S54 -> 150 | X54: =E54*F54*10.76 -> 116.208 | Y54: =X54*G54*3.28 -> 914.78938 | Z54: =Y54*S54/60 -> 2286.9734 | AA54: =Z54*L54 -> 228.69734 | AB54: =IF(N54="Amb",Z54,Z54*M54) -> 0 | AC54: =IF(ISNUMBER(N54), (AA54*0.075*60/2.20462)*BP54/7000, "Ambient") -> 0 | AD54: =IF(ISNUMBER(N54), CEILING(CF54/(0.68*BP54),25), "Ambient") -> #DIV/0! | AE54: =CEILING(MAX((Z54+AA54),AD54),25) -> #DIV/0! | AF54: =CEILING(IF(OR($R54="ISO 6",$R54="GRADE B",$R54="1K",$R54=1000),AE54*1/175,IF(OR($R54="ISO 5",$R54="GRADE A",$R54=100),AE54*1/100,IF(OR($R54="ISO 7",$R54="GRADE C",$R54="10K",$R54=10000),$AE54*1/250,IF(OR($R54="ISO 8",$R54="GRADE D",$R54="100K",$R54=100000),$AE54*1/250,IF(OR($R54="NC",$R54="20 Micron",$R54="5 Micron",$R54="N C"),$AE54*1/350,0))))),2) -> #DIV/0! | AG54: =IF(ISNUMBER(N54), CEILING(MAX(AI54,AJ54),0.5), "Ambient") -> #DIV/0! | AH54: D | AI54: =IF(ISNUMBER(N54), CEILING(CE54/12000,0.5), "Ambient") -> 0 | AJ54: =IF(ISNUMBER(N54),CEILING(AE54/(IF(AH54="C",400,300)),0.5), "Ambient") -> #DIV/0! | AL54: L
C55: =IF(D55<>"",COUNTA($D$10:D55),"") -> 40 | D55: Clean Room 15 | E55: 3.8 | F55: 4.2 | G55: 2.4 | H55: 3 | I55: 3 | J55: 1.75 | K55: 3 | L55: 0.1 | M55: 0 | N55: 24 | O55: 50 | P55: 45 | Q55: 85 | R55: GRADE A | S55: 150 | T55: 0 | U55: 100 | V55: =R55 -> GRADE A | W55: =S55 -> 150 | X55: =E55*F55*10.76 -> 171.7296 | Y55: =X55*G55*3.28 -> 1351.8554 | Z55: =Y55*S55/60 -> 3379.6385 | AA55: =Z55*L55 -> 337.96385 | AB55: =IF(N55="Amb",Z55,Z55*M55) -> 0 | AC55: =IF(ISNUMBER(N55), (AA55*0.075*60/2.20462)*BP55/7000, "Ambient") -> 0 | AD55: =IF(ISNUMBER(N55), CEILING(CF55/(0.68*BP55),25), "Ambient") -> #DIV/0! | AE55: =CEILING(MAX((Z55+AA55),AD55),25) -> #DIV/0! | AF55: =CEILING(IF(OR($R55="ISO 6",$R55="GRADE B",$R55="1K",$R55=1000),AE55*1/175,IF(OR($R55="ISO 5",$R55="GRADE A",$R55=100),AE55*1/100,IF(OR($R55="ISO 7",$R55="GRADE C",$R55="10K",$R55=10000),$AE55*1/250,IF(OR($R55="ISO 8",$R55="GRADE D",$R55="100K",$R55=100000),$AE55*1/250,IF(OR($R55="NC",$R55="20 Micron",$R55="5 Micron",$R55="N C"),$AE55*1/350,0))))),2) -> #DIV/0! | AG55: =IF(ISNUMBER(N55), CEILING(MAX(AI55,AJ55),0.5), "Ambient") -> #DIV/0! | AH55: D | AI55: =IF(ISNUMBER(N55), CEILING(CE55/12000,0.5), "Ambient") -> 0 | AJ55: =IF(ISNUMBER(N55),CEILING(AE55/(IF(AH55="C",400,300)),0.5), "Ambient") -> #DIV/0! | AL55: =IF(AL59<4000,AL59,AL59+400) -> #DIV/0!
C56: =IF(D56<>"",COUNTA($D$10:D56),"") -> 41 | D56: Clean Room 16 | E56: 3.1 | F56: 2.6 | G56: 2.4 | H56: 2 | I56: 1 | J56: 1.75 | K56: 3 | L56: 0.1 | M56: 0 | N56: 24 | O56: 50 | P56: 45 | Q56: 85 | R56: GRADE A | S56: 150 | T56: 0 | U56: 100 | V56: =R56 -> GRADE A | W56: =S56 -> 150 | X56: =E56*F56*10.76 -> 86.7256 | Y56: =X56*G56*3.28 -> 682.70392 | Z56: =Y56*S56/60 -> 1706.7598 | AA56: =Z56*L56 -> 170.67598 | AB56: =IF(N56="Amb",Z56,Z56*M56) -> 0 | AC56: =IF(ISNUMBER(N56), (AA56*0.075*60/2.20462)*BP56/7000, "Ambient") -> 0 | AD56: =IF(ISNUMBER(N56), CEILING(CF56/(0.68*BP56),25), "Ambient") -> #DIV/0! | AE56: =CEILING(MAX((Z56+AA56),AD56),25) -> #DIV/0! | AF56: =CEILING(IF(OR($R56="ISO 6",$R56="GRADE B",$R56="1K",$R56=1000),AE56*1/175,IF(OR($R56="ISO 5",$R56="GRADE A",$R56=100),AE56*1/100,IF(OR($R56="ISO 7",$R56="GRADE C",$R56="10K",$R56=10000),$AE56*1/250,IF(OR($R56="ISO 8",$R56="GRADE D",$R56="100K",$R56=100000),$AE56*1/250,IF(OR($R56="NC",$R56="20 Micron",$R56="5 Micron",$R56="N C"),$AE56*1/350,0))))),2) -> #DIV/0! | AG56: =IF(ISNUMBER(N56), CEILING(MAX(AI56,AJ56),0.5), "Ambient") -> #DIV/0! | AH56: D | AI56: =IF(ISNUMBER(N56), CEILING(CE56/12000,0.5), "Ambient") -> 0 | AJ56: =IF(ISNUMBER(N56),CEILING(AE56/(IF(AH56="C",400,300)),0.5), "Ambient") -> #DIV/0!
C57: =IF(D57<>"",COUNTA($D$10:D57),"") -> 42 | D57: Clean Room 17 | E57: 1.9 | F57: 2.4 | G57: 2.4 | H57: 3 | I57: 2 | J57: 1.75 | K57: 3 | L57: 0.1 | M57: 0 | N57: 24 | O57: 50 | P57: 45 | Q57: 85 | R57: GRADE A | S57: 150 | T57: 0 | U57: 100 | V57: =R57 -> GRADE A | W57: =S57 -> 150 | X57: =E57*F57*10.76 -> 49.0656 | Y57: =X57*G57*3.28 -> 386.2444 | Z57: =Y57*S57/60 -> 965.61101 | AA57: =Z57*L57 -> 96.561101 | AB57: =IF(N57="Amb",Z57,Z57*M57) -> 0 | AC57: =IF(ISNUMBER(N57), (AA57*0.075*60/2.20462)*BP57/7000, "Ambient") -> 0 | AD57: =IF(ISNUMBER(N57), CEILING(CF57/(0.68*BP57),25), "Ambient") -> #DIV/0! | AE57: =CEILING(MAX((Z57+AA57),AD57),25) -> #DIV/0! | AF57: =CEILING(IF(OR($R57="ISO 6",$R57="GRADE B",$R57="1K",$R57=1000),AE57*1/175,IF(OR($R57="ISO 5",$R57="GRADE A",$R57=100),AE57*1/100,IF(OR($R57="ISO 7",$R57="GRADE C",$R57="10K",$R57=10000),$AE57*1/250,IF(OR($R57="ISO 8",$R57="GRADE D",$R57="100K",$R57=100000),$AE57*1/250,IF(OR($R57="NC",$R57="20 Micron",$R57="5 Micron",$R57="N C"),$AE57*1/350,0))))),2) -> #DIV/0! | AG57: =IF(ISNUMBER(N57), CEILING(MAX(AI57,AJ57),0.5), "Ambient") -> #DIV/0! | AH57: D | AI57: =IF(ISNUMBER(N57), CEILING(CE57/12000,0.5), "Ambient") -> 0 | AJ57: =IF(ISNUMBER(N57),CEILING(AE57/(IF(AH57="C",400,300)),0.5), "Ambient") -> #DIV/0!
C58: =IF(D58<>"",COUNTA($D$10:D58),"") -> 43 | D58: Clean Room 18 | E58: 3 | F58: 2.9 | G58: 2.4 | H58: 2 | I58: 1 | J58: 1.75 | K58: 3 | L58: 0.1 | M58: 0 | N58: 24 | O58: 50 | P58: 45 | Q58: 85 | R58: GRADE A | S58: 150 | T58: 0 | U58: 100 | V58: =R58 -> GRADE A | W58: =S58 -> 150 | X58: =E58*F58*10.76 -> 93.612 | Y58: =X58*G58*3.28 -> 736.91366 | Z58: =Y58*S58/60 -> 1842.2842 | AA58: =Z58*L58 -> 184.22842 | AB58: =IF(N58="Amb",Z58,Z58*M58) -> 0 | AC58: =IF(ISNUMBER(N58), (AA58*0.075*60/2.20462)*BP58/7000, "Ambient") -> 0 | AD58: =IF(ISNUMBER(N58), CEILING(CF58/(0.68*BP58),25), "Ambient") -> #DIV/0! | AE58: =CEILING(MAX((Z58+AA58),AD58),25) -> #DIV/0! | AF58: =CEILING(IF(OR($R58="ISO 6",$R58="GRADE B",$R58="1K",$R58=1000),AE58*1/175,IF(OR($R58="ISO 5",$R58="GRADE A",$R58=100),AE58*1/100,IF(OR($R58="ISO 7",$R58="GRADE C",$R58="10K",$R58=10000),$AE58*1/250,IF(OR($R58="ISO 8",$R58="GRADE D",$R58="100K",$R58=100000),$AE58*1/250,IF(OR($R58="NC",$R58="20 Micron",$R58="5 Micron",$R58="N C"),$AE58*1/350,0))))),2) -> #DIV/0! | AG58: =IF(ISNUMBER(N58), CEILING(MAX(AI58,AJ58),0.5), "Ambient") -> #DIV/0! | AH58: D | AI58: =IF(ISNUMBER(N58), CEILING(CE58/12000,0.5), "Ambient") -> 0 | AJ58: =IF(ISNUMBER(N58),CEILING(AE58/(IF(AH58="C",400,300)),0.5), "Ambient") -> #DIV/0!
C59: =IF(D59<>"",COUNTA($D$10:D59),"") -> 44 | D59: Clean Room 19 | E59: 2.4 | F59: 2 | G59: 2.4 | H59: 2 | I59: 1 | J59: 1.75 | K59: 3 | L59: 0.1 | M59: 0 | N59: 24 | O59: 50 | P59: 45 | Q59: 85 | R59: GRADE A | S59: 150 | T59: 0 | U59: 100 | V59: =R59 -> GRADE A | W59: =S59 -> 150 | X59: =E59*F59*10.76 -> 51.648 | Y59: =X59*G59*3.28 -> 406.57306 | Z59: =Y59*S59/60 -> 1016.4326 | AA59: =Z59*L59 -> 101.64326 | AB59: =IF(N59="Amb",Z59,Z59*M59) -> 0 | AC59: =IF(ISNUMBER(N59), (AA59*0.075*60/2.20462)*BP59/7000, "Ambient") -> 0 | AD59: =IF(ISNUMBER(N59), CEILING(CF59/(0.68*BP59),25), "Ambient") -> #DIV/0! | AE59: =CEILING(MAX((Z59+AA59),AD59),25) -> #DIV/0! | AF59: =CEILING(IF(OR($R59="ISO 6",$R59="GRADE B",$R59="1K",$R59=1000),AE59*1/175,IF(OR($R59="ISO 5",$R59="GRADE A",$R59=100),AE59*1/100,IF(OR($R59="ISO 7",$R59="GRADE C",$R59="10K",$R59=10000),$AE59*1/250,IF(OR($R59="ISO 8",$R59="GRADE D",$R59="100K",$R59=100000),$AE59*1/250,IF(OR($R59="NC",$R59="20 Micron",$R59="5 Micron",$R59="N C"),$AE59*1/350,0))))),2) -> #DIV/0! | AG59: =IF(ISNUMBER(N59), CEILING(MAX(AI59,AJ59),0.5), "Ambient") -> #DIV/0! | AH59: D | AI59: =IF(ISNUMBER(N59), CEILING(CE59/12000,0.5), "Ambient") -> 0 | AJ59: =IF(ISNUMBER(N59),CEILING(AE59/(IF(AH59="C",400,300)),0.5), "Ambient") -> #DIV/0! | AL59: =IF(AN50<=315,1600,(IF(AN50=355,1650,(IF(AN50=400,1650,(IF(AN50=450,1700,(IF(AN50=500,1700,(IF(AN50=560,1800,(IF(AN50=630,2000,(IF(AN50=710,2200,2500)))))))))))))))+IF(AR50=2,1800,(IF(AR50=3,2300,(IF(AR50=4,3300,0)))))+IF(AP50<=4,600,(IF(AP50<=6,800,(IF(AP50<=8,1000,1200))))) -> #DIV/0!
C60: =IF(D60<>"",COUNTA($D$10:D60),"") -> 45 | D60: Clean Room 20 | E60: 2.1 | F60: 1.8 | G60: 2.4 | H60: 2 | I60: 1 | J60: 1.75 | K60: 3 | L60: 0.1 | M60: 0 | N60: 24 | O60: 50 | P60: 45 | Q60: 85 | R60: GRADE A | S60: 150 | T60: 0 | U60: 100 | V60: =R60 -> GRADE A | W60: =S60 -> 150 | X60: =E60*F60*10.76 -> 40.6728 | Y60: =X60*G60*3.28 -> 320.17628 | Z60: =Y60*S60/60 -> 800.4407 | AA60: =Z60*L60 -> 80.04407 | AB60: =IF(N60="Amb",Z60,Z60*M60) -> 0 | AC60: =IF(ISNUMBER(N60), (AA60*0.075*60/2.20462)*BP60/7000, "Ambient") -> 0 | AD60: =IF(ISNUMBER(N60), CEILING(CF60/(0.68*BP60),25), "Ambient") -> #DIV/0! | AE60: =CEILING(MAX((Z60+AA60),AD60),25) -> #DIV/0! | AF60: =CEILING(IF(OR($R60="ISO 6",$R60="GRADE B",$R60="1K",$R60=1000),AE60*1/175,IF(OR($R60="ISO 5",$R60="GRADE A",$R60=100),AE60*1/100,IF(OR($R60="ISO 7",$R60="GRADE C",$R60="10K",$R60=10000),$AE60*1/250,IF(OR($R60="ISO 8",$R60="GRADE D",$R60="100K",$R60=100000),$AE60*1/250,IF(OR($R60="NC",$R60="20 Micron",$R60="5 Micron",$R60="N C"),$AE60*1/350,0))))),2) -> #DIV/0! | AG60: =IF(ISNUMBER(N60), CEILING(MAX(AI60,AJ60),0.5), "Ambient") -> #DIV/0! | AH60: D | AI60: =IF(ISNUMBER(N60), CEILING(CE60/12000,0.5), "Ambient") -> 0 | AJ60: =IF(ISNUMBER(N60),CEILING(AE60/(IF(AH60="C",400,300)),0.5), "Ambient") -> #DIV/0!
C61: =IF(D61<>"",COUNTA($D$10:D61),"") -> 46 | D61: Clean Room 21 | E61: 1.8 | F61: 1.9 | G61: 2.4 | H61: 2 | I61: 1 | J61: 1.75 | K61: 3 | L61: 0.1 | M61: 0 | N61: 24 | O61: 50 | P61: 45 | Q61: 85 | R61: GRADE A | S61: 150 | T61: 0 | U61: 100 | V61: =R61 -> GRADE A | W61: =S61 -> 150 | X61: =E61*F61*10.76 -> 36.7992 | Y61: =X61*G61*3.28 -> 289.6833 | Z61: =Y61*S61/60 -> 724.20826 | AA61: =Z61*L61 -> 72.420826 | AB61: =IF(N61="Amb",Z61,Z61*M61) -> 0 | AC61: =IF(ISNUMBER(N61), (AA61*0.075*60/2.20462)*BP61/7000, "Ambient") -> 0 | AD61: =IF(ISNUMBER(N61), CEILING(CF61/(0.68*BP61),25), "Ambient") -> #DIV/0! | AE61: =CEILING(MAX((Z61+AA61),AD61),25) -> #DIV/0! | AF61: =CEILING(IF(OR($R61="ISO 6",$R61="GRADE B",$R61="1K",$R61=1000),AE61*1/175,IF(OR($R61="ISO 5",$R61="GRADE A",$R61=100),AE61*1/100,IF(OR($R61="ISO 7",$R61="GRADE C",$R61="10K",$R61=10000),$AE61*1/250,IF(OR($R61="ISO 8",$R61="GRADE D",$R61="100K",$R61=100000),$AE61*1/250,IF(OR($R61="NC",$R61="20 Micron",$R61="5 Micron",$R61="N C"),$AE61*1/350,0))))),2) -> #DIV/0! | AG61: =IF(ISNUMBER(N61), CEILING(MAX(AI61,AJ61),0.5), "Ambient") -> #DIV/0! | AH61: D | AI61: =IF(ISNUMBER(N61), CEILING(CE61/12000,0.5), "Ambient") -> 0 | AJ61: =IF(ISNUMBER(N61),CEILING(AE61/(IF(AH61="C",400,300)),0.5), "Ambient") -> #DIV/0!
C62: =IF(D62<>"",COUNTA($D$10:D62),"") -> 47 | D62: Clean Room 22 | E62: 1.9 | F62: 2 | G62: 2.4 | H62: 2 | I62: 1 | J62: 1.75 | K62: 3 | L62: 0.1 | M62: 0 | N62: 24 | O62: 50 | P62: 45 | Q62: 85 | R62: GRADE A | S62: 150 | T62: 0 | U62: 100 | V62: =R62 -> GRADE A | W62: =S62 -> 150 | X62: =E62*F62*10.76 -> 40.888 | Y62: =X62*G62*3.28 -> 321.87034 | Z62: =Y62*S62/60 -> 804.67584 | AA62: =Z62*L62 -> 80.467584 | AB62: =IF(N62="Amb",Z62,Z62*M62) -> 0 | AC62: =IF(ISNUMBER(N62), (AA62*0.075*60/2.20462)*BP62/7000, "Ambient") -> 0 | AD62: =IF(ISNUMBER(N62), CEILING(CF62/(0.68*BP62),25), "Ambient") -> #DIV/0! | AE62: =CEILING(MAX((Z62+AA62),AD62),25) -> #DIV/0! | AF62: =CEILING(IF(OR($R62="ISO 6",$R62="GRADE B",$R62="1K",$R62=1000),AE62*1/175,IF(OR($R62="ISO 5",$R62="GRADE A",$R62=100),AE62*1/100,IF(OR($R62="ISO 7",$R62="GRADE C",$R62="10K",$R62=10000),$AE62*1/250,IF(OR($R62="ISO 8",$R62="GRADE D",$R62="100K",$R62=100000),$AE62*1/250,IF(OR($R62="NC",$R62="20 Micron",$R62="5 Micron",$R62="N C"),$AE62*1/350,0))))),2) -> #DIV/0! | AG62: =IF(ISNUMBER(N62), CEILING(MAX(AI62,AJ62),0.5), "Ambient") -> #DIV/0! | AH62: D | AI62: =IF(ISNUMBER(N62), CEILING(CE62/12000,0.5), "Ambient") -> 0 | AJ62: =IF(ISNUMBER(N62),CEILING(AE62/(IF(AH62="C",400,300)),0.5), "Ambient") -> #DIV/0!
C63: =IF(D63<>"",COUNTA($D$10:D63),"") -> 48 | D63: Clean Room 23 | E63: 2.3 | F63: 2.2 | G63: 2.4 | H63: 2 | I63: 1 | J63: 1.75 | K63: 3 | L63: 0.1 | M63: 0 | N63: 24 | O63: 50 | P63: 45 | Q63: 85 | R63: GRADE A | S63: 150 | T63: 0 | U63: 100 | V63: =R63 -> GRADE A | W63: =S63 -> 150 | X63: =E63*F63*10.76 -> 54.4456 | Y63: =X63*G63*3.28 -> 428.59576 | Z63: =Y63*S63/60 -> 1071.4894 | AA63: =Z63*L63 -> 107.14894 | AB63: =IF(N63="Amb",Z63,Z63*M63) -> 0 | AC63: =IF(ISNUMBER(N63), (AA63*0.075*60/2.20462)*BP63/7000, "Ambient") -> 0 | AD63: =IF(ISNUMBER(N63), CEILING(CF63/(0.68*BP63),25), "Ambient") -> #DIV/0! | AE63: =CEILING(MAX((Z63+AA63),AD63),25) -> #DIV/0! | AF63: =CEILING(IF(OR($R63="ISO 6",$R63="GRADE B",$R63="1K",$R63=1000),AE63*1/175,IF(OR($R63="ISO 5",$R63="GRADE A",$R63=100),AE63*1/100,IF(OR($R63="ISO 7",$R63="GRADE C",$R63="10K",$R63=10000),$AE63*1/250,IF(OR($R63="ISO 8",$R63="GRADE D",$R63="100K",$R63=100000),$AE63*1/250,IF(OR($R63="NC",$R63="20 Micron",$R63="5 Micron",$R63="N C"),$AE63*1/350,0))))),2) -> #DIV/0! | AG63: =IF(ISNUMBER(N63), CEILING(MAX(AI63,AJ63),0.5), "Ambient") -> #DIV/0! | AH63: D | AI63: =IF(ISNUMBER(N63), CEILING(CE63/12000,0.5), "Ambient") -> 0 | AJ63: =IF(ISNUMBER(N63),CEILING(AE63/(IF(AH63="C",400,300)),0.5), "Ambient") -> #DIV/0!
C64: =IF(D64<>"",COUNTA($D$10:D64),"") -> 49 | D64: Clean Room 24 | E64: 2.2 | F64: 2.8 | G64: 2.4 | H64: 2 | I64: 1 | J64: 1.75 | K64: 3 | L64: 0.1 | M64: 0 | N64: 24 | O64: 50 | P64: 45 | Q64: 85 | R64: GRADE A | S64: 150 | T64: 0 | U64: 100 | V64: =R64 -> GRADE A | W64: =S64 -> 150 | X64: =E64*F64*10.76 -> 66.2816 | Y64: =X64*G64*3.28 -> 521.76876 | Z64: =Y64*S64/60 -> 1304.4219 | AA64: =Z64*L64 -> 130.44219 | AB64: =IF(N64="Amb",Z64,Z64*M64) -> 0 | AC64: =IF(ISNUMBER(N64), (AA64*0.075*60/2.20462)*BP64/7000, "Ambient") -> 0 | AD64: =IF(ISNUMBER(N64), CEILING(CF64/(0.68*BP64),25), "Ambient") -> #DIV/0! | AE64: =CEILING(MAX((Z64+AA64),AD64),25) -> #DIV/0! | AF64: =CEILING(IF(OR($R64="ISO 6",$R64="GRADE B",$R64="1K",$R64=1000),AE64*1/175,IF(OR($R64="ISO 5",$R64="GRADE A",$R64=100),AE64*1/100,IF(OR($R64="ISO 7",$R64="GRADE C",$R64="10K",$R64=10000),$AE64*1/250,IF(OR($R64="ISO 8",$R64="GRADE D",$R64="100K",$R64=100000),$AE64*1/250,IF(OR($R64="NC",$R64="20 Micron",$R64="5 Micron",$R64="N C"),$AE64*1/350,0))))),2) -> #DIV/0! | AG64: =IF(ISNUMBER(N64), CEILING(MAX(AI64,AJ64),0.5), "Ambient") -> #DIV/0! | AH64: D | AI64: =IF(ISNUMBER(N64), CEILING(CE64/12000,0.5), "Ambient") -> 0 | AJ64: =IF(ISNUMBER(N64),CEILING(AE64/(IF(AH64="C",400,300)),0.5), "Ambient") -> #DIV/0!
C65: =IF(D65<>"",COUNTA($D$10:D65),"") -> 50 | D65: Clean Room 25 | E65: 2.8 | F65: 2.4 | G65: 2.4 | H65: 2 | I65: 1 | J65: 1.75 | K65: 3 | L65: 0.1 | M65: 0 | N65: 24 | O65: 50 | P65: 45 | Q65: 85 | R65: GRADE A | S65: 150 | T65: 0 | U65: 100 | V65: =R65 -> GRADE A | W65: =S65 -> 150 | X65: =E65*F65*10.76 -> 72.3072 | Y65: =X65*G65*3.28 -> 569.20228 | Z65: =Y65*S65/60 -> 1423.0057 | AA65: =Z65*L65 -> 142.30057 | AB65: =IF(N65="Amb",Z65,Z65*M65) -> 0 | AC65: =IF(ISNUMBER(N65), (AA65*0.075*60/2.20462)*BP65/7000, "Ambient") -> 0 | AD65: =IF(ISNUMBER(N65), CEILING(CF65/(0.68*BP65),25), "Ambient") -> #DIV/0! | AE65: =CEILING(MAX((Z65+AA65),AD65),25) -> #DIV/0! | AF65: =CEILING(IF(OR($R65="ISO 6",$R65="GRADE B",$R65="1K",$R65=1000),AE65*1/175,IF(OR($R65="ISO 5",$R65="GRADE A",$R65=100),AE65*1/100,IF(OR($R65="ISO 7",$R65="GRADE C",$R65="10K",$R65=10000),$AE65*1/250,IF(OR($R65="ISO 8",$R65="GRADE D",$R65="100K",$R65=100000),$AE65*1/250,IF(OR($R65="NC",$R65="20 Micron",$R65="5 Micron",$R65="N C"),$AE65*1/350,0))))),2) -> #DIV/0! | AG65: =IF(ISNUMBER(N65), CEILING(MAX(AI65,AJ65),0.5), "Ambient") -> #DIV/0! | AH65: D | AI65: =IF(ISNUMBER(N65), CEILING(CE65/12000,0.5), "Ambient") -> 0 | AJ65: =IF(ISNUMBER(N65),CEILING(AE65/(IF(AH65="C",400,300)),0.5), "Ambient") -> #DIV/0!
C66: =IF(D66<>"",COUNTA($D$10:D66),"") | X66: =SUM(X50:X65) -> 1144.1108 | Y66: =SUM(Y50:Y65) -> 9006.4402 | Z66: =SUM(Z50:Z65) -> 22516.101 | AA66: =SUM(AA50:AA65) -> 2251.6101 | AB66: =SUM(AB50:AB65) -> 0 | AC66: =SUM(AC50:AC65) -> 0 | AD66: =SUM(AD50:AD65) -> #DIV/0! | AE66: =SUM(AE50:AE65) -> #DIV/0! | ... AG66: =SUM(AG50:AG65) -> #DIV/0! | AI66: =SUM(AI50:AI65) -> 0 | AJ66: =SUM(AJ50:AJ65) -> #DIV/0!
C67: =IF(D67<>"",COUNTA($D$10:D67),"")
C68: ="Zoning Area AHU - " & INT((ROW()-8)/20)+1 & " " &IF(AQ70>0,"Air-Conditioning System " & IF(AH70="D","(DX)",IF(AH70="C","(Chilled Water)","")),IF(AND(N70="Amb",AQ70=0),"Ventilation System","Refer")) -> #DIV/0! | AS68: Chilled Water Details | AW68: Hot Water/Steam Details
C69: =IF(D69<>"",COUNTA($D$10:D69),"") -> 51 | D69: Room Name | E69: Length in mtrs | F69: Width in mtrs | G69: Height in mtrs | H69: People in Nos | I69: Eqpt. Load in KW | J69: Lighting in W/Sft | K69: No.of Inf./Hr | L69: Fresh Air | M69: Exhaust | N69: T ˚C (Required inside) | O69: RH(in) +/- 5% | P69: Peak Max Temp.(Out) in ˚C | Q69: RH(Out) in +/- 5% | R69: Class | S69: ACPH | T69: Peak Min Temp.(Out) in ˚C | U69: RH(Out) +/- 5% | V69: Class | W69: ACPH | X69: Area | Y69: Volume | Z69: Room Cfm | AA69: FA | AB69: EA | AC69: Rem. Water vapour Kg/hr | AD69: Deh. Cfm | AE69: Res. Cfm | AF69: Room Terminal Supply Module in Sft | AG69: Res. Cooling Load in TR | AH69: Chilled Water (C) OR DX (D) | AI69: Room AC load in TR | AJ69: Cfm AC load in TR | AK69: AHU Cfm | AL69: AHU Size | AM69: Static Pressure | AN69: Blower Model BDB | AO69: Motor Selected in Hp | AP69: No. of Rows of Cooling Coil | AQ69: AHU Cooling Load in TR | AR69: No. Of Stages of Filtr. | AS69: Chilled water in GPM | AT69: Chilled water in L/s | AU69: Flow Velocity in m/s | AV69: Pipe Size in mm | AW69: Hot Water/Steam in GPM | AX69: Hot water/Steam in L/s | AY69: Flow Velocity | AZ69: Pipe Size
C70: =IF(D70<>"",COUNTA($D$10:D70),"") -> 52 | D70: Clean Room 10 | E70: 3 | F70: 3 | G70: 2.4 | H70: 1 | I70: 2 | J70: 1.75 | K70: 3 | L70: 0.1 | M70: 0 | N70: 24 | O70: 50 | P70: 45 | Q70: 85 | R70: 10K | S70: 80 | T70: 0 | U70: 100 | V70: =R70 -> 10K | W70: =S70 -> 80 | X70: =E70*F70*10.76 -> 96.84 | Y70: =X70*G70*3.28 -> 762.32448 | Z70: =Y70*S70/60 -> 1016.4326 | AA70: =Z70*L70 -> 101.64326 | AB70: =IF(N70="Amb",Z70,Z70*M70) -> 0 | AC70: =IF(ISNUMBER(N70), (AA70*0.075*60/2.20462)*BP70/7000, "Ambient") -> 0 | AD70: =IF(ISNUMBER(N70), CEILING(CF70/(0.68*BP70),25), "Ambient") -> #DIV/0! | AE70: =CEILING(MAX((Z70+AA70),AD70),25) -> #DIV/0! | AF70: =CEILING(IF(OR($R70="ISO 6",$R70="GRADE B",$R70="1K",$R70=1000),AE70*1/175,IF(OR($R70="ISO 5",$R70="GRADE A",$R70=100),AE70*1/100,IF(OR($R70="ISO 7",$R70="GRADE C",$R70="10K",$R70=10000),$AE70*1/250,IF(OR($R70="ISO 8",$R70="GRADE D",$R70="100K",$R70=100000),$AE70*1/250,IF(OR($R70="NC",$R70="20 Micron",$R70="5 Micron",$R70="N C"),$AE70*1/350,0))))),2) -> #DIV/0! | AG70: =IF(ISNUMBER(N70), CEILING(MAX(AI70,AJ70),0.5), "Ambient") -> #DIV/0! | AH70: C | AI70: =IF(ISNUMBER(N70), CEILING(CE70/12000,0.5), "Ambient") -> 0 | AJ70: =IF(ISNUMBER(N70),CEILING(AE70/(IF(AH70="C",400,300)),0.5), "Ambient") -> #DIV/0! | AK70: =CEILING(SUM(AE70:AE85),250) -> #DIV/0! | AL70: W | AM70: 150 | AN70: =IF(AK70<=1300,200,IF(AK70<=1600,225,IF(AK70<=2100,250,IF(AK70<=2700,280,IF(AK70<=3450,315,IF(AK70<=4250,355,IF(AK70<=5250,400,IF(AK70<=6750,450,IF(AK70<=8500,500,IF(AK70<=10750,560,IF(AK70<=13500,630,IF(AK70<=17000,710,IF(AK70<=21500,800,IF(AK70<=27000,900,IF(AK70<=34000,1000,IF(AK70<=43000,1120,IF(AK70<=49000,1200,IF(AK70<=68000,1450,"Refer")))))))))))))))))) -> #DIV/0! | AO70: =IF(AK70*AM70/(6356*0.7*0.9*1.1*25.4)<=1,1,IF(AK70*AM70/(6356*0.7*0.9*1.1*25.4)<=1.5,1.5,IF(AK70*AM70/(6356*0.7*0.9*1.1*25.4)<=2,2,IF(AK70*AM70/(6356*0.7*0.9*1.1*25.4)<=3,3,IF(AK70*AM70/(6356*0.7*0.9*1.1*25.4)<=5,5,IF(AK70*AM70/(6356*0.7*0.9*1.1*25.4)<=7.5,7.5,IF(AK70*AM70/(6356*0.7*0.9*1.1*25.4)<=10,10,IF(AK70*AM70/(6356*0.7*0.9*1.1*25.4)<=12.5,12.5,IF(AK70*AM70/(6356*0.7*0.9*1.1*25.4)<=15,15,IF(AK70*AM70/(6356*0.7*0.9*1.1*25.4)<=20,20,IF(AK70*AM70/(6356*0.7*0.9*1.1*25.4)<=25,25,IF(AK70*AM70/(6356*0.7*0.9*1.1*25.4)<=30,30,IF(AK70*AM70/(6356*0.7*0.9*1.1*25.4)<=40,40,IF(AK70*AM70/(6356*0.7*0.9*1.1*25.4)<=50,50,IF(AK70*AM70/(6356*0.7*0.9*1.1*25.4)<=60,60,IF(AK70*AM70/(6356*0.7*0.9*1.1*25.4)<=75,75,"Refer")))))))))))))))) -> #DIV/0! | AP70: =IF(AND(AQ70=0, N70="Amb"), "Amb",IF((AL71-250)*(AL73-150)*10.76/(1000*1000) >= MAX(AI86,AJ86), 4,IF((AL71-250)*(AL73-150)*10.76*1.5/(1000*1000) >= MAX(AI86,AJ86), 6,IF((AL71-250)*(AL73-150)*10.76*2/(1000*1000) >= MAX(AI86,AJ86), 8, 0)) ) ) -> #DIV/0! | AQ70: =AG86 -> #DIV/0! | AR70: =_xlfn.SWITCH(TRIM(UPPER(R70)),"ISO 9", 3,"ISO 8", 4,"Grade D", 4,"Class 100,000", 4,"Class 100K", 4,"ISO 7", 3,"Grade C", 3,"Class 10,000", 3,"Class 10K", 3,"ISO 6", 3,"Class 1,000", 3,"Class 1K", 3,"ISO 5", 4,"Grade A", 4,"Grade B", 4,"Class 100", 4,"ISO 4", 3,"ISO 3", 4,"ISO 2", 4,"ISO 1", 4,"NCV20",1,"NCV-10",2,"NCV-5",3,"NCAC-10",1,"NCAC-5",2,"NCAC-1",3,3) -> 3 | AS70: =MAX(AI86,AJ86)*24/6 -> #DIV/0! | AT70: =AS70*0.06309 -> #DIV/0! | AU70: 2 | AV70: =SQRT((4*AS70*0.00006309)/(3.14*AU70))*1000 -> #DIV/0!
C71: =IF(D71<>"",COUNTA($D$10:D71),"") -> 53 | D71: Clean Room 11 | E71: 1.8 | F71: 2.2 | G71: 2.4 | H71: 2 | I71: 1 | J71: 1.75 | K71: 3 | L71: 0.1 | M71: 0 | N71: 24 | O71: 50 | P71: 45 | Q71: 85 | R71: 10K | S71: 80 | T71: 0 | U71: 100 | V71: =R71 -> 10K | W71: =S71 -> 80 | X71: =E71*F71*10.76 -> 42.6096 | Y71: =X71*G71*3.28 -> 335.42277 | Z71: =Y71*S71/60 -> 447.23036 | AA71: =Z71*L71 -> 44.723036 | AB71: =IF(N71="Amb",Z71,Z71*M71) -> 0 | AC71: =IF(ISNUMBER(N71), (AA71*0.075*60/2.20462)*BP71/7000, "Ambient") -> 0 | AD71: =IF(ISNUMBER(N71), CEILING(CF71/(0.68*BP71),25), "Ambient") -> #DIV/0! | AE71: =CEILING(MAX((Z71+AA71),AD71),25) -> #DIV/0! | AF71: =CEILING(IF(OR($R71="ISO 6",$R71="GRADE B",$R71="1K",$R71=1000),AE71*1/175,IF(OR($R71="ISO 5",$R71="GRADE A",$R71=100),AE71*1/100,IF(OR($R71="ISO 7",$R71="GRADE C",$R71="10K",$R71=10000),$AE71*1/250,IF(OR($R71="ISO 8",$R71="GRADE D",$R71="100K",$R71=100000),$AE71*1/250,IF(OR($R71="NC",$R71="20 Micron",$R71="5 Micron",$R71="N C"),$AE71*1/350,0))))),2) -> #DIV/0! | AG71: =IF(ISNUMBER(N71), CEILING(MAX(AI71,AJ71),0.5), "Ambient") -> #DIV/0! | AH71: C | AI71: =IF(ISNUMBER(N71), CEILING(CE71/12000,0.5), "Ambient") -> 0 | AJ71: =IF(ISNUMBER(N71),CEILING(AE71/(IF(AH71="C",400,300)),0.5), "Ambient") -> #DIV/0! | AL71: =IF(AK70<=2000,950,(IF(AK70<=3000,1150,(IF(AK70<=8000,1550,(IF(AK70<=10000,1750,(IF(AK70<=18000,2050,(IF(AK70<=32000,2900,(IF(AK70<=40000,3600,4000))))))))))))) -> #DIV/0!
C72: =IF(D72<>"",COUNTA($D$10:D72),"") -> 54 | D72: Clean Room 12 | E72: 1.5 | F72: 2.8 | G72: 2.4 | H72: 2 | I72: 3 | J72: 1.75 | K72: 3 | L72: 0.1 | M72: 0 | N72: 24 | O72: 50 | P72: 45 | Q72: 85 | R72: 10K | S72: 80 | T72: 0 | U72: 100 | V72: =R72 -> 10K | W72: =S72 -> 80 | X72: =E72*F72*10.76 -> 45.192 | Y72: =X72*G72*3.28 -> 355.75142 | Z72: =Y72*S72/60 -> 474.33523 | AA72: =Z72*L72 -> 47.433523 | AB72: =IF(N72="Amb",Z72,Z72*M72) -> 0 | AC72: =IF(ISNUMBER(N72), (AA72*0.075*60/2.20462)*BP72/7000, "Ambient") -> 0 | AD72: =IF(ISNUMBER(N72), CEILING(CF72/(0.68*BP72),25), "Ambient") -> #DIV/0! | AE72: =CEILING(MAX((Z72+AA72),AD72),25) -> #DIV/0! | AF72: =CEILING(IF(OR($R72="ISO 6",$R72="GRADE B",$R72="1K",$R72=1000),AE72*1/175,IF(OR($R72="ISO 5",$R72="GRADE A",$R72=100),AE72*1/100,IF(OR($R72="ISO 7",$R72="GRADE C",$R72="10K",$R72=10000),$AE72*1/250,IF(OR($R72="ISO 8",$R72="GRADE D",$R72="100K",$R72=100000),$AE72*1/250,IF(OR($R72="NC",$R72="20 Micron",$R72="5 Micron",$R72="N C"),$AE72*1/350,0))))),2) -> #DIV/0! | AG72: =IF(ISNUMBER(N72), CEILING(MAX(AI72,AJ72),0.5), "Ambient") -> #DIV/0! | AH72: C | AI72: =IF(ISNUMBER(N72), CEILING(CE72/12000,0.5), "Ambient") -> 0 | AJ72: =IF(ISNUMBER(N72),CEILING(AE72/(IF(AH72="C",400,300)),0.5), "Ambient") -> #DIV/0! | AL72: H
C73: =IF(D73<>"",COUNTA($D$10:D73),"") -> 55 | D73: Clean Room 13 | E73: 2.1 | F73: 3.5 | G73: 2.4 | H73: 0 | I73: 1 | J73: 1.75 | K73: 3 | L73: 0.1 | M73: 0 | N73: 24 | O73: 50 | P73: 45 | Q73: 85 | R73: 10K | S73: 80 | T73: 0 | U73: 100 | V73: =R73 -> 10K | W73: =S73 -> 80 | X73: =E73*F73*10.76 -> 79.086 | Y73: =X73*G73*3.28 -> 622.56499 | Z73: =Y73*S73/60 -> 830.08666 | AA73: =Z73*L73 -> 83.008666 | AB73: =IF(N73="Amb",Z73,Z73*M73) -> 0 | AC73: =IF(ISNUMBER(N73), (AA73*0.075*60/2.20462)*BP73/7000, "Ambient") -> 0 | AD73: =IF(ISNUMBER(N73), CEILING(CF73/(0.68*BP73),25), "Ambient") -> #DIV/0! | AE73: =CEILING(MAX((Z73+AA73),AD73),25) -> #DIV/0! | AF73: =CEILING(IF(OR($R73="ISO 6",$R73="GRADE B",$R73="1K",$R73=1000),AE73*1/175,IF(OR($R73="ISO 5",$R73="GRADE A",$R73=100),AE73*1/100,IF(OR($R73="ISO 7",$R73="GRADE C",$R73="10K",$R73=10000),$AE73*1/250,IF(OR($R73="ISO 8",$R73="GRADE D",$R73="100K",$R73=100000),$AE73*1/250,IF(OR($R73="NC",$R73="20 Micron",$R73="5 Micron",$R73="N C"),$AE73*1/350,0))))),2) -> #DIV/0! | AG73: =IF(ISNUMBER(N73), CEILING(MAX(AI73,AJ73),0.5), "Ambient") -> #DIV/0! | AH73: C | AI73: =IF(ISNUMBER(N73), CEILING(CE73/12000,0.5), "Ambient") -> 0 | AJ73: =IF(ISNUMBER(N73),CEILING(AE73/(IF(AH73="C",400,300)),0.5), "Ambient") -> #DIV/0! | AL73: =IF(AK70<=2000,950,(IF(AK70<=4000,1100,(IF(AK70<=6000,1250,(IF(AK70<=10000,1550,(IF(AK70<=15000,1750,(IF(AK70<=24000,2050,(IF(AK70<=40000,2900,3600))))))))))))) -> #DIV/0!
C74: =IF(D74<>"",COUNTA($D$10:D74),"") -> 56 | D74: Clean Room 14 | E74: 2.7 | F74: 4 | G74: 2.4 | H74: 2 | I74: 1 | J74: 1.75 | K74: 3 | L74: 0.1 | M74: 0 | N74: 24 | O74: 50 | P74: 45 | Q74: 85 | R74: 10K | S74: 80 | T74: 0 | U74: 100 | V74: =R74 -> 10K | W74: =S74 -> 80 | X74: =E74*F74*10.76 -> 116.208 | Y74: =X74*G74*3.28 -> 914.78938 | Z74: =Y74*S74/60 -> 1219.7192 | AA74: =Z74*L74 -> 121.97192 | AB74: =IF(N74="Amb",Z74,Z74*M74) -> 0 | AC74: =IF(ISNUMBER(N74), (AA74*0.075*60/2.20462)*BP74/7000, "Ambient") -> 0 | AD74: =IF(ISNUMBER(N74), CEILING(CF74/(0.68*BP74),25), "Ambient") -> #DIV/0! | AE74: =CEILING(MAX((Z74+AA74),AD74),25) -> #DIV/0! | AF74: =CEILING(IF(OR($R74="ISO 6",$R74="GRADE B",$R74="1K",$R74=1000),AE74*1/175,IF(OR($R74="ISO 5",$R74="GRADE A",$R74=100),AE74*1/100,IF(OR($R74="ISO 7",$R74="GRADE C",$R74="10K",$R74=10000),$AE74*1/250,IF(OR($R74="ISO 8",$R74="GRADE D",$R74="100K",$R74=100000),$AE74*1/250,IF(OR($R74="NC",$R74="20 Micron",$R74="5 Micron",$R74="N C"),$AE74*1/350,0))))),2) -> #DIV/0! | AG74: =IF(ISNUMBER(N74), CEILING(MAX(AI74,AJ74),0.5), "Ambient") -> #DIV/0! | AH74: C | AI74: =IF(ISNUMBER(N74), CEILING(CE74/12000,0.5), "Ambient") -> 0 | AJ74: =IF(ISNUMBER(N74),CEILING(AE74/(IF(AH74="C",400,300)),0.5), "Ambient") -> #DIV/0! | AL74: L
C75: =IF(D75<>"",COUNTA($D$10:D75),"") -> 57 | D75: Clean Room 15 | E75: 3.8 | F75: 4.2 | G75: 2.4 | H75: 3 | I75: 3 | J75: 1.75 | K75: 3 | L75: 0.1 | M75: 0 | N75: 24 | O75: 50 | P75: 45 | Q75: 85 | R75: 10K | S75: 80 | T75: 0 | U75: 100 | V75: =R75 -> 10K | W75: =S75 -> 80 | X75: =E75*F75*10.76 -> 171.7296 | Y75: =X75*G75*3.28 -> 1351.8554 | Z75: =Y75*S75/60 -> 1802.4739 | AA75: =Z75*L75 -> 180.24739 | AB75: =IF(N75="Amb",Z75,Z75*M75) -> 0 | AC75: =IF(ISNUMBER(N75), (AA75*0.075*60/2.20462)*BP75/7000, "Ambient") -> 0 | AD75: =IF(ISNUMBER(N75), CEILING(CF75/(0.68*BP75),25), "Ambient") -> #DIV/0! | AE75: =CEILING(MAX((Z75+AA75),AD75),25) -> #DIV/0! | AF75: =CEILING(IF(OR($R75="ISO 6",$R75="GRADE B",$R75="1K",$R75=1000),AE75*1/175,IF(OR($R75="ISO 5",$R75="GRADE A",$R75=100),AE75*1/100,IF(OR($R75="ISO 7",$R75="GRADE C",$R75="10K",$R75=10000),$AE75*1/250,IF(OR($R75="ISO 8",$R75="GRADE D",$R75="100K",$R75=100000),$AE75*1/250,IF(OR($R75="NC",$R75="20 Micron",$R75="5 Micron",$R75="N C"),$AE75*1/350,0))))),2) -> #DIV/0! | AG75: =IF(ISNUMBER(N75), CEILING(MAX(AI75,AJ75),0.5), "Ambient") -> #DIV/0! | AH75: C | AI75: =IF(ISNUMBER(N75), CEILING(CE75/12000,0.5), "Ambient") -> 0 | AJ75: =IF(ISNUMBER(N75),CEILING(AE75/(IF(AH75="C",400,300)),0.5), "Ambient") -> #DIV/0! | AL75: =IF(AL79<4000,AL79,AL79+400) -> #DIV/0!
C76: =IF(D76<>"",COUNTA($D$10:D76),"") -> 58 | D76: Clean Room 16 | E76: 3.1 | F76: 2.6 | G76: 2.4 | H76: 2 | I76: 1 | J76: 1.75 | K76: 3 | L76: 0.1 | M76: 0 | N76: 24 | O76: 50 | P76: 45 | Q76: 85 | R76: 10K | S76: 80 | T76: 0 | U76: 100 | V76: =R76 -> 10K | W76: =S76 -> 80 | X76: =E76*F76*10.76 -> 86.7256 | Y76: =X76*G76*3.28 -> 682.70392 | Z76: =Y76*S76/60 -> 910.2719 | AA76: =Z76*L76 -> 91.02719 | AB76: =IF(N76="Amb",Z76,Z76*M76) -> 0 | AC76: =IF(ISNUMBER(N76), (AA76*0.075*60/2.20462)*BP76/7000, "Ambient") -> 0 | AD76: =IF(ISNUMBER(N76), CEILING(CF76/(0.68*BP76),25), "Ambient") -> #DIV/0! | AE76: =CEILING(MAX((Z76+AA76),AD76),25) -> #DIV/0! | AF76: =CEILING(IF(OR($R76="ISO 6",$R76="GRADE B",$R76="1K",$R76=1000),AE76*1/175,IF(OR($R76="ISO 5",$R76="GRADE A",$R76=100),AE76*1/100,IF(OR($R76="ISO 7",$R76="GRADE C",$R76="10K",$R76=10000),$AE76*1/250,IF(OR($R76="ISO 8",$R76="GRADE D",$R76="100K",$R76=100000),$AE76*1/250,IF(OR($R76="NC",$R76="20 Micron",$R76="5 Micron",$R76="N C"),$AE76*1/350,0))))),2) -> #DIV/0! | AG76: =IF(ISNUMBER(N76), CEILING(MAX(AI76,AJ76),0.5), "Ambient") -> #DIV/0! | AH76: C | AI76: =IF(ISNUMBER(N76), CEILING(CE76/12000,0.5), "Ambient") -> 0 | AJ76: =IF(ISNUMBER(N76),CEILING(AE76/(IF(AH76="C",400,300)),0.5), "Ambient") -> #DIV/0!
C77: =IF(D77<>"",COUNTA($D$10:D77),"") -> 59 | D77: Clean Room 17 | E77: 1.9 | F77: 2.4 | G77: 2.4 | H77: 3 | I77: 2 | J77: 1.75 | K77: 3 | L77: 0.1 | M77: 0 | N77: 24 | O77: 50 | P77: 45 | Q77: 85 | R77: 10K | S77: 80 | T77: 0 | U77: 100 | V77: =R77 -> 10K | W77: =S77 -> 80 | X77: =E77*F77*10.76 -> 49.0656 | Y77: =X77*G77*3.28 -> 386.2444 | Z77: =Y77*S77/60 -> 514.99254 | AA77: =Z77*L77 -> 51.499254 | AB77: =IF(N77="Amb",Z77,Z77*M77) -> 0 | AC77: =IF(ISNUMBER(N77), (AA77*0.075*60/2.20462)*BP77/7000, "Ambient") -> 0 | AD77: =IF(ISNUMBER(N77), CEILING(CF77/(0.68*BP77),25), "Ambient") -> #DIV/0! | AE77: =CEILING(MAX((Z77+AA77),AD77),25) -> #DIV/0! | AF77: =CEILING(IF(OR($R77="ISO 6",$R77="GRADE B",$R77="1K",$R77=1000),AE77*1/175,IF(OR($R77="ISO 5",$R77="GRADE A",$R77=100),AE77*1/100,IF(OR($R77="ISO 7",$R77="GRADE C",$R77="10K",$R77=10000),$AE77*1/250,IF(OR($R77="ISO 8",$R77="GRADE D",$R77="100K",$R77=100000),$AE77*1/250,IF(OR($R77="NC",$R77="20 Micron",$R77="5 Micron",$R77="N C"),$AE77*1/350,0))))),2) -> #DIV/0! | AG77: =IF(ISNUMBER(N77), CEILING(MAX(AI77,AJ77),0.5), "Ambient") -> #DIV/0! | AH77: C | AI77: =IF(ISNUMBER(N77), CEILING(CE77/12000,0.5), "Ambient") -> 0 | AJ77: =IF(ISNUMBER(N77),CEILING(AE77/(IF(AH77="C",400,300)),0.5), "Ambient") -> #DIV/0!
C78: =IF(D78<>"",COUNTA($D$10:D78),"") -> 60 | D78: Clean Room 18 | E78: 3 | F78: 2.9 | G78: 2.4 | H78: 2 | I78: 1 | J78: 1.75 | K78: 3 | L78: 0.1 | M78: 0 | N78: 24 | O78: 50 | P78: 45 | Q78: 85 | R78: 10K | S78: 80 | T78: 0 | U78: 100 | V78: =R78 -> 10K | W78: =S78 -> 80 | X78: =E78*F78*10.76 -> 93.612 | Y78: =X78*G78*3.28 -> 736.91366 | Z78: =Y78*S78/60 -> 982.55155 | AA78: =Z78*L78 -> 98.255155 | AB78: =IF(N78="Amb",Z78,Z78*M78) -> 0 | AC78: =IF(ISNUMBER(N78), (AA78*0.075*60/2.20462)*BP78/7000, "Ambient") -> 0 | AD78: =IF(ISNUMBER(N78), CEILING(CF78/(0.68*BP78),25), "Ambient") -> #DIV/0! | AE78: =CEILING(MAX((Z78+AA78),AD78),25) -> #DIV/0! | AF78: =CEILING(IF(OR($R78="ISO 6",$R78="GRADE B",$R78="1K",$R78=1000),AE78*1/175,IF(OR($R78="ISO 5",$R78="GRADE A",$R78=100),AE78*1/100,IF(OR($R78="ISO 7",$R78="GRADE C",$R78="10K",$R78=10000),$AE78*1/250,IF(OR($R78="ISO 8",$R78="GRADE D",$R78="100K",$R78=100000),$AE78*1/250,IF(OR($R78="NC",$R78="20 Micron",$R78="5 Micron",$R78="N C"),$AE78*1/350,0))))),2) -> #DIV/0! | AG78: =IF(ISNUMBER(N78), CEILING(MAX(AI78,AJ78),0.5), "Ambient") -> #DIV/0! | AH78: C | AI78: =IF(ISNUMBER(N78), CEILING(CE78/12000,0.5), "Ambient") -> 0 | AJ78: =IF(ISNUMBER(N78),CEILING(AE78/(IF(AH78="C",400,300)),0.5), "Ambient") -> #DIV/0!
C79: =IF(D79<>"",COUNTA($D$10:D79),"") -> 61 | D79: Clean Room 19 | E79: 2.4 | F79: 2 | G79: 2.4 | H79: 2 | I79: 1 | J79: 1.75 | K79: 3 | L79: 0.1 | M79: 0 | N79: 24 | O79: 50 | P79: 45 | Q79: 85 | R79: 10K | S79: 80 | T79: 0 | U79: 100 | V79: =R79 -> 10K | W79: =S79 -> 80 | X79: =E79*F79*10.76 -> 51.648 | Y79: =X79*G79*3.28 -> 406.57306 | Z79: =Y79*S79/60 -> 542.09741 | AA79: =Z79*L79 -> 54.209741 | AB79: =IF(N79="Amb",Z79,Z79*M79) -> 0 | AC79: =IF(ISNUMBER(N79), (AA79*0.075*60/2.20462)*BP79/7000, "Ambient") -> 0 | AD79: =IF(ISNUMBER(N79), CEILING(CF79/(0.68*BP79),25), "Ambient") -> #DIV/0! | AE79: =CEILING(MAX((Z79+AA79),AD79),25) -> #DIV/0! | AF79: =CEILING(IF(OR($R79="ISO 6",$R79="GRADE B",$R79="1K",$R79=1000),AE79*1/175,IF(OR($R79="ISO 5",$R79="GRADE A",$R79=100),AE79*1/100,IF(OR($R79="ISO 7",$R79="GRADE C",$R79="10K",$R79=10000),$AE79*1/250,IF(OR($R79="ISO 8",$R79="GRADE D",$R79="100K",$R79=100000),$AE79*1/250,IF(OR($R79="NC",$R79="20 Micron",$R79="5 Micron",$R79="N C"),$AE79*1/350,0))))),2) -> #DIV/0! | AG79: =IF(ISNUMBER(N79), CEILING(MAX(AI79,AJ79),0.5), "Ambient") -> #DIV/0! | AH79: C | AI79: =IF(ISNUMBER(N79), CEILING(CE79/12000,0.5), "Ambient") -> 0 | AJ79: =IF(ISNUMBER(N79),CEILING(AE79/(IF(AH79="C",400,300)),0.5), "Ambient") -> #DIV/0! | AL79: =IF(AN70<=315,1600,(IF(AN70=355,1650,(IF(AN70=400,1650,(IF(AN70=450,1700,(IF(AN70=500,1700,(IF(AN70=560,1800,(IF(AN70=630,2000,(IF(AN70=710,2200,2500)))))))))))))))+IF(AR70=2,1800,(IF(AR70=3,2300,(IF(AR70=4,3300,0)))))+IF(AP70<=4,600,(IF(AP70<=6,800,(IF(AP70<=8,1000,1200))))) -> #DIV/0!
C80: =IF(D80<>"",COUNTA($D$10:D80),"") -> 62 | D80: Clean Room 20 | E80: 2.1 | F80: 1.8 | G80: 2.4 | H80: 2 | I80: 1 | J80: 1.75 | K80: 3 | L80: 0.1 | M80: 0 | N80: 24 | O80: 50 | P80: 45 | Q80: 85 | R80: 10K | S80: 80 | T80: 0 | U80: 100 | V80: =R80 -> 10K | W80: =S80 -> 80 | X80: =E80*F80*10.76 -> 40.6728 | Y80: =X80*G80*3.28 -> 320.17628 | Z80: =Y80*S80/60 -> 426.90171 | AA80: =Z80*L80 -> 42.690171 | AB80: =IF(N80="Amb",Z80,Z80*M80) -> 0 | AC80: =IF(ISNUMBER(N80), (AA80*0.075*60/2.20462)*BP80/7000, "Ambient") -> 0 | AD80: =IF(ISNUMBER(N80), CEILING(CF80/(0.68*BP80),25), "Ambient") -> #DIV/0! | AE80: =CEILING(MAX((Z80+AA80),AD80),25) -> #DIV/0! | AF80: =CEILING(IF(OR($R80="ISO 6",$R80="GRADE B",$R80="1K",$R80=1000),AE80*1/175,IF(OR($R80="ISO 5",$R80="GRADE A",$R80=100),AE80*1/100,IF(OR($R80="ISO 7",$R80="GRADE C",$R80="10K",$R80=10000),$AE80*1/250,IF(OR($R80="ISO 8",$R80="GRADE D",$R80="100K",$R80=100000),$AE80*1/250,IF(OR($R80="NC",$R80="20 Micron",$R80="5 Micron",$R80="N C"),$AE80*1/350,0))))),2) -> #DIV/0! | AG80: =IF(ISNUMBER(N80), CEILING(MAX(AI80,AJ80),0.5), "Ambient") -> #DIV/0! | AH80: C | AI80: =IF(ISNUMBER(N80), CEILING(CE80/12000,0.5), "Ambient") -> 0 | AJ80: =IF(ISNUMBER(N80),CEILING(AE80/(IF(AH80="C",400,300)),0.5), "Ambient") -> #DIV/0!
C81: =IF(D81<>"",COUNTA($D$10:D81),"") -> 63 | D81: Clean Room 21 | E81: 1.8 | F81: 1.9 | G81: 2.4 | H81: 2 | I81: 1 | J81: 1.75 | K81: 3 | L81: 0.1 | M81: 0 | N81: 24 | O81: 50 | P81: 45 | Q81: 85 | R81: 10K | S81: 80 | T81: 0 | U81: 100 | V81: =R81 -> 10K | W81: =S81 -> 80 | X81: =E81*F81*10.76 -> 36.7992 | Y81: =X81*G81*3.28 -> 289.6833 | Z81: =Y81*S81/60 -> 386.2444 | AA81: =Z81*L81 -> 38.62444 | AB81: =IF(N81="Amb",Z81,Z81*M81) -> 0 | AC81: =IF(ISNUMBER(N81), (AA81*0.075*60/2.20462)*BP81/7000, "Ambient") -> 0 | AD81: =IF(ISNUMBER(N81), CEILING(CF81/(0.68*BP81),25), "Ambient") -> #DIV/0! | AE81: =CEILING(MAX((Z81+AA81),AD81),25) -> #DIV/0! | AF81: =CEILING(IF(OR($R81="ISO 6",$R81="GRADE B",$R81="1K",$R81=1000),AE81*1/175,IF(OR($R81="ISO 5",$R81="GRADE A",$R81=100),AE81*1/100,IF(OR($R81="ISO 7",$R81="GRADE C",$R81="10K",$R81=10000),$AE81*1/250,IF(OR($R81="ISO 8",$R81="GRADE D",$R81="100K",$R81=100000),$AE81*1/250,IF(OR($R81="NC",$R81="20 Micron",$R81="5 Micron",$R81="N C"),$AE81*1/350,0))))),2) -> #DIV/0! | AG81: =IF(ISNUMBER(N81), CEILING(MAX(AI81,AJ81),0.5), "Ambient") -> #DIV/0! | AH81: C | AI81: =IF(ISNUMBER(N81), CEILING(CE81/12000,0.5), "Ambient") -> 0 | AJ81: =IF(ISNUMBER(N81),CEILING(AE81/(IF(AH81="C",400,300)),0.5), "Ambient") -> #DIV/0!
C82: =IF(D82<>"",COUNTA($D$10:D82),"") -> 64 | D82: Clean Room 22 | E82: 1.9 | F82: 2 | G82: 2.4 | H82: 2 | I82: 1 | J82: 1.75 | K82: 3 | L82: 0.1 | M82: 0 | N82: 24 | O82: 50 | P82: 45 | Q82: 85 | R82: 10K | S82: 80 | T82: 0 | U82: 100 | V82: =R82 -> 10K | W82: =S82 -> 80 | X82: =E82*F82*10.76 -> 40.888 | Y82: =X82*G82*3.28 -> 321.87034 | Z82: =Y82*S82/60 -> 429.16045 | AA82: =Z82*L82 -> 42.916045 | AB82: =IF(N82="Amb",Z82,Z82*M82) -> 0 | AC82: =IF(ISNUMBER(N82), (AA82*0.075*60/2.20462)*BP82/7000, "Ambient") -> 0 | AD82: =IF(ISNUMBER(N82), CEILING(CF82/(0.68*BP82),25), "Ambient") -> #DIV/0! | AE82: =CEILING(MAX((Z82+AA82),AD82),25) -> #DIV/0! | AF82: =CEILING(IF(OR($R82="ISO 6",$R82="GRADE B",$R82="1K",$R82=1000),AE82*1/175,IF(OR($R82="ISO 5",$R82="GRADE A",$R82=100),AE82*1/100,IF(OR($R82="ISO 7",$R82="GRADE C",$R82="10K",$R82=10000),$AE82*1/250,IF(OR($R82="ISO 8",$R82="GRADE D",$R82="100K",$R82=100000),$AE82*1/250,IF(OR($R82="NC",$R82="20 Micron",$R82="5 Micron",$R82="N C"),$AE82*1/350,0))))),2) -> #DIV/0! | AG82: =IF(ISNUMBER(N82), CEILING(MAX(AI82,AJ82),0.5), "Ambient") -> #DIV/0! | AH82: C | AI82: =IF(ISNUMBER(N82), CEILING(CE82/12000,0.5), "Ambient") -> 0 | AJ82: =IF(ISNUMBER(N82),CEILING(AE82/(IF(AH82="C",400,300)),0.5), "Ambient") -> #DIV/0!
C83: =IF(D83<>"",COUNTA($D$10:D83),"") -> 65 | D83: Clean Room 23 | E83: 2.3 | F83: 2.2 | G83: 2.4 | H83: 2 | I83: 1 | J83: 1.75 | K83: 3 | L83: 0.1 | M83: 0 | N83: 24 | O83: 50 | P83: 45 | Q83: 85 | R83: 10K | S83: 80 | T83: 0 | U83: 100 | V83: =R83 -> 10K | W83: =S83 -> 80 | X83: =E83*F83*10.76 -> 54.4456 | Y83: =X83*G83*3.28 -> 428.59576 | Z83: =Y83*S83/60 -> 571.46102 | AA83: =Z83*L83 -> 57.146102 | AB83: =IF(N83="Amb",Z83,Z83*M83) -> 0 | AC83: =IF(ISNUMBER(N83), (AA83*0.075*60/2.20462)*BP83/7000, "Ambient") -> 0 | AD83: =IF(ISNUMBER(N83), CEILING(CF83/(0.68*BP83),25), "Ambient") -> #DIV/0! | AE83: =CEILING(MAX((Z83+AA83),AD83),25) -> #DIV/0! | AF83: =CEILING(IF(OR($R83="ISO 6",$R83="GRADE B",$R83="1K",$R83=1000),AE83*1/175,IF(OR($R83="ISO 5",$R83="GRADE A",$R83=100),AE83*1/100,IF(OR($R83="ISO 7",$R83="GRADE C",$R83="10K",$R83=10000),$AE83*1/250,IF(OR($R83="ISO 8",$R83="GRADE D",$R83="100K",$R83=100000),$AE83*1/250,IF(OR($R83="NC",$R83="20 Micron",$R83="5 Micron",$R83="N C"),$AE83*1/350,0))))),2) -> #DIV/0! | AG83: =IF(ISNUMBER(N83), CEILING(MAX(AI83,AJ83),0.5), "Ambient") -> #DIV/0! | AH83: C | AI83: =IF(ISNUMBER(N83), CEILING(CE83/12000,0.5), "Ambient") -> 0 | AJ83: =IF(ISNUMBER(N83),CEILING(AE83/(IF(AH83="C",400,300)),0.5), "Ambient") -> #DIV/0!
C84: =IF(D84<>"",COUNTA($D$10:D84),"") -> 66 | D84: Clean Room 24 | E84: 2.2 | F84: 2.8 | G84: 2.4 | H84: 2 | I84: 1 | J84: 1.75 | K84: 3 | L84: 0.1 | M84: 0 | N84: 24 | O84: 50 | P84: 45 | Q84: 85 | R84: 10K | S84: 80 | T84: 0 | U84: 100 | V84: =R84 -> 10K | W84: =S84 -> 80 | X84: =E84*F84*10.76 -> 66.2816 | Y84: =X84*G84*3.28 -> 521.76876 | Z84: =Y84*S84/60 -> 695.69167 | AA84: =Z84*L84 -> 69.569167 | AB84: =IF(N84="Amb",Z84,Z84*M84) -> 0 | AC84: =IF(ISNUMBER(N84), (AA84*0.075*60/2.20462)*BP84/7000, "Ambient") -> 0 | AD84: =IF(ISNUMBER(N84), CEILING(CF84/(0.68*BP84),25), "Ambient") -> #DIV/0! | AE84: =CEILING(MAX((Z84+AA84),AD84),25) -> #DIV/0! | AF84: =CEILING(IF(OR($R84="ISO 6",$R84="GRADE B",$R84="1K",$R84=1000),AE84*1/175,IF(OR($R84="ISO 5",$R84="GRADE A",$R84=100),AE84*1/100,IF(OR($R84="ISO 7",$R84="GRADE C",$R84="10K",$R84=10000),$AE84*1/250,IF(OR($R84="ISO 8",$R84="GRADE D",$R84="100K",$R84=100000),$AE84*1/250,IF(OR($R84="NC",$R84="20 Micron",$R84="5 Micron",$R84="N C"),$AE84*1/350,0))))),2) -> #DIV/0! | AG84: =IF(ISNUMBER(N84), CEILING(MAX(AI84,AJ84),0.5), "Ambient") -> #DIV/0! | AH84: C | AI84: =IF(ISNUMBER(N84), CEILING(CE84/12000,0.5), "Ambient") -> 0 | AJ84: =IF(ISNUMBER(N84),CEILING(AE84/(IF(AH84="C",400,300)),0.5), "Ambient") -> #DIV/0!
C85: =IF(D85<>"",COUNTA($D$10:D85),"") -> 67 | D85: Clean Room 25 | E85: 2.8 | F85: 2.4 | G85: 2.4 | H85: 2 | I85: 1 | J85: 1.75 | K85: 3 | L85: 0.1 | M85: 0 | N85: 24 | O85: 50 | P85: 45 | Q85: 85 | R85: 10K | S85: 80 | T85: 0 | U85: 100 | V85: =R85 -> 10K | W85: =S85 -> 80 | X85: =E85*F85*10.76 -> 72.3072 | Y85: =X85*G85*3.28 -> 569.20228 | Z85: =Y85*S85/60 -> 758.93637 | AA85: =Z85*L85 -> 75.893637 | AB85: =IF(N85="Amb",Z85,Z85*M85) -> 0 | AC85: =IF(ISNUMBER(N85), (AA85*0.075*60/2.20462)*BP85/7000, "Ambient") -> 0 | AD85: =IF(ISNUMBER(N85), CEILING(CF85/(0.68*BP85),25), "Ambient") -> #DIV/0! | AE85: =CEILING(MAX((Z85+AA85),AD85),25) -> #DIV/0! | AF85: =CEILING(IF(OR($R85="ISO 6",$R85="GRADE B",$R85="1K",$R85=1000),AE85*1/175,IF(OR($R85="ISO 5",$R85="GRADE A",$R85=100),AE85*1/100,IF(OR($R85="ISO 7",$R85="GRADE C",$R85="10K",$R85=10000),$AE85*1/250,IF(OR($R85="ISO 8",$R85="GRADE D",$R85="100K",$R85=100000),$AE85*1/250,IF(OR($R85="NC",$R85="20 Micron",$R85="5 Micron",$R85="N C"),$AE85*1/350,0))))),2) -> #DIV/0! | AG85: =IF(ISNUMBER(N85), CEILING(MAX(AI85,AJ85),0.5), "Ambient") -> #DIV/0! | AH85: C | AI85: =IF(ISNUMBER(N85), CEILING(CE85/12000,0.5), "Ambient") -> 0 | AJ85: =IF(ISNUMBER(N85),CEILING(AE85/(IF(AH85="C",400,300)),0.5), "Ambient") -> #DIV/0!
C86: =IF(D86<>"",COUNTA($D$10:D86),"") | X86: =SUM(X70:X85) -> 1144.1108 | Y86: =SUM(Y70:Y85) -> 9006.4402 | Z86: =SUM(Z70:Z85) -> 12008.587 | AA86: =SUM(AA70:AA85) -> 1200.8587 | AB86: =SUM(AB70:AB85) -> 0 | AC86: =SUM(AC70:AC85) -> 0 | AD86: =SUM(AD70:AD85) -> #DIV/0! | AE86: =SUM(AE70:AE85) -> #DIV/0! | ... AG86: =SUM(AG70:AG85) -> #DIV/0! | AI86: =SUM(AI70:AI85) -> 0 | AJ86: =SUM(AJ70:AJ85) -> #DIV/0!
C87: =IF(D87<>"",COUNTA($D$10:D87),"")
C88: ="Zoning Area AHU - " & INT((ROW()-8)/20)+1 & " " &IF(AQ90>0,"Air-Conditioning System " & IF(AH90="D","(DX)",IF(AH90="C","(Chilled Water)","")),IF(AND(N90="Amb",AQ90=0),"Ventilation System","Refer")) -> #DIV/0! | AS88: Chilled Water Details | AW88: Hot Water/Steam Details
C89: =IF(D89<>"",COUNTA($D$10:D89),"") -> 68 | D89: Room Name | E89: Length in mtrs | F89: Width in mtrs | G89: Height in mtrs | H89: People in Nos | I89: Eqpt. Load in KW | J89: Lighting in W/Sft | K89: No.of Inf./Hr | L89: Fresh Air | M89: Exhaust | N89: T ˚C (Required inside) | O89: RH(in) +/- 5% | P89: Peak Max Temp.(Out) in ˚C | Q89: RH(Out) in +/- 5% | R89: Class | S89: ACPH | T89: Peak Min Temp.(Out) in ˚C | U89: RH(Out) +/- 5% | V89: Class | W89: ACPH | X89: Area | Y89: Volume | Z89: Room Cfm | AA89: FA | AB89: EA | AC89: Rem. Water vapour Kg/hr | AD89: Deh. Cfm | AE89: Res. Cfm | AF89: Room Terminal Supply Module in Sft | AG89: Res. Cooling Load in TR | AH89: Chilled Water (C) OR DX (D) | AI89: Room AC load in TR | AJ89: Cfm AC load in TR | AK89: AHU Cfm | AL89: AHU Size | AM89: Static Pressure | AN89: Blower Model BDB | AO89: Motor Selected in Hp | AP89: No. of Rows of Cooling Coil | AQ89: AHU Cooling Load in TR | AR89: No. Of Stages of Filtr. | AS89: Chilled water in GPM | AT89: Chilled water in L/s | AU89: Flow Velocity in m/s | AV89: Pipe Size in mm | AW89: Hot Water/Steam in GPM | AX89: Hot water/Steam in L/s | AY89: Flow Velocity | AZ89: Pipe Size
C90: =IF(D90<>"",COUNTA($D$10:D90),"") -> 69 | D90: Clean Room 10 | E90: 3 | F90: 3 | G90: 2.4 | H90: 1 | I90: 2 | J90: 1.75 | K90: 3 | L90: 0.1 | M90: 0 | N90: 24 | O90: 50 | P90: 45 | Q90: 85 | R90: NC | S90: 20 | T90: 0 | U90: 100 | V90: =R90 -> NC | W90: =S90 -> 20 | X90: =E90*F90*10.76 -> 96.84 | Y90: =X90*G90*3.28 -> 762.32448 | Z90: =Y90*S90/60 -> 254.10816 | AA90: =Z90*L90 -> 25.410816 | AB90: =IF(N90="Amb",Z90,Z90*M90) -> 0 | AC90: =IF(ISNUMBER(N90), (AA90*0.075*60/2.20462)*BP90/7000, "Ambient") -> 0 | AD90: =IF(ISNUMBER(N90), CEILING(CF90/(0.68*BP90),25), "Ambient") -> #DIV/0! | AE90: =CEILING(MAX((Z90+AA90),AD90),25) -> #DIV/0! | AF90: =CEILING(IF(OR($R90="ISO 6",$R90="GRADE B",$R90="1K",$R90=1000),AE90*1/175,IF(OR($R90="ISO 5",$R90="GRADE A",$R90=100),AE90*1/100,IF(OR($R90="ISO 7",$R90="GRADE C",$R90="10K",$R90=10000),$AE90*1/250,IF(OR($R90="ISO 8",$R90="GRADE D",$R90="100K",$R90=100000),$AE90*1/250,IF(OR($R90="NC",$R90="20 Micron",$R90="5 Micron",$R90="N C"),$AE90*1/350,0))))),2) -> #DIV/0! | AG90: =IF(ISNUMBER(N90), CEILING(MAX(AI90,AJ90),0.5), "Ambient") -> #DIV/0! | AH90: C | AI90: =IF(ISNUMBER(N90), CEILING(CE90/12000,0.5), "Ambient") -> 0 | AJ90: =IF(ISNUMBER(N90),CEILING(AE90/(IF(AH90="C",400,300)),0.5), "Ambient") -> #DIV/0! | AK90: =CEILING(SUM(AE90:AE105),250) -> #DIV/0! | AL90: W | AM90: 150 | AN90: =IF(AK90<=1300,200,IF(AK90<=1600,225,IF(AK90<=2100,250,IF(AK90<=2700,280,IF(AK90<=3450,315,IF(AK90<=4250,355,IF(AK90<=5250,400,IF(AK90<=6750,450,IF(AK90<=8500,500,IF(AK90<=10750,560,IF(AK90<=13500,630,IF(AK90<=17000,710,IF(AK90<=21500,800,IF(AK90<=27000,900,IF(AK90<=34000,1000,IF(AK90<=43000,1120,IF(AK90<=49000,1200,IF(AK90<=68000,1450,"Refer")))))))))))))))))) -> #DIV/0! | AO90: =IF(AK90*AM90/(6356*0.7*0.9*1.1*25.4)<=1,1,IF(AK90*AM90/(6356*0.7*0.9*1.1*25.4)<=1.5,1.5,IF(AK90*AM90/(6356*0.7*0.9*1.1*25.4)<=2,2,IF(AK90*AM90/(6356*0.7*0.9*1.1*25.4)<=3,3,IF(AK90*AM90/(6356*0.7*0.9*1.1*25.4)<=5,5,IF(AK90*AM90/(6356*0.7*0.9*1.1*25.4)<=7.5,7.5,IF(AK90*AM90/(6356*0.7*0.9*1.1*25.4)<=10,10,IF(AK90*AM90/(6356*0.7*0.9*1.1*25.4)<=12.5,12.5,IF(AK90*AM90/(6356*0.7*0.9*1.1*25.4)<=15,15,IF(AK90*AM90/(6356*0.7*0.9*1.1*25.4)<=20,20,IF(AK90*AM90/(6356*0.7*0.9*1.1*25.4)<=25,25,IF(AK90*AM90/(6356*0.7*0.9*1.1*25.4)<=30,30,IF(AK90*AM90/(6356*0.7*0.9*1.1*25.4)<=40,40,IF(AK90*AM90/(6356*0.7*0.9*1.1*25.4)<=50,50,IF(AK90*AM90/(6356*0.7*0.9*1.1*25.4)<=60,60,IF(AK90*AM90/(6356*0.7*0.9*1.1*25.4)<=75,75,"Refer")))))))))))))))) -> #DIV/0! | AP90: =IF(AND(AQ90=0, N90="Amb"), "Amb",IF((AL91-250)*(AL93-150)*10.76/(1000*1000) >= MAX(AI106,AJ106), 4,IF((AL91-250)*(AL93-150)*10.76*1.5/(1000*1000) >= MAX(AI106,AJ106), 6,IF((AL91-250)*(AL93-150)*10.76*2/(1000*1000) >= MAX(AI106,AJ106), 8, 0)) ) ) -> #DIV/0! | AQ90: =AG106 -> #DIV/0! | AR90: =_xlfn.SWITCH(TRIM(UPPER(R90)),"ISO 9", 3,"ISO 8", 4,"Grade D", 4,"Class 100,000", 4,"Class 100K", 4,"ISO 7", 3,"Grade C", 3,"Class 10,000", 3,"Class 10K", 3,"ISO 6", 3,"Class 1,000", 3,"Class 1K", 3,"ISO 5", 4,"Grade A", 4,"Grade B", 4,"Class 100", 4,"ISO 4", 3,"ISO 3", 4,"ISO 2", 4,"ISO 1", 4,"NCV20",1,"NCV-10",2,"NCV-5",3,"NCAC-10",1,"NCAC-5",2,"NCAC-1",3,3) -> 3 | AS90: =MAX(AI106,AJ106)*24/6 -> #DIV/0! | AT90: =AS90*0.06309 -> #DIV/0! | AU90: 2 | AV90: =SQRT((4*AS90*0.00006309)/(3.14*AU90))*1000 -> #DIV/0!
C91: =IF(D91<>"",COUNTA($D$10:D91),"") -> 70 | D91: Clean Room 11 | E91: 1.8 | F91: 2.2 | G91: 2.4 | H91: 2 | I91: 1 | J91: 1.75 | K91: 3 | L91: 0.1 | M91: 0 | N91: 24 | O91: 50 | P91: 45 | Q91: 85 | R91: NC | S91: 20 | T91: 0 | U91: 100 | V91: =R91 -> NC | W91: =S91 -> 20 | X91: =E91*F91*10.76 -> 42.6096 | Y91: =X91*G91*3.28 -> 335.42277 | Z91: =Y91*S91/60 -> 111.80759 | AA91: =Z91*L91 -> 11.180759 | AB91: =IF(N91="Amb",Z91,Z91*M91) -> 0 | AC91: =IF(ISNUMBER(N91), (AA91*0.075*60/2.20462)*BP91/7000, "Ambient") -> 0 | AD91: =IF(ISNUMBER(N91), CEILING(CF91/(0.68*BP91),25), "Ambient") -> #DIV/0! | AE91: =CEILING(MAX((Z91+AA91),AD91),25) -> #DIV/0! | AF91: =CEILING(IF(OR($R91="ISO 6",$R91="GRADE B",$R91="1K",$R91=1000),AE91*1/175,IF(OR($R91="ISO 5",$R91="GRADE A",$R91=100),AE91*1/100,IF(OR($R91="ISO 7",$R91="GRADE C",$R91="10K",$R91=10000),$AE91*1/250,IF(OR($R91="ISO 8",$R91="GRADE D",$R91="100K",$R91=100000),$AE91*1/250,IF(OR($R91="NC",$R91="20 Micron",$R91="5 Micron",$R91="N C"),$AE91*1/350,0))))),2) -> #DIV/0! | AG91: =IF(ISNUMBER(N91), CEILING(MAX(AI91,AJ91),0.5), "Ambient") -> #DIV/0! | AH91: C | AI91: =IF(ISNUMBER(N91), CEILING(CE91/12000,0.5), "Ambient") -> 0 | AJ91: =IF(ISNUMBER(N91),CEILING(AE91/(IF(AH91="C",400,300)),0.5), "Ambient") -> #DIV/0! | AL91: =IF(AK90<=2000,950,(IF(AK90<=3000,1150,(IF(AK90<=8000,1550,(IF(AK90<=10000,1750,(IF(AK90<=18000,2050,(IF(AK90<=32000,2900,(IF(AK90<=40000,3600,4000))))))))))))) -> #DIV/0!
C92: =IF(D92<>"",COUNTA($D$10:D92),"") -> 71 | D92: Clean Room 12 | E92: 1.5 | F92: 2.8 | G92: 2.4 | H92: 2 | I92: 3 | J92: 1.75 | K92: 3 | L92: 0.1 | M92: 0 | N92: 24 | O92: 50 | P92: 45 | Q92: 85 | R92: NC | S92: 20 | T92: 0 | U92: 100 | V92: =R92 -> NC | W92: =S92 -> 20 | X92: =E92*F92*10.76 -> 45.192 | Y92: =X92*G92*3.28 -> 355.75142 | Z92: =Y92*S92/60 -> 118.58381 | AA92: =Z92*L92 -> 11.858381 | AB92: =IF(N92="Amb",Z92,Z92*M92) -> 0 | AC92: =IF(ISNUMBER(N92), (AA92*0.075*60/2.20462)*BP92/7000, "Ambient") -> 0 | AD92: =IF(ISNUMBER(N92), CEILING(CF92/(0.68*BP92),25), "Ambient") -> #DIV/0! | AE92: =CEILING(MAX((Z92+AA92),AD92),25) -> #DIV/0! | AF92: =CEILING(IF(OR($R92="ISO 6",$R92="GRADE B",$R92="1K",$R92=1000),AE92*1/175,IF(OR($R92="ISO 5",$R92="GRADE A",$R92=100),AE92*1/100,IF(OR($R92="ISO 7",$R92="GRADE C",$R92="10K",$R92=10000),$AE92*1/250,IF(OR($R92="ISO 8",$R92="GRADE D",$R92="100K",$R92=100000),$AE92*1/250,IF(OR($R92="NC",$R92="20 Micron",$R92="5 Micron",$R92="N C"),$AE92*1/350,0))))),2) -> #DIV/0! | AG92: =IF(ISNUMBER(N92), CEILING(MAX(AI92,AJ92),0.5), "Ambient") -> #DIV/0! | AH92: C | AI92: =IF(ISNUMBER(N92), CEILING(CE92/12000,0.5), "Ambient") -> 0 | AJ92: =IF(ISNUMBER(N92),CEILING(AE92/(IF(AH92="C",400,300)),0.5), "Ambient") -> #DIV/0! | AL92: H
C93: =IF(D93<>"",COUNTA($D$10:D93),"") -> 72 | D93: Clean Room 13 | E93: 2.1 | F93: 3.5 | G93: 2.4 | H93: 0 | I93: 1 | J93: 1.75 | K93: 3 | L93: 0.1 | M93: 0 | N93: 24 | O93: 50 | P93: 45 | Q93: 85 | R93: NC | S93: 20 | T93: 0 | U93: 100 | V93: =R93 -> NC | W93: =S93 -> 20 | X93: =E93*F93*10.76 -> 79.086 | Y93: =X93*G93*3.28 -> 622.56499 | Z93: =Y93*S93/60 -> 207.52166 | AA93: =Z93*L93 -> 20.752166 | AB93: =IF(N93="Amb",Z93,Z93*M93) -> 0 | AC93: =IF(ISNUMBER(N93), (AA93*0.075*60/2.20462)*BP93/7000, "Ambient") -> 0 | AD93: =IF(ISNUMBER(N93), CEILING(CF93/(0.68*BP93),25), "Ambient") -> #DIV/0! | AE93: =CEILING(MAX((Z93+AA93),AD93),25) -> #DIV/0! | AF93: =CEILING(IF(OR($R93="ISO 6",$R93="GRADE B",$R93="1K",$R93=1000),AE93*1/175,IF(OR($R93="ISO 5",$R93="GRADE A",$R93=100),AE93*1/100,IF(OR($R93="ISO 7",$R93="GRADE C",$R93="10K",$R93=10000),$AE93*1/250,IF(OR($R93="ISO 8",$R93="GRADE D",$R93="100K",$R93=100000),$AE93*1/250,IF(OR($R93="NC",$R93="20 Micron",$R93="5 Micron",$R93="N C"),$AE93*1/350,0))))),2) -> #DIV/0! | AG93: =IF(ISNUMBER(N93), CEILING(MAX(AI93,AJ93),0.5), "Ambient") -> #DIV/0! | AH93: C | AI93: =IF(ISNUMBER(N93), CEILING(CE93/12000,0.5), "Ambient") -> 0 | AJ93: =IF(ISNUMBER(N93),CEILING(AE93/(IF(AH93="C",400,300)),0.5), "Ambient") -> #DIV/0! | AL93: =IF(AK90<=2000,950,(IF(AK90<=4000,1100,(IF(AK90<=6000,1250,(IF(AK90<=10000,1550,(IF(AK90<=15000,1750,(IF(AK90<=24000,2050,(IF(AK90<=40000,2900,3600))))))))))))) -> #DIV/0!
C94: =IF(D94<>"",COUNTA($D$10:D94),"") -> 73 | D94: Clean Room 14 | E94: 2.7 | F94: 4 | G94: 2.4 | H94: 2 | I94: 1 | J94: 1.75 | K94: 3 | L94: 0.1 | M94: 0 | N94: 24 | O94: 50 | P94: 45 | Q94: 85 | R94: NC | S94: 20 | T94: 0 | U94: 100 | V94: =R94 -> NC | W94: =S94 -> 20 | X94: =E94*F94*10.76 -> 116.208 | Y94: =X94*G94*3.28 -> 914.78938 | Z94: =Y94*S94/60 -> 304.92979 | AA94: =Z94*L94 -> 30.492979 | AB94: =IF(N94="Amb",Z94,Z94*M94) -> 0 | AC94: =IF(ISNUMBER(N94), (AA94*0.075*60/2.20462)*BP94/7000, "Ambient") -> 0 | AD94: =IF(ISNUMBER(N94), CEILING(CF94/(0.68*BP94),25), "Ambient") -> #DIV/0! | AE94: =CEILING(MAX((Z94+AA94),AD94),25) -> #DIV/0! | AF94: =CEILING(IF(OR($R94="ISO 6",$R94="GRADE B",$R94="1K",$R94=1000),AE94*1/175,IF(OR($R94="ISO 5",$R94="GRADE A",$R94=100),AE94*1/100,IF(OR($R94="ISO 7",$R94="GRADE C",$R94="10K",$R94=10000),$AE94*1/250,IF(OR($R94="ISO 8",$R94="GRADE D",$R94="100K",$R94=100000),$AE94*1/250,IF(OR($R94="NC",$R94="20 Micron",$R94="5 Micron",$R94="N C"),$AE94*1/350,0))))),2) -> #DIV/0! | AG94: =IF(ISNUMBER(N94), CEILING(MAX(AI94,AJ94),0.5), "Ambient") -> #DIV/0! | AH94: C | AI94: =IF(ISNUMBER(N94), CEILING(CE94/12000,0.5), "Ambient") -> 0 | AJ94: =IF(ISNUMBER(N94),CEILING(AE94/(IF(AH94="C",400,300)),0.5), "Ambient") -> #DIV/0! | AL94: L
C95: =IF(D95<>"",COUNTA($D$10:D95),"") -> 74 | D95: Clean Room 15 | E95: 3.8 | F95: 4.2 | G95: 2.4 | H95: 3 | I95: 3 | J95: 1.75 | K95: 3 | L95: 0.1 | M95: 0 | N95: 24 | O95: 50 | P95: 45 | Q95: 85 | R95: NC | S95: 20 | T95: 0 | U95: 100 | V95: =R95 -> NC | W95: =S95 -> 20 | X95: =E95*F95*10.76 -> 171.7296 | Y95: =X95*G95*3.28 -> 1351.8554 | Z95: =Y95*S95/60 -> 450.61847 | AA95: =Z95*L95 -> 45.061847 | AB95: =IF(N95="Amb",Z95,Z95*M95) -> 0 | AC95: =IF(ISNUMBER(N95), (AA95*0.075*60/2.20462)*BP95/7000, "Ambient") -> 0 | AD95: =IF(ISNUMBER(N95), CEILING(CF95/(0.68*BP95),25), "Ambient") -> #DIV/0! | AE95: =CEILING(MAX((Z95+AA95),AD95),25) -> #DIV/0! | AF95: =CEILING(IF(OR($R95="ISO 6",$R95="GRADE B",$R95="1K",$R95=1000),AE95*1/175,IF(OR($R95="ISO 5",$R95="GRADE A",$R95=100),AE95*1/100,IF(OR($R95="ISO 7",$R95="GRADE C",$R95="10K",$R95=10000),$AE95*1/250,IF(OR($R95="ISO 8",$R95="GRADE D",$R95="100K",$R95=100000),$AE95*1/250,IF(OR($R95="NC",$R95="20 Micron",$R95="5 Micron",$R95="N C"),$AE95*1/350,0))))),2) -> #DIV/0! | AG95: =IF(ISNUMBER(N95), CEILING(MAX(AI95,AJ95),0.5), "Ambient") -> #DIV/0! | AH95: C | AI95: =IF(ISNUMBER(N95), CEILING(CE95/12000,0.5), "Ambient") -> 0 | AJ95: =IF(ISNUMBER(N95),CEILING(AE95/(IF(AH95="C",400,300)),0.5), "Ambient") -> #DIV/0! | AL95: =IF(AL99<4000,AL99,AL99+400) -> #DIV/0!
C96: =IF(D96<>"",COUNTA($D$10:D96),"") -> 75 | D96: Clean Room 16 | E96: 3.1 | F96: 2.6 | G96: 2.4 | H96: 2 | I96: 1 | J96: 1.75 | K96: 3 | L96: 0.1 | M96: 0 | N96: 24 | O96: 50 | P96: 45 | Q96: 85 | R96: NC | S96: 20 | T96: 0 | U96: 100 | V96: =R96 -> NC | W96: =S96 -> 20 | X96: =E96*F96*10.76 -> 86.7256 | Y96: =X96*G96*3.28 -> 682.70392 | Z96: =Y96*S96/60 -> 227.56797 | AA96: =Z96*L96 -> 22.756797 | AB96: =IF(N96="Amb",Z96,Z96*M96) -> 0 | AC96: =IF(ISNUMBER(N96), (AA96*0.075*60/2.20462)*BP96/7000, "Ambient") -> 0 | AD96: =IF(ISNUMBER(N96), CEILING(CF96/(0.68*BP96),25), "Ambient") -> #DIV/0! | AE96: =CEILING(MAX((Z96+AA96),AD96),25) -> #DIV/0! | AF96: =CEILING(IF(OR($R96="ISO 6",$R96="GRADE B",$R96="1K",$R96=1000),AE96*1/175,IF(OR($R96="ISO 5",$R96="GRADE A",$R96=100),AE96*1/100,IF(OR($R96="ISO 7",$R96="GRADE C",$R96="10K",$R96=10000),$AE96*1/250,IF(OR($R96="ISO 8",$R96="GRADE D",$R96="100K",$R96=100000),$AE96*1/250,IF(OR($R96="NC",$R96="20 Micron",$R96="5 Micron",$R96="N C"),$AE96*1/350,0))))),2) -> #DIV/0! | AG96: =IF(ISNUMBER(N96), CEILING(MAX(AI96,AJ96),0.5), "Ambient") -> #DIV/0! | AH96: C | AI96: =IF(ISNUMBER(N96), CEILING(CE96/12000,0.5), "Ambient") -> 0 | AJ96: =IF(ISNUMBER(N96),CEILING(AE96/(IF(AH96="C",400,300)),0.5), "Ambient") -> #DIV/0!
C97: =IF(D97<>"",COUNTA($D$10:D97),"") -> 76 | D97: Clean Room 17 | E97: 1.9 | F97: 2.4 | G97: 2.4 | H97: 3 | I97: 2 | J97: 1.75 | K97: 3 | L97: 0.1 | M97: 0 | N97: 24 | O97: 50 | P97: 45 | Q97: 85 | R97: NC | S97: 20 | T97: 0 | U97: 100 | V97: =R97 -> NC | W97: =S97 -> 20 | X97: =E97*F97*10.76 -> 49.0656 | Y97: =X97*G97*3.28 -> 386.2444 | Z97: =Y97*S97/60 -> 128.74813 | AA97: =Z97*L97 -> 12.874813 | AB97: =IF(N97="Amb",Z97,Z97*M97) -> 0 | AC97: =IF(ISNUMBER(N97), (AA97*0.075*60/2.20462)*BP97/7000, "Ambient") -> 0 | AD97: =IF(ISNUMBER(N97), CEILING(CF97/(0.68*BP97),25), "Ambient") -> #DIV/0! | AE97: =CEILING(MAX((Z97+AA97),AD97),25) -> #DIV/0! | AF97: =CEILING(IF(OR($R97="ISO 6",$R97="GRADE B",$R97="1K",$R97=1000),AE97*1/175,IF(OR($R97="ISO 5",$R97="GRADE A",$R97=100),AE97*1/100,IF(OR($R97="ISO 7",$R97="GRADE C",$R97="10K",$R97=10000),$AE97*1/250,IF(OR($R97="ISO 8",$R97="GRADE D",$R97="100K",$R97=100000),$AE97*1/250,IF(OR($R97="NC",$R97="20 Micron",$R97="5 Micron",$R97="N C"),$AE97*1/350,0))))),2) -> #DIV/0! | AG97: =IF(ISNUMBER(N97), CEILING(MAX(AI97,AJ97),0.5), "Ambient") -> #DIV/0! | AH97: C | AI97: =IF(ISNUMBER(N97), CEILING(CE97/12000,0.5), "Ambient") -> 0 | AJ97: =IF(ISNUMBER(N97),CEILING(AE97/(IF(AH97="C",400,300)),0.5), "Ambient") -> #DIV/0!
C98: =IF(D98<>"",COUNTA($D$10:D98),"") -> 77 | D98: Clean Room 18 | E98: 3 | F98: 2.9 | G98: 2.4 | H98: 2 | I98: 1 | J98: 1.75 | K98: 3 | L98: 0.1 | M98: 0 | N98: 24 | O98: 50 | P98: 45 | Q98: 85 | R98: NC | S98: 20 | T98: 0 | U98: 100 | V98: =R98 -> NC | W98: =S98 -> 20 | X98: =E98*F98*10.76 -> 93.612 | Y98: =X98*G98*3.28 -> 736.91366 | Z98: =Y98*S98/60 -> 245.63789 | AA98: =Z98*L98 -> 24.563789 | AB98: =IF(N98="Amb",Z98,Z98*M98) -> 0 | AC98: =IF(ISNUMBER(N98), (AA98*0.075*60/2.20462)*BP98/7000, "Ambient") -> 0 | AD98: =IF(ISNUMBER(N98), CEILING(CF98/(0.68*BP98),25), "Ambient") -> #DIV/0! | AE98: =CEILING(MAX((Z98+AA98),AD98),25) -> #DIV/0! | AF98: =CEILING(IF(OR($R98="ISO 6",$R98="GRADE B",$R98="1K",$R98=1000),AE98*1/175,IF(OR($R98="ISO 5",$R98="GRADE A",$R98=100),AE98*1/100,IF(OR($R98="ISO 7",$R98="GRADE C",$R98="10K",$R98=10000),$AE98*1/250,IF(OR($R98="ISO 8",$R98="GRADE D",$R98="100K",$R98=100000),$AE98*1/250,IF(OR($R98="NC",$R98="20 Micron",$R98="5 Micron",$R98="N C"),$AE98*1/350,0))))),2) -> #DIV/0! | AG98: =IF(ISNUMBER(N98), CEILING(MAX(AI98,AJ98),0.5), "Ambient") -> #DIV/0! | AH98: C | AI98: =IF(ISNUMBER(N98), CEILING(CE98/12000,0.5), "Ambient") -> 0 | AJ98: =IF(ISNUMBER(N98),CEILING(AE98/(IF(AH98="C",400,300)),0.5), "Ambient") -> #DIV/0!
C99: =IF(D99<>"",COUNTA($D$10:D99),"") -> 78 | D99: Clean Room 19 | E99: 2.4 | F99: 2 | G99: 2.4 | H99: 2 | I99: 1 | J99: 1.75 | K99: 3 | L99: 0.1 | M99: 0 | N99: 24 | O99: 50 | P99: 45 | Q99: 85 | R99: NC | S99: 20 | T99: 0 | U99: 100 | V99: =R99 -> NC | W99: =S99 -> 20 | X99: =E99*F99*10.76 -> 51.648 | Y99: =X99*G99*3.28 -> 406.57306 | Z99: =Y99*S99/60 -> 135.52435 | AA99: =Z99*L99 -> 13.552435 | AB99: =IF(N99="Amb",Z99,Z99*M99) -> 0 | AC99: =IF(ISNUMBER(N99), (AA99*0.075*60/2.20462)*BP99/7000, "Ambient") -> 0 | AD99: =IF(ISNUMBER(N99), CEILING(CF99/(0.68*BP99),25), "Ambient") -> #DIV/0! | AE99: =CEILING(MAX((Z99+AA99),AD99),25) -> #DIV/0! | AF99: =CEILING(IF(OR($R99="ISO 6",$R99="GRADE B",$R99="1K",$R99=1000),AE99*1/175,IF(OR($R99="ISO 5",$R99="GRADE A",$R99=100),AE99*1/100,IF(OR($R99="ISO 7",$R99="GRADE C",$R99="10K",$R99=10000),$AE99*1/250,IF(OR($R99="ISO 8",$R99="GRADE D",$R99="100K",$R99=100000),$AE99*1/250,IF(OR($R99="NC",$R99="20 Micron",$R99="5 Micron",$R99="N C"),$AE99*1/350,0))))),2) -> #DIV/0! | AG99: =IF(ISNUMBER(N99), CEILING(MAX(AI99,AJ99),0.5), "Ambient") -> #DIV/0! | AH99: C | AI99: =IF(ISNUMBER(N99), CEILING(CE99/12000,0.5), "Ambient") -> 0 | AJ99: =IF(ISNUMBER(N99),CEILING(AE99/(IF(AH99="C",400,300)),0.5), "Ambient") -> #DIV/0! | AL99: =IF(AN90<=315,1600,(IF(AN90=355,1650,(IF(AN90=400,1650,(IF(AN90=450,1700,(IF(AN90=500,1700,(IF(AN90=560,1800,(IF(AN90=630,2000,(IF(AN90=710,2200,2500)))))))))))))))+IF(AR90=2,1800,(IF(AR90=3,2300,(IF(AR90=4,3300,0)))))+IF(AP90<=4,600,(IF(AP90<=6,800,(IF(AP90<=8,1000,1200))))) -> #DIV/0!
C100: =IF(D100<>"",COUNTA($D$10:D100),"") -> 79 | D100: Clean Room 20 | E100: 2.1 | F100: 1.8 | G100: 2.4 | H100: 2 | I100: 1 | J100: 1.75 | K100: 3 | L100: 0.1 | M100: 0 | N100: 24 | O100: 50 | P100: 45 | Q100: 85 | R100: NC | S100: 20 | T100: 0 | U100: 100 | V100: =R100 -> NC | W100: =S100 -> 20 | X100: =E100*F100*10.76 -> 40.6728 | Y100: =X100*G100*3.28 -> 320.17628 | Z100: =Y100*S100/60 -> 106.72543 | AA100: =Z100*L100 -> 10.672543 | AB100: =IF(N100="Amb",Z100,Z100*M100) -> 0 | AC100: =IF(ISNUMBER(N100), (AA100*0.075*60/2.20462)*BP100/7000, "Ambient") -> 0 | AD100: =IF(ISNUMBER(N100), CEILING(CF100/(0.68*BP100),25), "Ambient") -> #DIV/0! | AE100: =CEILING(MAX((Z100+AA100),AD100),25) -> #DIV/0! | AF100: =CEILING(IF(OR($R100="ISO 6",$R100="GRADE B",$R100="1K",$R100=1000),AE100*1/175,IF(OR($R100="ISO 5",$R100="GRADE A",$R100=100),AE100*1/100,IF(OR($R100="ISO 7",$R100="GRADE C",$R100="10K",$R100=10000),$AE100*1/250,IF(OR($R100="ISO 8",$R100="GRADE D",$R100="100K",$R100=100000),$AE100*1/250,IF(OR($R100="NC",$R100="20 Micron",$R100="5 Micron",$R100="N C"),$AE100*1/350,0))))),2) -> #DIV/0! | AG100: =IF(ISNUMBER(N100), CEILING(MAX(AI100,AJ100),0.5), "Ambient") -> #DIV/0! | AH100: C | AI100: =IF(ISNUMBER(N100), CEILING(CE100/12000,0.5), "Ambient") -> 0 | AJ100: =IF(ISNUMBER(N100),CEILING(AE100/(IF(AH100="C",400,300)),0.5), "Ambient") -> #DIV/0!
C101: =IF(D101<>"",COUNTA($D$10:D101),"") -> 80 | D101: Clean Room 21 | E101: 1.8 | F101: 1.9 | G101: 2.4 | H101: 2 | I101: 1 | J101: 1.75 | K101: 3 | L101: 0.1 | M101: 0 | N101: 24 | O101: 50 | P101: 45 | Q101: 85 | R101: NC | S101: 20 | T101: 0 | U101: 100 | V101: =R101 -> NC | W101: =S101 -> 20 | X101: =E101*F101*10.76 -> 36.7992 | Y101: =X101*G101*3.28 -> 289.6833 | Z101: =Y101*S101/60 -> 96.561101 | AA101: =Z101*L101 -> 9.6561101 | AB101: =IF(N101="Amb",Z101,Z101*M101) -> 0 | AC101: =IF(ISNUMBER(N101), (AA101*0.075*60/2.20462)*BP101/7000, "Ambient") -> 0 | AD101: =IF(ISNUMBER(N101), CEILING(CF101/(0.68*BP101),25), "Ambient") -> #DIV/0! | AE101: =CEILING(MAX((Z101+AA101),AD101),25) -> #DIV/0! | AF101: =CEILING(IF(OR($R101="ISO 6",$R101="GRADE B",$R101="1K",$R101=1000),AE101*1/175,IF(OR($R101="ISO 5",$R101="GRADE A",$R101=100),AE101*1/100,IF(OR($R101="ISO 7",$R101="GRADE C",$R101="10K",$R101=10000),$AE101*1/250,IF(OR($R101="ISO 8",$R101="GRADE D",$R101="100K",$R101=100000),$AE101*1/250,IF(OR($R101="NC",$R101="20 Micron",$R101="5 Micron",$R101="N C"),$AE101*1/350,0))))),2) -> #DIV/0! | AG101: =IF(ISNUMBER(N101), CEILING(MAX(AI101,AJ101),0.5), "Ambient") -> #DIV/0! | AH101: C | AI101: =IF(ISNUMBER(N101), CEILING(CE101/12000,0.5), "Ambient") -> 0 | AJ101: =IF(ISNUMBER(N101),CEILING(AE101/(IF(AH101="C",400,300)),0.5), "Ambient") -> #DIV/0!
C102: =IF(D102<>"",COUNTA($D$10:D102),"") -> 81 | D102: Clean Room 22 | E102: 1.9 | F102: 2 | G102: 2.4 | H102: 2 | I102: 1 | J102: 1.75 | K102: 3 | L102: 0.1 | M102: 0 | N102: 24 | O102: 50 | P102: 45 | Q102: 85 | R102: NC | S102: 20 | T102: 0 | U102: 100 | V102: =R102 -> NC | W102: =S102 -> 20 | X102: =E102*F102*10.76 -> 40.888 | Y102: =X102*G102*3.28 -> 321.87034 | Z102: =Y102*S102/60 -> 107.29011 | AA102: =Z102*L102 -> 10.729011 | AB102: =IF(N102="Amb",Z102,Z102*M102) -> 0 | AC102: =IF(ISNUMBER(N102), (AA102*0.075*60/2.20462)*BP102/7000, "Ambient") -> 0 | AD102: =IF(ISNUMBER(N102), CEILING(CF102/(0.68*BP102),25), "Ambient") -> #DIV/0! | AE102: =CEILING(MAX((Z102+AA102),AD102),25) -> #DIV/0! | AF102: =CEILING(IF(OR($R102="ISO 6",$R102="GRADE B",$R102="1K",$R102=1000),AE102*1/175,IF(OR($R102="ISO 5",$R102="GRADE A",$R102=100),AE102*1/100,IF(OR($R102="ISO 7",$R102="GRADE C",$R102="10K",$R102=10000),$AE102*1/250,IF(OR($R102="ISO 8",$R102="GRADE D",$R102="100K",$R102=100000),$AE102*1/250,IF(OR($R102="NC",$R102="20 Micron",$R102="5 Micron",$R102="N C"),$AE102*1/350,0))))),2) -> #DIV/0! | AG102: =IF(ISNUMBER(N102), CEILING(MAX(AI102,AJ102),0.5), "Ambient") -> #DIV/0! | AH102: C | AI102: =IF(ISNUMBER(N102), CEILING(CE102/12000,0.5), "Ambient") -> 0 | AJ102: =IF(ISNUMBER(N102),CEILING(AE102/(IF(AH102="C",400,300)),0.5), "Ambient") -> #DIV/0!
C103: =IF(D103<>"",COUNTA($D$10:D103),"") -> 82 | D103: Clean Room 23 | E103: 2.3 | F103: 2.2 | G103: 2.4 | H103: 2 | I103: 1 | J103: 1.75 | K103: 3 | L103: 0.1 | M103: 0 | N103: 24 | O103: 50 | P103: 45 | Q103: 85 | R103: NC | S103: 20 | T103: 0 | U103: 100 | V103: =R103 -> NC | W103: =S103 -> 20 | X103: =E103*F103*10.76 -> 54.4456 | Y103: =X103*G103*3.28 -> 428.59576 | Z103: =Y103*S103/60 -> 142.86525 | AA103: =Z103*L103 -> 14.286525 | AB103: =IF(N103="Amb",Z103,Z103*M103) -> 0 | AC103: =IF(ISNUMBER(N103), (AA103*0.075*60/2.20462)*BP103/7000, "Ambient") -> 0 | AD103: =IF(ISNUMBER(N103), CEILING(CF103/(0.68*BP103),25), "Ambient") -> #DIV/0! | AE103: =CEILING(MAX((Z103+AA103),AD103),25) -> #DIV/0! | AF103: =CEILING(IF(OR($R103="ISO 6",$R103="GRADE B",$R103="1K",$R103=1000),AE103*1/175,IF(OR($R103="ISO 5",$R103="GRADE A",$R103=100),AE103*1/100,IF(OR($R103="ISO 7",$R103="GRADE C",$R103="10K",$R103=10000),$AE103*1/250,IF(OR($R103="ISO 8",$R103="GRADE D",$R103="100K",$R103=100000),$AE103*1/250,IF(OR($R103="NC",$R103="20 Micron",$R103="5 Micron",$R103="N C"),$AE103*1/350,0))))),2) -> #DIV/0! | AG103: =IF(ISNUMBER(N103), CEILING(MAX(AI103,AJ103),0.5), "Ambient") -> #DIV/0! | AH103: C | AI103: =IF(ISNUMBER(N103), CEILING(CE103/12000,0.5), "Ambient") -> 0 | AJ103: =IF(ISNUMBER(N103),CEILING(AE103/(IF(AH103="C",400,300)),0.5), "Ambient") -> #DIV/0!
C104: =IF(D104<>"",COUNTA($D$10:D104),"") -> 83 | D104: Clean Room 24 | E104: 2.2 | F104: 2.8 | G104: 2.4 | H104: 2 | I104: 1 | J104: 1.75 | K104: 3 | L104: 0.1 | M104: 0 | N104: 24 | O104: 50 | P104: 45 | Q104: 85 | R104: NC | S104: 20 | T104: 0 | U104: 100 | V104: =R104 -> NC | W104: =S104 -> 20 | X104: =E104*F104*10.76 -> 66.2816 | Y104: =X104*G104*3.28 -> 521.76876 | Z104: =Y104*S104/60 -> 173.92292 | AA104: =Z104*L104 -> 17.392292 | AB104: =IF(N104="Amb",Z104,Z104*M104) -> 0 | AC104: =IF(ISNUMBER(N104), (AA104*0.075*60/2.20462)*BP104/7000, "Ambient") -> 0 | AD104: =IF(ISNUMBER(N104), CEILING(CF104/(0.68*BP104),25), "Ambient") -> #DIV/0! | AE104: =CEILING(MAX((Z104+AA104),AD104),25) -> #DIV/0! | AF104: =CEILING(IF(OR($R104="ISO 6",$R104="GRADE B",$R104="1K",$R104=1000),AE104*1/175,IF(OR($R104="ISO 5",$R104="GRADE A",$R104=100),AE104*1/100,IF(OR($R104="ISO 7",$R104="GRADE C",$R104="10K",$R104=10000),$AE104*1/250,IF(OR($R104="ISO 8",$R104="GRADE D",$R104="100K",$R104=100000),$AE104*1/250,IF(OR($R104="NC",$R104="20 Micron",$R104="5 Micron",$R104="N C"),$AE104*1/350,0))))),2) -> #DIV/0! | AG104: =IF(ISNUMBER(N104), CEILING(MAX(AI104,AJ104),0.5), "Ambient") -> #DIV/0! | AH104: C | AI104: =IF(ISNUMBER(N104), CEILING(CE104/12000,0.5), "Ambient") -> 0 | AJ104: =IF(ISNUMBER(N104),CEILING(AE104/(IF(AH104="C",400,300)),0.5), "Ambient") -> #DIV/0!
C105: =IF(D105<>"",COUNTA($D$10:D105),"") -> 84 | D105: Clean Room 25 | E105: 2.8 | F105: 2.4 | G105: 2.4 | H105: 2 | I105: 1 | J105: 1.75 | K105: 3 | L105: 0.1 | M105: 0 | N105: 24 | O105: 50 | P105: 45 | Q105: 85 | R105: NC | S105: 20 | T105: 0 | U105: 100 | V105: =R105 -> NC | W105: =S105 -> 20 | X105: =E105*F105*10.76 -> 72.3072 | Y105: =X105*G105*3.28 -> 569.20228 | Z105: =Y105*S105/60 -> 189.73409 | AA105: =Z105*L105 -> 18.973409 | AB105: =IF(N105="Amb",Z105,Z105*M105) -> 0 | AC105: =IF(ISNUMBER(N105), (AA105*0.075*60/2.20462)*BP105/7000, "Ambient") -> 0 | AD105: =IF(ISNUMBER(N105), CEILING(CF105/(0.68*BP105),25), "Ambient") -> #DIV/0! | AE105: =CEILING(MAX((Z105+AA105),AD105),25) -> #DIV/0! | AF105: =CEILING(IF(OR($R105="ISO 6",$R105="GRADE B",$R105="1K",$R105=1000),AE105*1/175,IF(OR($R105="ISO 5",$R105="GRADE A",$R105=100),AE105*1/100,IF(OR($R105="ISO 7",$R105="GRADE C",$R105="10K",$R105=10000),$AE105*1/250,IF(OR($R105="ISO 8",$R105="GRADE D",$R105="100K",$R105=100000),$AE105*1/250,IF(OR($R105="NC",$R105="20 Micron",$R105="5 Micron",$R105="N C"),$AE105*1/350,0))))),2) -> #DIV/0! | AG105: =IF(ISNUMBER(N105), CEILING(MAX(AI105,AJ105),0.5), "Ambient") -> #DIV/0! | AH105: C | AI105: =IF(ISNUMBER(N105), CEILING(CE105/12000,0.5), "Ambient") -> 0 | AJ105: =IF(ISNUMBER(N105),CEILING(AE105/(IF(AH105="C",400,300)),0.5), "Ambient") -> #DIV/0!
C106: =IF(D106<>"",COUNTA($D$10:D106),"") | X106: =SUM(X90:X105) -> 1144.1108 | Y106: =SUM(Y90:Y105) -> 9006.4402 | Z106: =SUM(Z90:Z105) -> 3002.1467 | AA106: =SUM(AA90:AA105) -> 300.21467 | AB106: =SUM(AB90:AB105) -> 0 | AC106: =SUM(AC90:AC105) -> 0 | AD106: =SUM(AD90:AD105) -> #DIV/0! | AE106: =SUM(AE90:AE105) -> #DIV/0! | ... AG106: =SUM(AG90:AG105) -> #DIV/0! | AI106: =SUM(AI90:AI105) -> 0 | AJ106: =SUM(AJ90:AJ105) -> #DIV/0!
C107: =IF(D107<>"",COUNTA($D$10:D107),"")
...

Sheet Output BOQ
C24: Sub.: Offer for Class 100K AC & Ventilation System and NC System for your PB - C and Pilot Plan Reg.
C26: S.No. | D26: Description & Specifications | J26: Units | K26: Qty | L26: Supply | N26: Installation
L27: Rate | M27: Amount | N27: Rate | O27: Amount
C28: I | D28: AIR HANDLING UNITS
D31: Supply, Installation, Testing & Commissioning of Factory assembled/ modular Single / Double Skin floor mounted type Air Handling Units (AHUs)(Single / Double Decker as per Plant Room Specs. AHUs shall be complete with Single skin 25 mm panels with 1.2mm Zinc / G.I. Sheets or double skin 25/47 mm thick insulated panels with CFC free polyurethane foam (PUF) insulation material with minimum density of 42 Kg/m3, sandwiched between 0.63/0.8 mm thick Aluminium Zinc / G.I.Sheets (inner skin) and pre-coated G.I. Sheets (outer skin). The AHUs shall be complete with mixing box with necessary openings and provosion for aluminium dampers for teminating return air and fresh air ducts. Food grade self-adhesive coated EPDM gaskets shall be provided between panels and structure of the AHU to ensure the entire housing is airtight, and should meet clean room class leakage requirments as per Standards. The AHUs shall be complete with provision for Fresh air filter section/ pre-filter section/ fine-filter or filters section/Superfine filter sections as mentioned below along without/with cooling coil section with specified multirows deep chilled water cooling coil of copper tube & aluminium fin construction to be sized for Cooling load specified with all controls & accessories, Re-heat section complete with finned type strip heaters, SS drain pan constructed from 18 gauge stainless steel & factory insulated with closed cell elastomeric Class 'O' material, copper header with "Copper to MS" adopter for Evaporator coil made out of 1/2" / 5/8" copper tubes with MS Header/Distributor with 12-13 FPI of mentioned capacities., all adaptive controls such as airstat, geyserstat, safetystat complete with wiring & vibration isolation pads etc. and all complete as per the specifications for Air-conditioning. AHUs shall be selected for a maximum face velocity of 500 FPM (2.5 MPS) and as per the Schedule of Air Handling Units. fan section with backward curved centrifugal fan (Kruger / Nicotra / Equivalent Make) with V-Belt drive arrangement and access doors where ever necessary with Motor (Crompton / equivalent Make) and Fan outlet velocity shall not exceed as per selected blower ratings and not more than 2000 FPM (10.2 MPS). AHUs should have marine lamps including adequately rated LED inside the AHU Cabinets. AHU inspection doors should have view windows with perfectly sealed gaksets on either side to ensure air tightness. All AHU doors shall be provided with door limit switch and door safety GI guard as well. | AM31: Gear Type Aluminium Volume Control Dampers | AN31: Fire Retardent / Control Dampers
AG32: Fresh Air | AL32: Exhaust
AG33: 20 Micron | AH33: 10 Micron | AI33: 5 Micron | AJ33: 1 Micron | AK33: 0.3 Micron | AL33: 20 Micron
D34: ="AHU - " & INT((ROW()-34)/14)+1 & " " & IF(I35>0,"Air-Conditioning System " & IF(OR(G38="Header", G38="C"), "(Chilled Water)",IF(OR(G38="Distributor", G38="D"), "(DX)", "Ventilation System")),IF(NOT(I35>0), "Ventilation System ( SUPPLY )", "Refer")) -> AHU - 1 Air-Conditioning System (DX)
D35: CLASS | E35: ='BOD-Cold & Amb.'!R10 -> Class100K | F35: CFM | G35: ='BOD-Cold & Amb.'!AK10 -> 15750 | H35: AC Load | I35: ='BOD-Cold & Amb.'!AQ10 -> 56 | J35: Nos. | K35: 1 | L35: =Q35 -> 867500 | M35: =K35*L35 -> 867500 | Q35: =CEILING((S35+T35+U35+V35+W35),250) -> 867500 | R35: =IF(I35>0,625,375) -> 625 | S35: =(E36*G36*3*10.76+E36*I36*2*10.76+G36*I36*2*10.76)*R35/(1000*1000) -> 410140.94 | T35: =I35*4*1050 -> 235200 | U35: =_xlfn.IFS( G35<=2000,5000, G35<=5000,8000, G35<=10000,10000, G35<=18000,15000, G35<=40000,20000, G35>40000,25000 ) -> 15000 | V35: =IF(X35=200,17150,(IF(X35=225,18150,(IF(X35=250,18900,(IF(X35=280,19150,(IF(X35=315,19650,(IF(X35=355,21900,(IF(X35=400,24400,0)))))))))))))+IF(X35=450,31000,(IF(X35=500,37450,(IF(X35=560,45650,(IF(X35=630,58900,(IF(X35=710,77950,0)))))))))+IF(X35=800,119650,(IF(X35=900,153300,(IF(X35=1000,178900,(IF(X35=1120,286500,(IF(X35=1250,394500,(IF(X35=1450,461500,0))))))))))) -> 77950 | W35: =_xlfn.IFS( $I$37=0.5,16600, $I$37=1,19050, $I$37=1.5,21750, $I$37=2,23600, $I$37=3,30000, $I$37=5,38000, $I$37=7.5,52300, $I$37=10,59600, $I$37=12.5,100350, $I$37=15,106000, $I$37=20,129150, $I$37=25,146050, $I$37=30,173600, $I$51=40,233900, $I$37=50,304650, $I$37=60,350000, $I$37=70,400000 ) -> 129150 | X35: =E37 -> 710 | Y35: =IF(G35<=6750,450,(IF(G35<=8500,500,(IF(G35<=10750,560,(IF(G35<=13500,630,(IF(G35<=17000,710,(IF(G35<=21500,800,(IF(G35<=27000,900,(IF(G35<=34000,1000,0))))))))))))))) -> 710 | Z35: =IF(G35<=1300,200,(IF(G35<=1600,225,(IF(G35<=2100,250,(IF(G35<=2700,280,(IF(G35<=3450,315,(IF(G35<=4250,355,(IF(G35<=5250,400,(IF(G35<=6750,450,0))))))))))))))) -> 0 | AA35: =IF(G35<=2000,5000,(IF(G35<=5000,8000,(IF(G35<=10000,10000,(IF(G35<=18000,15000,(IF(G35<=40000,20000,10000))))))))) -> 15000 | AB35: =IF(E36=950,2,(IF(E36=1150,3,(IF(E36=1550,4,(IF(E36=1750,5,(IF(E36=2050,6,(IF(E36=2900,8,(IF(E36=3600,10,12))))))))))))) -> 6 | AC35: =IF(G36=950,2,(IF(G36=1150,3,(IF(G36=1550,4,(IF(G36=1750,5,(IF(G36=2050,6,(IF(G36=2900,8,(IF(G36=3600,10,12))))))))))))) -> 6 | AD35: =AC35*AB35 -> 36 | AE35: 150 | AF35: =CEILING((SQRT(G35/1000))*4*2*AE35*1.25*K35,100) -> 6000 | AG35: =E43*F43*H43/(305*305) -> 0 | AH35: =E44*F44*H44/(305*305) -> 36 | AI35: =H45*E45*F45/(305*305) -> 36 | AJ35: =H46*E46*F46/(305*305) -> 36 | AK35: =H47*E47*F47/(305*305) -> 0 | AL35: =IF(I35=0,0) -> FALSE | AM35: =(G35*2.2/1100) -> 31.5 | AN35: =(G35*1/1100) -> 14.318182
D36: AHU(W) | E36: ='BOD-Cold & Amb.'!AL11 -> 2050 | F36: AHU(H) | G36: ='BOD-Cold & Amb.'!AL13 -> 2050 | H36: AHU(L) | I36: ='BOD-Cold & Amb.'!AL15 -> 5900
D37: Blower | E37: ='BOD-Cold & Amb.'!AN10 -> 710 | F37: Static Pr | G37: ='BOD-Cold & Amb.'!AM10 -> 125 | H37: Motor Hp | I37: ='BOD-Cold & Amb.'!AO10 -> 20
D38: Coil Rows | E38: ='BOD-Cold & Amb.'!AP10 -> 8 | F38: Coil Head Type | G38: =IF(OR(I35=0, E38="Amb"), "Amb",IF('BOD-Cold & Amb.'!AH10="C", "Header",IF('BOD-Cold & Amb.'!AH10="D", "Distributor", "Refer"))) -> Distributor | H38: Coil Size hxw in mm | I38: =IF(OR(I35=0, E38=0), 0,ROUND(((( I35/E38)*304.8)/(E36-400))*1000,0)&" h "&" x " & (E36-400)&" w ") -> 1293 h x 1650 w
D39: No. of Filtr. Stages | E39: ='BOD-Cold & Amb.'!AR10 -> 3 | F39: Filter Ratings | G39: =IF(E39=5,"20µ,10µ, 5µ, 1µ & 0.3µ (HEPA Plenum Fitted 95% eff.)",IF(E39=4,"10µ, 5µ, 1µ & 0.3µ (HEPA Plenum Fitted 95% eff.)",IF(E39=3,"10µ, 5µ & 1µ ",IF(E39=2,"10µ & 5µ",IF(E39=1,"10µ","Filter Ratings"))))) -> 10µ, 5µ & 1µ
D40: Filters Size and Quantity for mentioned ratings
D41: Filter Rating | E41: Width mm | F41: Height mm | G41: Depth mm | H41: Filter Qty Nos
E42: =IF(E36<=950,2,(IF(E36<=1200,3,(IF(E36<=1550,4,(IF(E36<=1750,5,(IF(E36<=2050,6,(IF(E36<=2900,8,(IF(E36<=3600,10,IF(E36<=4000,12,0)))))))))))))) -> 6 | F42: =IF(G36<=950,2,(IF(G36<=1200,3,(IF(G36<=1550,4,(IF(G36<=1750,5,(IF(G36<=2050,6,(IF(G36<=2900,8,(IF(G36<=3600,10,IF(E36<=4000,12,0)))))))))))))) -> 6
D43: =IF(AND(I35=0, OR(E39=1, E39=2, E39=3, E39=4, E39=5)), "20µ", 0) -> 0 | E43: =IF(OR(D43=0),0,IF(MOD($E$42*$F$42,2)=0,"610",IF(MOD($E$42*$F$42,2.5)=0,"760",IF(MOD($E$42*$F$42,3)=0,"915","Refer")))) -> 0 | F43: =IF(OR(D43=0),0,IF(MOD($E$42*$F$42,4)=0,"610",IF(MOD($E$42*$F$42,5)=0,"760",IF(MOD($E$42*$F$42,6)=0,"915","Refer")))) -> 0 | G43: =IF(D43=0,0,100) -> 0 | H43: =ROUND(IF(D43=0,0,($E$42*$F$42*305*305)/(E43*F43)),0) -> 0
D44: =IF(E39=5,"10µ",IF(E39=4,"10µ",IF(E39=3,"10µ",IF(E39=2,"10µ",IF(E39=1,"10µ",0))))) -> 10µ | E44: =IF(OR(D44=0),0,IF(MOD($E$42*$F$42,2)=0,"610",IF(MOD($E$42*$F$42,2.5)=0,"760",IF(MOD($E$42*$F$42,3)=0,"915","Refer")))) -> 610 | F44: =IF(OR(D44=0),0,IF(MOD($E$42*$F$42,4)=0,"610",IF(MOD($E$42*$F$42,5)=0,"760",IF(MOD($E$42*$F$42,6)=0,"915","Refer")))) -> 610 | G44: =IF(D44=0,0,150) -> 150 | H44: =ROUND(IF(D44=0,0,($E$42*$F$42*305*305)/(E44*F44)),0) -> 9
D45: =IF(E39=5,"5µ",IF(E39=4,"5µ",IF(E39=3,"5µ",IF(E39=2,"5µ",0)))) -> 5µ | E45: =IF(OR(D45=0),0,IF(MOD($E$42*$F$42,2)=0,"610",IF(MOD($E$42*$F$42,2.5)=0,"760",IF(MOD($E$42*$F$42,3)=0,"915","Refer")))) -> 610 | F45: =IF(OR(D45=0),0,IF(MOD($E$42*$F$42,4)=0,"610",IF(MOD($E$42*$F$42,5)=0,"760",IF(MOD($E$42*$F$42,6)=0,"915","Refer")))) -> 610 | G45: =IF(D45=0,0,300) -> 300 | H45: =ROUND(IF(D45=0,0,($E$42*$F$42*305*305)/(E45*F45)),0) -> 9
D46: =IF(E39=5,"1µ",IF(E39=4,"1µ",IF(E39=3,"1µ",0))) -> 1µ | E46: =IF(OR(D46=0),0,IF(MOD($E$42*$F$42,2)=0,"610",IF(MOD($E$42*$F$42,2.5)=0,"760",IF(MOD($E$42*$F$42,3)=0,"915","Refer")))) -> 610 | F46: =IF(OR(D46=0),0,IF(MOD($E$42*$F$42,4)=0,"610",IF(MOD($E$42*$F$42,5)=0,"760",IF(MOD($E$42*$F$42,6)=0,"915","Refer")))) -> 610 | G46: =IF(D46=0,0,300) -> 300 | H46: =ROUND(IF(D46=0,0,($E$42*$F$42*305*305)/(E46*F46)),0) -> 9
D47: =IF(E39=5,"0.3µHEPA(95%)",IF(E39=4,"0.3µHEPA(95%)",0)) -> 0 | E47: =IF(OR(D47=0),0,IF(MOD($E$42*$F$42,2)=0,"610",IF(MOD($E$42*$F$42,2.5)=0,"760",IF(MOD($E$42*$F$42,3)=0,"915","Refer")))) -> 0 | F47: =IF(OR(D47=0),0,IF(MOD($E$42*$F$42,4)=0,"610",IF(MOD($E$42*$F$42,5)=0,"760",IF(MOD($E$42*$F$42,6)=0,"915","Refer")))) -> 0 | G47: =IF(D47=0,0,300) -> 0 | H47: =ROUND(IF(D47=0,0,($E$42*$F$42*305*305)/(E47*F47)),0) -> 0
D48: EXHAUST | E48: ="AHU - " & INT((ROW()-34)/14) & " " & IF(I35>0,"Air-Conditioning System " & IF(OR(G38="Header", G38="C"), "(Chilled Water)",IF(OR(G38="Distributor", G38="D"), "(DX)", "Ventilation System")),IF(NOT(I35>0), "Ventilation System ( EXHAUST )", "NOT APPLICABLE / Refer")) -> AHU - 1 Air-Conditioning System (DX)
D49: No. of Filtr. Stages | E49: 1 | F49: CFM | G49: =IF(I35=0,CEILING('BOD-Cold & Amb.'!AB26,100),0) -> 0 | H49: Filter Ratings | I49: =IF(E49=5,"20µ,10µ, 5µ, 1µ & 0.3µ (HEPA Plenum Fitted 95% eff.)",IF(E49=4,"20µ,10µ, 5µ, 1µ ",IF(E49=3,"20µ, 10µ & 5µ ",IF(E49=2,"20µ & 10µ",IF(E49=1,"20µ","Filter Ratings"))))) -> 20µ | J49: Nos. | K49: 1 | L49: =Q52 -> 406750 | M49: =K49*L49 -> 406750
D50: AHU(W) | E50: ='BOD-Cold & Amb.'!AL11 -> 2050 | F50: AHU(H) | G50: ='BOD-Cold & Amb.'!AL13 -> 2050 | H50: AHU(L) | I50: =IF(E51<=315,1600,(IF(E51=355,1650,(IF(E51=400,1650,(IF(E51=450,1700,(IF(E51=500,1700,(IF(E51=560,1800,(IF(E51=630,2000,(IF(E51=710,2200,2500)))))))))))))))+IF(E49=1,800,(IF(E49=2,1300,(IF(E49=3,2300,(IF(E49=4,3300,(IF(E49=3,4000,0))))))))) -> 2400
D51: Blower | E51: =IF(G49<=1300,200,IF(G49<=1600,225,IF(G49<=2100,250,IF(G49<=2700,280,IF(G49<=3450,315,IF(G49<=4250,355,IF(G49<=5250,400,IF(G49<=6750,450,IF(G49<=8500,500,IF(G49<=10750,560,IF(G49<=13500,630,IF(G49<=17000,710,IF(G49<=21500,800,IF(G49<=27000,900,IF(G49<=34000,1000,IF(G49<=43000,1120,IF(G49<=49000,1200,IF(G49<=68000,1450,"Refer")))))))))))))))))) -> 200 | F51: Static Pr | G51: =IF(E49=5,135,IF(E49=4,110,IF(E49=3,90,IF(E49=2,65,IF(E49=1,50,"Filter Ratings"))))) -> 50 | H51: Motor Hp | I51: =IF(G49*G51/(6356*0.7*0.9*1.1*25.4)<=1,1,IF(G49*G51/(6356*0.7*0.9*1.1*25.4)<=1.5,1.5,IF(G49*G51/(6356*0.7*0.9*1.1*25.4)<=2,2,IF(G49*G51/(6356*0.7*0.9*1.1*25.4)<=3,3,IF(G49*G51/(6356*0.7*0.9*1.1*25.4)<=5,5,IF(G49*G51/(6356*0.7*0.9*1.1*25.4)<=7.5,7.5,IF(G49*G51/(6356*0.7*0.9*1.1*25.4)<=10,10,IF(G49*G51/(6356*0.7*0.9*1.1*25.4)<=12.5,12.5,IF(G49*G51/(6356*0.7*0.9*1.1*25.4)<=15,15,IF(G49*G51/(6356*0.7*0.9*1.1*25.4)<=20,20,IF(G49*G51/(6356*0.7*0.9*1.1*25.4)<=25,25,IF(G49*G51/(6356*0.7*0.9*1.1*25.4)<=30,30,IF(G49*G51/(6356*0.7*0.9*1.1*25.4)<=40,40,IF(G49*G51/(6356*0.7*0.9*1.1*25.4)<=50,50,IF(G49*G51/(6356*0.7*0.9*1.1*25.4)<=60,60,IF(G49*G51/(6356*0.7*0.9*1.1*25.4)<=75,75,"Refer")))))))))))))))) -> 1
D52: Filter Rating | E52: Width mm | F52: Height mm | G52: Depth mm | H52: Filter Qty Nos | Q52: =CEILING((S52+T52+U52+V52+W52),250) -> 406750 | R52: =IF(I52>0,625,375) -> 375 | S52: =($E$50*$G$50*3*10.76+$E$50*$I$50*2*10.76+$G$50*$I$50*2*10.76)*R52/(1000*1000) -> 130280.06 | T52: =$I$35*4*1050 -> 235200 | U52: =_xlfn.IFS( $G$49<=2000,5000, $G$49<=5000,8000, $G$49<=10000,10000, $G$49<=18000,15000, $G$49<=40000,20000, $G$49>40000,25000 ) -> 5000 | V52: =IF(X52=200,17150,(IF(X52=225,18150,(IF(X52=250,18900,(IF(X52=280,19150,(IF(X52=315,19650,(IF(X52=355,21900,(IF(X52=400,24400,0)))))))))))))+IF(X52=450,31000,(IF(X52=500,37450,(IF(X52=560,45650,(IF(X52=630,58900,(IF(X52=710,77950,0)))))))))+IF(X52=800,119650,(IF(X52=900,153300,(IF(X52=1000,178900,(IF(X52=1120,286500,(IF(X52=1250,394500,(IF(X52=1450,461500,0))))))))))) -> 17150 | W52: =_xlfn.IFS( $I$51=0.5,16600, $I$51=1,19050, $I$51=1.5,21750, $I$51=2,23600, $I$51=3,30000, $I$51=5,38000, $I$51=7.5,52300, $I$51=10,59600, $I$51=12.5,100350, $I$51=15,106000, $I$51=20,129150, $I$51=25,146050, $I$51=30,173600, $I$51=40,233900, $I$51=50,304650, $I$51=60,350000, $I$51=70,400000 ) -> 19050 | X52: =E51 -> 200 | Y52: =IF(G52<=6750,450,(IF(G52<=8500,500,(IF(G52<=10750,560,(IF(G52<=13500,630,(IF(G52<=17000,710,(IF(G52<=21500,800,(IF(G52<=27000,900,(IF(G52<=34000,1000,0))))))))))))))) -> 0 | Z52: =IF(G52<=1300,200,(IF(G52<=1600,225,(IF(G52<=2100,250,(IF(G52<=2700,280,(IF(G52<=3450,315,(IF(G52<=4250,355,(IF(G52<=5250,400,(IF(G52<=6750,450,0))))))))))))))) -> 0 | AA52: =IF(G52<=2000,5000,(IF(G52<=5000,8000,(IF(G52<=10000,10000,(IF(G52<=18000,15000,(IF(G52<=40000,20000,10000))))))))) -> 10000 | AB52: =IF(E53=950,2,(IF(E53=1150,3,(IF(E53=1550,4,(IF(E53=1750,5,(IF(E53=2050,6,(IF(E53=2900,8,(IF(E53=3600,10,12))))))))))))) -> 12 | AC52: =IF(G53=950,2,(IF(G53=1150,3,(IF(G53=1550,4,(IF(G53=1750,5,(IF(G53=2050,6,(IF(G53=2900,8,(IF(G53=3600,10,12))))))))))))) -> 12 | AD52: =AC52*AB52 -> 144 | AE52: 150 | AF52: =CEILING((SQRT(G49/1000))*4*2*AE52*1.25*K49,100) -> 0 | AG52: =E60*F60*H60/(305*305) -> 0 | AH52: =E61*F61*H61/(305*305) -> 0 | AI52: =IF(I35=0,0) -> FALSE | AJ52: =H55*E55*F55/(305*305) -> 0 | AK52: =H55*E55*F55/(305*305) -> 0 | AL52: =E54*F54*H54/(305*305) -> 0 | AM52: =(G49*2.2/1100) -> 0 | AN52: =(G49*1/1100) -> 0
E53: =IF(E50<=950,2,(IF(E50<=1200,3,(IF(E50<=1550,4,(IF(E50<=1750,5,(IF(E50<=2050,6,(IF(E50<=2900,8,(IF(E50<=3600,10,IF(E50<=4000,12,0)))))))))))))) -> 6 | F53: =IF(G50<=950,2,(IF(G50<=1200,3,(IF(G50<=1550,4,(IF(G50<=1750,5,(IF(G50<=2050,6,(IF(G50<=2900,8,(IF(G50<=3600,10,IF(E50<=4000,12,0)))))))))))))) -> 6
D54: =IF(AND(I35=0, OR(E49=1, E49=2, E49=3, E49=4, E49=5)), "20µ", 0) -> 0 | E54: =IF(OR(D54=0),0,IF(MOD($E$53*$F$53,2)=0,"610",IF(MOD($E$53*$F$53,2.5)=0,"760",IF(MOD($E$53*$F$53,3)=0,"915","Refer")))) -> 0 | F54: =IF(OR(D54=0),0,IF(MOD($E$53*$F$53,4)=0,"610",IF(MOD($E$53*$F$53,5)=0,"760",IF(MOD($E$53*$F$53,6)=0,"915","Refer")))) -> 0 | G54: =IF(D54=0,0,100) -> 0 | H54: =ROUND(IF(D54=0,0,($E$53*$F$53*305*305)/(E54*F54)),0) -> 0
D55: =IF(AND(I35=0, OR( E49=2, E49=3, E49=4, E49=5)), "10µ", 0) -> 0 | E55: =IF(OR(D55=0),0,IF(MOD($E$53*$F$53,2)=0,"610",IF(MOD($E$53*$F$53,2.5)=0,"760",IF(MOD($E$53*$F$53,3)=0,"915","Refer")))) -> 0 | F55: =IF(OR(D55=0),0,IF(MOD($E$53*$F$53,4)=0,"610",IF(MOD($E$53*$F$53,5)=0,"760",IF(MOD($E$53*$F$53,6)=0,"915","Refer")))) -> 0 | G55: =IF(D55=0,0,150) -> 0 | H55: =ROUND(IF(D55=0,0,($E$53*$F$53*305*305)/(E55*F55)),0) -> 0
D56: =IF(AND(I35=0, OR(E49=3, E49=4, E49=5)), "5µ", 0) -> 0 | E56: =IF(OR(D56=0),0,IF(MOD($E$53*$F$53,2)=0,"610",IF(MOD($E$53*$F$53,2.5)=0,"760",IF(MOD($E$53*$F$53,3)=0,"915","Refer")))) -> 0 | F56: =IF(OR(D56=0),0,IF(MOD($E$53*$F$53,4)=0,"610",IF(MOD($E$53*$F$53,5)=0,"760",IF(MOD($E$53*$F$53,6)=0,"915","Refer")))) -> 0 | G56: =IF(D56=0,0,300) -> 0 | H56: =ROUND(IF(D56=0,0,($E$53*$F$53*305*305)/(E56*F56)),0) -> 0
D57: =IF(AND(I35=0, OR(E49=4, E49=5)), "1µ", 0) -> 0 | E57: =IF(OR(D57=0),0,IF(MOD($E$53*$F$53,2)=0,"610",IF(MOD($E$53*$F$53,2.5)=0,"760",IF(MOD($E$53*$F$53,3)=0,"915","Refer")))) -> 0 | F57: =IF(OR(D57=0),0,IF(MOD($E$53*$F$53,4)=0,"610",IF(MOD($E$53*$F$53,5)=0,"760",IF(MOD($E$53*$F$53,6)=0,"915","Refer")))) -> 0 | G57: =IF(D57=0,0,300) -> 0 | H57: =ROUND(IF(D57=0,0,($E$53*$F$53*305*305)/(E57*F57)),0) -> 0
D58: =IF(AND(I35=0, OR(E49=5)), "0.3µHEPA(95%)", 0) -> 0 | E58: =IF(OR(D58=0),0,IF(MOD($E$53*$F$53,2)=0,"610",IF(MOD($E$53*$F$53,2.5)=0,"760",IF(MOD($E$53*$F$53,3)=0,"915","Refer")))) -> 0 | F58: =IF(OR(D58=0),0,IF(MOD($E$53*$F$53,4)=0,"610",IF(MOD($E$53*$F$53,5)=0,"760",IF(MOD($E$53*$F$53,6)=0,"915","Refer")))) -> 0 | G58: =IF(D58=0,0,300) -> 0 | H58: =ROUND(IF(D58=0,0,($E$53*$F$53*305*305)/(E58*F58)),0) -> 0
D61: ="AHU - " & INT((ROW()-34)/14)+1 & " " & IF(I62>0,"Air-Conditioning System " & IF(OR(G65="Header", G65="C"), "(Chilled Water)",IF(OR(G65="Distributor", G65="D"), "(DX)", "Ventilation System")),IF(NOT(I62>0), "Ventilation System ( SUPPLY )", "Refer")) -> AHU - 2 Air-Conditioning System (DX)
D62: CLASS | E62: ='BOD-Cold & Amb.'!R30 -> ISO 6 | F62: CFM | G62: ='BOD-Cold & Amb.'!AK30 -> 48500 | H62: AC Load | I62: ='BOD-Cold & Amb.'!AQ30 -> 124.5 | J62: Nos. | K62: 1 | L62: =Q62 -> 1911500 | M62: =K62*L62 -> 1911500 | Q62: =CEILING((S62+T62+U62+V62+W62),250) -> 1911500 | R62: =IF(I62>0,625,375) -> 625 | S62: =(E63*G63*3*10.76+E63*I63*2*10.76+G63*I63*2*10.76)*R62/(1000*1000) -> 883396 | T62: =I62*4*1050 -> 522900 | U62: =IF(G62<=2000,5000,(IF(G62<=5000,8000,(IF(G62<=10000,10000,(IF(G62<=18000,15000,(IF(G62<=40000,20000,25000))))))))) -> 25000 | V62: =IF(X62=200,17150,(IF(X62=225,18150,(IF(X62=250,18900,(IF(X62=280,19150,(IF(X62=315,19650,(IF(X62=355,21900,(IF(X62=400,24400,0)))))))))))))+IF(X62=450,31000,(IF(X62=500,37450,(IF(X62=560,45650,(IF(X62=630,58900,(IF(X62=710,77950,0)))))))))+IF(X62=800,119650,(IF(X62=900,153300,(IF(X62=1000,178900,(IF(X62=1120,286500,(IF(X62=1250,394500,(IF(X62=1450,461500,0))))))))))) -> 0 | W62: =IF(I64=0.5,16600,(IF(I64=1,19050,(IF(I64=1.5,21750,(IF(I64=2,23600,(IF(I64=3,30000,(IF(I64=5,38000,0)))))))))))*1.2+IF(I64=7.5,52300,(IF(I64=10,59600,0)))*1.2+IF(I64=12.5,100350,(IF(I64=15,106000,(IF(I64=20,129150,(IF(I64=25,146050,(IF(I64=30,173600,(IF(I64=40,233900,(IF(I64=50,304650,IF(I64=60,350000,400000)))))))))))))*1.2) -> 480000 | X62: =E64 -> 1200 | Y62: =IF(G62<=6750,450,(IF(G62<=8500,500,(IF(G62<=10750,560,(IF(G62<=13500,630,(IF(G62<=17000,710,(IF(G62<=21500,800,(IF(G62<=27000,900,(IF(G62<=34000,1000,0))))))))))))))) -> 0 | Z62: =IF(G62<=1300,200,(IF(G62<=1600,225,(IF(G62<=2100,250,(IF(G62<=2700,280,(IF(G62<=3450,315,(IF(G62<=4250,355,(IF(G62<=5250,400,(IF(G62<=6750,450,0))))))))))))))) -> 0 | AA62: =IF(G62<=2000,5000,(IF(G62<=5000,8000,(IF(G62<=10000,10000,(IF(G62<=18000,15000,(IF(G62<=40000,20000,10000))))))))) -> 10000 | AB62: =IF(E63=950,2,(IF(E63=1150,3,(IF(E63=1550,4,(IF(E63=1750,5,(IF(E63=2050,6,(IF(E63=2900,8,(IF(E63=3600,10,12))))))))))))) -> 12 | AC62: =IF(G63=950,2,(IF(G63=1150,3,(IF(G63=1550,4,(IF(G63=1750,5,(IF(G63=2050,6,(IF(G63=2900,8,(IF(G63=3600,10,12))))))))))))) -> 10 | AD62: =AC62*AB62 -> 120 | AE62: 150 | AF62: =CEILING((SQRT(G62/1000))*4*2*AE62*1.25*K62,100) -> 10500 | AG62: =E70*F70*H70/(305*305) -> 0 | AH62: =E71*F71*H71/(305*305) -> 36 | AI62: =H72*E72*F72/(305*305) -> 36 | AJ62: =H73*E73*F73/(305*305) -> 36 | AK62: =H74*E74*F74/(305*305) -> 0 | AM62: =(G62*2.2/1100) -> 97 | AN62: =(G62*1/1100) -> 44.090909
D63: AHU(W) | E63: ='BOD-Cold & Amb.'!AL31 -> 4000 | F63: AHU(H) | G63: ='BOD-Cold & Amb.'!AL33 -> 3600 | H63: AHU(L) | I63: ='BOD-Cold & Amb.'!AL35 -> 5800
D64: Blower | E64: ='BOD-Cold & Amb.'!AN30 -> 1200 | F64: Static Pr | G64: ='BOD-Cold & Amb.'!AM30 -> 150 | H64: Motor Hp | I64: ='BOD-Cold & Amb.'!AO30 -> 75
D65: Coil Rows | E65: ='BOD-Cold & Amb.'!AP30 -> 4 | F65: Coil Head Type | G65: =IF(OR(I62=0, E65="Amb"), "Amb",IF('BOD-Cold & Amb.'!AH25="C", "Header",IF('BOD-Cold & Amb.'!AH25="D", "Distributor", "Refer"))) -> Distributor | H65: Coil Size hxw in mm | I65: =IF(OR(I62=0, E65=0), 0,ROUND(((( I62/E65)*304.8)/(E63-400))*1000,0)&" h "&" x " & (E63-400)&" w ") -> 2635 h x 3600 w
D66: No. of Filtr. Stages | E66: ='BOD-Cold & Amb.'!AR30 -> 3 | F66: Filter Ratings | G66: =IF(E66=4,"10µ, 5µ, 1µ & 0.3µ (HEPA Plenum Fitted 95% eff.)",IF(E66=3,"10µ, 5µ & 1µ ",IF(E66=2,"10µ & 5µ",IF(E66=1,"10µ", "Filter Ratings")))) -> 10µ, 5µ & 1µ
D67: Filters Size and Quantity for mentioned ratings
D68: Filter Rating | E68: Width mm | F68: Height mm | G68: Depth mm | H68: Filter Qty Nos
E69: =IF(E63<=950,2,(IF(E63<=1150,3,(IF(E63<=1550,4,(IF(E63<=1750,5,(IF(E63<=2050,6,(IF(E63<=2900,8,(IF(E63<=3600,10,IF(E63<=4000,12,0)))))))))))))) -> 12 | F69: =IF(G63<=950,2,(IF(G63<=1150,3,(IF(G63<=1550,4,(IF(G63<=1750,5,(IF(G63<=2050,6,(IF(G63<=2900,8,(IF(G63<=3600,10,IF(E63<=4000,12,0)))))))))))))) -> 10
D70: =IF(AND(I62=0, OR(E66=1, E66=2, E66=3, E66=4, E66=5)), "20µ", 0) -> 0 | E70: =IF(OR(D70=0),0,IF(MOD($E$42*$F$42,2)=0,"610",IF(MOD($E$42*$F$42,2.5)=0,"760",IF(MOD($E$42*$F$42,3)=0,"915","Refer")))) -> 0 | F70: =IF(OR(D70=0),0,IF(MOD($E$42*$F$42,6)=0,"915",IF(MOD($E$42*$F$42,5)=0,"760",IF(MOD($E$42*$F$42,4)=0,"610","Refer")))) -> 0 | G70: =IF(D70=0,0,100) -> 0 | H70: =IF(D70=0,0,($E$42*$F$42*305*305)/(E70*F70)) -> 0
D71: =IF(E66=4,"10µ",IF(E66=3,"10µ",IF(E66=2,"10µ",IF(E66=1,"10µ",0)))) -> 10µ | E71: =IF(OR(D71=0),0,IF(MOD($E$42*$F$42,2)=0,"610",IF(MOD($E$42*$F$42,2.5)=0,"760",IF(MOD($E$42*$F$42,3)=0,"915","Refer")))) -> 610 | F71: =IF(OR(D71=0),0,IF(MOD($E$42*$F$42,6)=0,"915",IF(MOD($E$42*$F$42,5)=0,"760",IF(MOD($E$42*$F$42,4)=0,"610","Refer")))) -> 915 | G71: =IF(D71=0,0,150) -> 150 | H71: =IF(D71=0,0,($E$42*$F$42*305*305)/(E71*F71)) -> 6
D72: =IF(E66=4,"5µ",IF(E66=3,"5µ",IF(E66=2,"5µ",0))) -> 5µ | E72: =IF(OR(D72=0),0,IF(MOD($E$42*$F$42,2)=0,"610",IF(MOD($E$42*$F$42,2.5)=0,"760",IF(MOD($E$42*$F$42,3)=0,"915","Refer")))) -> 610 | F72: =IF(OR(D72=0),0,IF(MOD($E$42*$F$42,6)=0,"915",IF(MOD($E$42*$F$42,5)=0,"760",IF(MOD($E$42*$F$42,4)=0,"610","Refer")))) -> 915 | G72: =IF(D72=0,0,300) -> 300 | H72: =IF(D72=0,0,($E$42*$F$42*305*305)/(E72*F72)) -> 6
D73: =IF(E66=4,"1µ",IF(E66=3,"1µ",0)) -> 1µ | E73: =IF(OR(D73=0),0,IF(MOD($E$42*$F$42,2)=0,"610",IF(MOD($E$42*$F$42,2.5)=0,"760",IF(MOD($E$42*$F$42,3)=0,"915","Refer")))) -> 610 | F73: =IF(OR(D73=0),0,IF(MOD($E$42*$F$42,6)=0,"915",IF(MOD($E$42*$F$42,5)=0,"760",IF(MOD($E$42*$F$42,4)=0,"610","Refer")))) -> 915 | G73: =IF(D73=0,0,300) -> 300 | H73: =IF(D73=0,0,($E$42*$F$42*305*305)/(E73*F73)) -> 6
D74: =IF(E66=4,"0.3µ 95% Eff. HEPA Filetr",0) -> 0 | E74: =IF(OR(D74=0),0,IF(MOD($E$42*$F$42,2)=0,"610",IF(MOD($E$42*$F$42,2.5)=0,"760",IF(MOD($E$42*$F$42,3)=0,"915","Refer")))) -> 0 | F74: =IF(OR(D74=0),0,IF(MOD($E$42*$F$42,6)=0,"915",IF(MOD($E$42*$F$42,5)=0,"760",IF(MOD($E$42*$F$42,4)=0,"610","Refer")))) -> 0 | G74: =IF(D74=0,0,300) -> 0 | H74: =IF(D74=0,0,($E$42*$F$42*305*305)/(E74*F74)) -> 0
D76: ="AHU - " & INT((ROW()-34)/14)+1 & " " & IF(I77>0,"Air-Conditioning System " & IF(OR(G80="Header", G80="C"), "(Chilled Water)",IF(OR(G80="Distributor", G80="D"), "(DX)", "Ventilation System")),IF(NOT(I77>0), "Ventilation System ( SUPPLY )", "Refer")) -> AHU - 4 Air-Conditioning System (Chilled Water)
D77: CLASS | E77: ='BOD-Cold & Amb.'!R50 -> GRADE A | F77: CFM | G77: ='BOD-Cold & Amb.'!AK50 -> 47000 | H77: AC Load | I77: ='BOD-Cold & Amb.'!AQ50 -> 159 | J77: Nos. | K77: 1 | L77: =Q77 -> 2179000 | M77: =K77*L77 -> 2179000 | Q77: =CEILING((S77+T77+U77+V77+W77),250) -> 2179000 | R77: =IF(I77>0,625,375) -> 625 | S77: =(E78*G78*3*10.76+E78*I78*2*10.76+G78*I78*2*10.76)*R77/(1000*1000) -> 1006060 | T77: =I77*4*1050 -> 667800 | U77: =IF(G77<=2000,5000,(IF(G77<=5000,8000,(IF(G77<=10000,10000,(IF(G77<=18000,15000,(IF(G77<=40000,20000,25000))))))))) -> 25000 | V77: =IF(X77=200,17150,(IF(X77=225,18150,(IF(X77=250,18900,(IF(X77=280,19150,(IF(X77=315,19650,(IF(X77=355,21900,(IF(X77=400,24400,0)))))))))))))+IF(X77=450,31000,(IF(X77=500,37450,(IF(X77=560,45650,(IF(X77=630,58900,(IF(X77=710,77950,0)))))))))+IF(X77=800,119650,(IF(X77=900,153300,(IF(X77=1000,178900,(IF(X77=1120,286500,(IF(X77=1250,394500,(IF(X77=1450,461500,0))))))))))) -> 0 | W77: =IF(I79=0.5,16600,(IF(I79=1,19050,(IF(I79=1.5,21750,(IF(I79=2,23600,(IF(I79=3,30000,(IF(I79=5,38000,0)))))))))))*1.2+IF(I79=7.5,52300,(IF(I79=10,59600,0)))*1.2+IF(I79=12.5,100350,(IF(I79=15,106000,(IF(I79=20,129150,(IF(I79=25,146050,(IF(I79=30,173600,(IF(I79=40,233900,(IF(I79=50,304650,IF(I79=60,350000,400000)))))))))))))*1.2) -> 480000 | X77: =E79 -> 1200 | Y77: =IF(G77<=6750,450,(IF(G77<=8500,500,(IF(G77<=10750,560,(IF(G77<=13500,630,(IF(G77<=17000,710,(IF(G77<=21500,800,(IF(G77<=27000,900,(IF(G77<=34000,1000,0))))))))))))))) -> 0 | Z77: =IF(G77<=1300,200,(IF(G77<=1600,225,(IF(G77<=2100,250,(IF(G77<=2700,280,(IF(G77<=3450,315,(IF(G77<=4250,355,(IF(G77<=5250,400,(IF(G77<=6750,450,0))))))))))))))) -> 0 | AA77: =IF(G77<=2000,5000,(IF(G77<=5000,8000,(IF(G77<=10000,10000,(IF(G77<=18000,15000,(IF(G77<=40000,20000,10000))))))))) -> 10000 | AB77: =IF(E78=950,2,(IF(E78=1150,3,(IF(E78=1550,4,(IF(E78=1750,5,(IF(E78=2050,6,(IF(E78=2900,8,(IF(E78=3600,10,12))))))))))))) -> 12 | AC77: =IF(G78=950,2,(IF(G78=1150,3,(IF(G78=1550,4,(IF(G78=1750,5,(IF(G78=2050,6,(IF(G78=2900,8,(IF(G78=3600,10,12))))))))))))) -> 10 | AD77: =AC77*AB77 -> 120 | AE77: 150 | AF77: =CEILING((SQRT(G77/1000))*4*2*AE77*1.25*K77,100) -> 10300 | AG77: =E85*F85*H85/(305*305) -> 0 | AH77: =E86*F86*H86/(305*305) -> 36 | AI77: =H87*E87*F87/(305*305) -> 36 | AJ77: =H88*E88*F88/(305*305) -> 36 | AK77: =H89*E89*F89/(305*305) -> 36 | AM77: =(G77*2.2/1100) -> 94 | AN77: =(G77*1/1100) -> 42.727273
D78: AHU(W) | E78: ='BOD-Cold & Amb.'!AL51 -> 4000 | F78: AHU(H) | G78: ='BOD-Cold & Amb.'!AL53 -> 3600 | H78: AHU(L) | I78: ='BOD-Cold & Amb.'!AL55 -> 7000
D79: Blower | E79: ='BOD-Cold & Amb.'!AN50 -> 1200 | F79: Static Pr | G79: ='BOD-Cold & Amb.'!AM50 -> 150 | H79: Motor Hp | I79: ='BOD-Cold & Amb.'!AO50 -> 75
D80: Coil Rows | E80: ='BOD-Cold & Amb.'!AP50 -> 6 | F80: Coil Head Type | G80: =IF(OR(I77=0, E80="Amb"), "Amb",IF('BOD-Cold & Amb.'!AH40="C", "Header",IF('BOD-Cold & Amb.'!AH40="D", "Distributor", "Refer"))) -> Header | H80: Coil Size hxw in mm | I80: =IF(OR(I77=0, E80=0), 0,ROUND(((( I77/E80)*304.8)/(E78-400))*1000,0)&" h "&" x " & (E78-400)&" w ") -> 2244 h x 3600 w
D81: No. of Filtr. Stages | E81: ='BOD-Cold & Amb.'!AR50 -> 4 | F81: Filter Ratings | G81: =IF(E81=4,"10µ, 5µ, 1µ & 0.3µ (HEPA Plenum Fitted 95% eff.)",IF(E81=3,"10µ, 5µ & 1µ ",IF(E81=2,"10µ & 5µ",IF(E81=1,"10µ", "Filter Ratings")))) -> 10µ, 5µ, 1µ & 0.3µ (HEPA Plenum Fitted 95% eff.)
D82: Filters Size and Quantity for mentioned ratings
D83: Filter Rating | E83: Width mm | F83: Height mm | G83: Depth mm | H83: Filter Qty Nos
E84: =IF(E78<=950,2,(IF(E78<=1150,3,(IF(E78<=1550,4,(IF(E78<=1750,5,(IF(E78<=2050,6,(IF(E78<=2900,8,(IF(E78<=3600,10,IF(E78<=4000,12,0)))))))))))))) -> 12 | F84: =IF(G78<=950,2,(IF(G78<=1150,3,(IF(G78<=1550,4,(IF(G78<=1750,5,(IF(G78<=2050,6,(IF(G78<=2900,8,(IF(G78<=3600,10,IF(E78<=4000,12,0)))))))))))))) -> 10
D85: =IF(AND(I77=0, OR(E81=1, E81=2, E81=3, E81=4, E81=5)), "20µ", 0) -> 0 | E85: =IF(OR(D85=0),0,IF(MOD($E$42*$F$42,2)=0,"610",IF(MOD($E$42*$F$42,2.5)=0,"760",IF(MOD($E$42*$F$42,3)=0,"915","Refer")))) -> 0 | F85: =IF(OR(D85=0),0,IF(MOD($E$42*$F$42,6)=0,"915",IF(MOD($E$42*$F$42,5)=0,"760",IF(MOD($E$42*$F$42,4)=0,"610","Refer")))) -> 0 | G85: =IF(D85=0,0,100) -> 0 | H85: =IF(D85=0,0,($E$42*$F$42*305*305)/(E85*F85)) -> 0
D86: =IF(E81=4,"10µ",IF(E81=3,"10µ",IF(E81=2,"10µ",IF(E81=1,"10µ",0)))) -> 10µ | E86: =IF(OR(D86=0),0,IF(MOD($E$42*$F$42,2)=0,"610",IF(MOD($E$42*$F$42,2.5)=0,"760",IF(MOD($E$42*$F$42,3)=0,"915","Refer")))) -> 610 | F86: =IF(OR(D86=0),0,IF(MOD($E$42*$F$42,6)=0,"915",IF(MOD($E$42*$F$42,5)=0,"760",IF(MOD($E$42*$F$42,4)=0,"610","Refer")))) -> 915 | G86: =IF(D86=0,0,150) -> 150 | H86: =IF(D86=0,0,($E$42*$F$42*305*305)/(E86*F86)) -> 6
D87: =IF(E81=4,"5µ",IF(E81=3,"5µ",IF(E81=2,"5µ",0))) -> 5µ | E87: =IF(OR(D87=0),0,IF(MOD($E$42*$F$42,2)=0,"610",IF(MOD($E$42*$F$42,2.5)=0,"760",IF(MOD($E$42*$F$42,3)=0,"915","Refer")))) -> 610 | F87: =IF(OR(D87=0),0,IF(MOD($E$42*$F$42,6)=0,"915",IF(MOD($E$42*$F$42,5)=0,"760",IF(MOD($E$42*$F$42,4)=0,"610","Refer")))) -> 915 | G87: =IF(D87=0,0,300) -> 300 | H87: =IF(D87=0,0,($E$42*$F$42*305*305)/(E87*F87)) -> 6
D88: =IF(E81=4,"1µ",IF(E81=3,"1µ",0)) -> 1µ | E88: =IF(OR(D88=0),0,IF(MOD($E$42*$F$42,2)=0,"610",IF(MOD($E$42*$F$42,2.5)=0,"760",IF(MOD($E$42*$F$42,3)=0,"915","Refer")))) -> 610 | F88: =IF(OR(D88=0),0,IF(MOD($E$42*$F$42,6)=0,"915",IF(MOD($E$42*$F$42,5)=0,"760",IF(MOD($E$42*$F$42,4)=0,"610","Refer")))) -> 915 | G88: =IF(D88=0,0,300) -> 300 | H88: =IF(D88=0,0,($E$42*$F$42*305*305)/(E88*F88)) -> 6
D89: =IF(E81=4,"0.3µ 95% Eff. HEPA Filetr",0) -> 0.3µ 95% Eff. HEPA Filetr | E89: =IF(OR(D89=0),0,IF(MOD($E$42*$F$42,2)=0,"610",IF(MOD($E$42*$F$42,2.5)=0,"760",IF(MOD($E$42*$F$42,3)=0,"915","Refer")))) -> 610 | F89: =IF(OR(D89=0),0,IF(MOD($E$42*$F$42,6)=0,"915",IF(MOD($E$42*$F$42,5)=0,"760",IF(MOD($E$42*$F$42,4)=0,"610","Refer")))) -> 915 | G89: =IF(D89=0,0,300) -> 300 | H89: =IF(D89=0,0,($E$42*$F$42*305*305)/(E89*F89)) -> 6
D91: ="AHU - " & INT((ROW()-34)/14)+1 & " " & IF(I92>0,"Air-Conditioning System " & IF(OR(G95="Header", G95="C"), "(Chilled Water)",IF(OR(G95="Distributor", G95="D"), "(DX)", "Ventilation System")),IF(NOT(I92>0), "Ventilation System ( SUPPLY )", "Refer")) -> AHU - 5 Air-Conditioning System (DX)
D92: CLASS | E92: ='BOD-Cold & Amb.'!R70 -> 10K | F92: CFM | G92: ='BOD-Cold & Amb.'!AK70 -> 36500 | H92: AC Load | I92: ='BOD-Cold & Amb.'!AQ70 -> 94 | J92: Nos. | K92: 1 | L92: =Q92 -> 1784750 | M92: =K92*L92 -> 1784750 | Q92: =CEILING((S92+T92+U92+V92+W92),250) -> 1784750 | R92: =IF(I92>0,625,375) -> 625 | S92: =(E93*G93*3*10.76+E93*I93*2*10.76+G93*I93*2*10.76)*R92/(1000*1000) -> 717692 | T92: =I92*4*1050 -> 394800 | U92: =IF(G92<=2000,5000,(IF(G92<=5000,8000,(IF(G92<=10000,10000,(IF(G92<=18000,15000,(IF(G92<=40000,20000,25000))))))))) -> 20000 | V92: =IF(X92=200,17150,(IF(X92=225,18150,(IF(X92=250,18900,(IF(X92=280,19150,(IF(X92=315,19650,(IF(X92=355,21900,(IF(X92=400,24400,0)))))))))))))+IF(X92=450,31000,(IF(X92=500,37450,(IF(X92=560,45650,(IF(X92=630,58900,(IF(X92=710,77950,0)))))))))+IF(X92=800,119650,(IF(X92=900,153300,(IF(X92=1000,178900,(IF(X92=1120,286500,(IF(X92=1250,394500,(IF(X92=1450,461500,0))))))))))) -> 286500 | W92: =IF(I94=0.5,16600,(IF(I94=1,19050,(IF(I94=1.5,21750,(IF(I94=2,23600,(IF(I94=3,30000,(IF(I94=5,38000,0)))))))))))*1.2+IF(I94=7.5,52300,(IF(I94=10,59600,0)))*1.2+IF(I94=12.5,100350,(IF(I94=15,106000,(IF(I94=20,129150,(IF(I94=25,146050,(IF(I94=30,173600,(IF(I94=40,233900,(IF(I94=50,304650,IF(I94=60,350000,400000)))))))))))))*1.2) -> 365580 | X92: =E94 -> 1120 | Y92: =IF(G92<=6750,450,(IF(G92<=8500,500,(IF(G92<=10750,560,(IF(G92<=13500,630,(IF(G92<=17000,710,(IF(G92<=21500,800,(IF(G92<=27000,900,(IF(G92<=34000,1000,0))))))))))))))) -> 0 | Z92: =IF(G92<=1300,200,(IF(G92<=1600,225,(IF(G92<=2100,250,(IF(G92<=2700,280,(IF(G92<=3450,315,(IF(G92<=4250,355,(IF(G92<=5250,400,(IF(G92<=6750,450,0))))))))))))))) -> 0 | AA92: =IF(G92<=2000,5000,(IF(G92<=5000,8000,(IF(G92<=10000,10000,(IF(G92<=18000,15000,(IF(G92<=40000,20000,10000))))))))) -> 20000 | AB92: =IF(E93=950,2,(IF(E93=1150,3,(IF(E93=1550,4,(IF(E93=1750,5,(IF(E93=2050,6,(IF(E93=2900,8,(IF(E93=3600,10,12))))))))))))) -> 10 | AC92: =IF(G93=950,2,(IF(G93=1150,3,(IF(G93=1550,4,(IF(G93=1750,5,(IF(G93=2050,6,(IF(G93=2900,8,(IF(G93=3600,10,12))))))))))))) -> 8 | AD92: =AC92*AB92 -> 80 | AE92: 150 | AF92: =CEILING((SQRT(G92/1000))*4*2*AE92*1.25*K92,100) -> 9100 | AG92: =E100*F100*H100/(305*305) -> 0 | AH92: =E101*F101*H101/(305*305) -> 36 | AI92: =H102*E102*F102/(305*305) -> 36 | AJ92: =H103*E103*F103/(305*305) -> 36 | AK92: =H104*E104*F104/(305*305) -> 0 | AM92: =(G92*2.2/1100) -> 73 | AN92: =(G92*1/1100) -> 33.181818
D93: AHU(W) | E93: ='BOD-Cold & Amb.'!AL71 -> 3600 | F93: AHU(H) | G93: ='BOD-Cold & Amb.'!AL73 -> 2900 | H93: AHU(L) | I93: ='BOD-Cold & Amb.'!AL75 -> 5800
D94: Blower | E94: ='BOD-Cold & Amb.'!AN70 -> 1120 | F94: Static Pr | G94: ='BOD-Cold & Amb.'!AM70 -> 150 | H94: Motor Hp | I94: ='BOD-Cold & Amb.'!AO70 -> 50
D95: Coil Rows | E95: ='BOD-Cold & Amb.'!AP70 -> 4 | F95: Coil Head Type | G95: =IF(OR(I92=0, E95="Amb"), "Amb",IF('BOD-Cold & Amb.'!AH55="C", "Header",IF('BOD-Cold & Amb.'!AH55="D", "Distributor", "Refer"))) -> Distributor | H95: Coil Size hxw in mm | I95: =IF(OR(I92=0, E95=0), 0,ROUND(((( I92/E95)*304.8)/(E93-400))*1000,0)&" h "&" x " & (E93-400)&" w ") -> 2238 h x 3200 w
D96: No. of Filtr. Stages | E96: ='BOD-Cold & Amb.'!AR70 -> 3 | F96: Filter Ratings | G96: =IF(E96=4,"10µ, 5µ, 1µ & 0.3µ (HEPA Plenum Fitted 95% eff.)",IF(E96=3,"10µ, 5µ & 1µ ",IF(E96=2,"10µ & 5µ",IF(E96=1,"10µ", "Filter Ratings")))) -> 10µ, 5µ & 1µ
D97: Filters Size and Quantity for mentioned ratings
D98: Filter Rating | E98: Width mm | F98: Height mm | G98: Depth mm | H98: Filter Qty Nos
E99: =IF(E93<=950,2,(IF(E93<=1150,3,(IF(E93<=1550,4,(IF(E93<=1750,5,(IF(E93<=2050,6,(IF(E93<=2900,8,(IF(E93<=3600,10,IF(E93<=4000,12,0)))))))))))))) -> 10 | F99: =IF(G93<=950,2,(IF(G93<=1150,3,(IF(G93<=1550,4,(IF(G93<=1750,5,(IF(G93<=2050,6,(IF(G93<=2900,8,(IF(G93<=3600,10,IF(E93<=4000,12,0)))))))))))))) -> 8
D100: =IF(AND(I92=0, OR(E96=1, E96=2, E96=3, E96=4, E96=5)), "20µ", 0) -> 0 | E100: =IF(OR(D100=0),0,IF(MOD($E$42*$F$42,2)=0,"610",IF(MOD($E$42*$F$42,2.5)=0,"760",IF(MOD($E$42*$F$42,3)=0,"915","Refer")))) -> 0 | F100: =IF(OR(D100=0),0,IF(MOD($E$42*$F$42,6)=0,"915",IF(MOD($E$42*$F$42,5)=0,"760",IF(MOD($E$42*$F$42,4)=0,"610","Refer")))) -> 0 | G100: =IF(D100=0,0,100) -> 0 | H100: =IF(D100=0,0,($E$42*$F$42*305*305)/(E100*F100)) -> 0
D101: =IF(E96=4,"10µ",IF(E96=3,"10µ",IF(E96=2,"10µ",IF(E96=1,"10µ",0)))) -> 10µ | E101: =IF(OR(D101=0),0,IF(MOD($E$42*$F$42,2)=0,"610",IF(MOD($E$42*$F$42,2.5)=0,"760",IF(MOD($E$42*$F$42,3)=0,"915","Refer")))) -> 610 | F101: =IF(OR(D101=0),0,IF(MOD($E$42*$F$42,6)=0,"915",IF(MOD($E$42*$F$42,5)=0,"760",IF(MOD($E$42*$F$42,4)=0,"610","Refer")))) -> 915 | G101: =IF(D101=0,0,150) -> 150 | H101: =IF(D101=0,0,($E$42*$F$42*305*305)/(E101*F101)) -> 6
D102: =IF(E96=4,"5µ",IF(E96=3,"5µ",IF(E96=2,"5µ",0))) -> 5µ | E102: =IF(OR(D102=0),0,IF(MOD($E$42*$F$42,2)=0,"610",IF(MOD($E$42*$F$42,2.5)=0,"760",IF(MOD($E$42*$F$42,3)=0,"915","Refer")))) -> 610 | F102: =IF(OR(D102=0),0,IF(MOD($E$42*$F$42,6)=0,"915",IF(MOD($E$42*$F$42,5)=0,"760",IF(MOD($E$42*$F$42,4)=0,"610","Refer")))) -> 915 | G102: =IF(D102=0,0,300) -> 300 | H102: =IF(D102=0,0,($E$42*$F$42*305*305)/(E102*F102)) -> 6
D103: =IF(E96=4,"1µ",IF(E96=3,"1µ",0)) -> 1µ | E103: =IF(OR(D103=0),0,IF(MOD($E$42*$F$42,2)=0,"610",IF(MOD($E$42*$F$42,2.5)=0,"760",IF(MOD($E$42*$F$42,3)=0,"915","Refer")))) -> 610 | F103: =IF(OR(D103=0),0,IF(MOD($E$42*$F$42,6)=0,"915",IF(MOD($E$42*$F$42,5)=0,"760",IF(MOD($E$42*$F$42,4)=0,"610","Refer")))) -> 915 | G103: =IF(D103=0,0,300) -> 300 | H103: =IF(D103=0,0,($E$42*$F$42*305*305)/(E103*F103)) -> 6
D104: =IF(E96=4,"0.3µ 95% Eff. HEPA Filetr",0) -> 0 | E104: =IF(OR(D104=0),0,IF(MOD($E$42*$F$42,2)=0,"610",IF(MOD($E$42*$F$42,2.5)=0,"760",IF(MOD($E$42*$F$42,3)=0,"915","Refer")))) -> 0 | F104: =IF(OR(D104=0),0,IF(MOD($E$42*$F$42,6)=0,"915",IF(MOD($E$42*$F$42,5)=0,"760",IF(MOD($E$42*$F$42,4)=0,"610","Refer")))) -> 0 | G104: =IF(D104=0,0,300) -> 0 | H104: =IF(D104=0,0,($E$42*$F$42*305*305)/(E104*F104)) -> 0
D106: ="AHU - " & INT((ROW()-34)/14)+1 & " " & IF(I107>0,"Air-Conditioning System " & IF(OR(G110="Header", G110="C"), "(Chilled Water)",IF(OR(G110="Distributor", G110="D"), "(DX)", "Ventilation System")),IF(NOT(I107>0), "Ventilation System ( SUPPLY )", "Refer")) -> AHU - 6 Air-Conditioning System (Chilled Water)
